Workbook

Sheet Synthèse
B2: B Â T I - S U D · G R O U P E A R T I S A N A L
B3: Rapport de pilotage — synthèse | K3: Bâti-Sud
B4: Niveau strategique · exercice 2025-2026 (01/07/2025 → 30/06/2026)
B7: CHIFFRE D'AFFAIRES PAR TECHNICIEN | E7: TAUX DE MARGE BRUTE | H7: CONCENTRATION DU CHIFFRE D'AFFAIRES | K7: DSO — DÉLAI MOYEN D'ENCAISSEMENT
B8: =IFERROR(SUMIFS(Interventions!$R$2:$R$1106,Interventions!$C$2:$C$1106,">="&Paramètres!$C$9,Interventions!$C$2:$C$1106,"<="&Paramètres!$C$10)/SUMIFS(Interventions!$V$2:$V$1106,Interventions!$C$2:$C$1106,">="&Paramètres!$C$9,Interventions!$C$2:$C$1106,"<="&Paramètres!$C$10),"") | E8: =IFERROR(SUMIFS(Factures!$V$2:$V$1085,Factures!$F$2:$F$1085,">="&Paramètres!$C$9,Factures!$F$2:$F$1085,"<="&Paramètres!$C$10)/SUMIFS(Factures!$K$2:$K$1085,Factures!$F$2:$F$1085,">="&Paramètres!$C$9,Factures!$F$2:$F$1085,"<="&Paramètres!$C$10),"") | H8: =IFERROR(SUMIF(Clients!$J$2:$J$1020,">="&LARGE(Clients!$J$2:$J$1020,MAX(1,ROUND(COUNTIF(Clients!$J$2:$J$1020,">0")*0.1,0))))/SUM(Clients!$J$2:$J$1020),"") | K8: =IFERROR(365.0*(SUMIFS(Factures!$X$2:$X$1085,Factures!$F$2:$F$1085,">="&Paramètres!$C$9,Factures!$F$2:$F$1085,"<="&Paramètres!$C$10)/SUMIFS(Factures!$M$2:$M$1085,Factures!$F$2:$F$1085,">="&Paramètres!$C$9,Factures!$F$2:$F$1085,"<="&Paramètres!$C$10)),"")
B9: =IFERROR((IFERROR(SUMIFS(Interventions!$R$2:$R$1106,Interventions!$C$2:$C$1106,">="&Paramètres!$C$9,Interventions!$C$2:$C$1106,"<="&Paramètres!$C$10)/SUMIFS(Interventions!$V$2:$V$1106,Interventions!$C$2:$C$1106,">="&Paramètres!$C$9,Interventions!$C$2:$C$1106,"<="&Paramètres!$C$10),""))/(IFERROR(SUMIFS(Interventions!$R$2:$R$1106,Interventions!$C$2:$C$1106,">="&Paramètres!$C$11,Interventions!$C$2:$C$1106,"<="&Paramètres!$C$12)/SUMIFS(Interventions!$W$2:$W$1106,Interventions!$C$2:$C$1106,">="&Paramètres!$C$11,Interventions!$C$2:$C$1106,"<="&Paramètres!$C$12),""))-1,"") | E9: =IFERROR((IFERROR(SUMIFS(Factures!$V$2:$V$1085,Factures!$F$2:$F$1085,">="&Paramètres!$C$9,Factures!$F$2:$F$1085,"<="&Paramètres!$C$10)/SUMIFS(Factures!$K$2:$K$1085,Factures!$F$2:$F$1085,">="&Paramètres!$C$9,Factures!$F$2:$F$1085,"<="&Paramètres!$C$10),""))/(IFERROR(SUMIFS(Factures!$V$2:$V$1085,Factures!$F$2:$F$1085,">="&Paramètres!$C$11,Factures!$F$2:$F$1085,"<="&Paramètres!$C$12)/SUMIFS(Factures!$K$2:$K$1085,Factures!$F$2:$F$1085,">="&Paramètres!$C$11,Factures!$F$2:$F$1085,"<="&Paramètres!$C$12),""))-1,"") | H9: =IFERROR((IFERROR(SUMIF(Clients!$J$2:$J$1020,">="&LARGE(Clients!$J$2:$J$1020,MAX(1,ROUND(COUNTIF(Clients!$J$2:$J$1020,">0")*0.1,0))))/SUM(Clients!$J$2:$J$1020),""))/(IFERROR(SUMIF(Clients!$K$2:$K$1020,">="&LARGE(Clients!$K$2:$K$1020,MAX(1,ROUND(COUNTIF(Clients!$K$2:$K$1020,">0")*0.1,0))))/SUM(Clients!$K$2:$K$1020),""))-1,"") | K9: état à la date de situation
B11: TAUX DE TRANSFORMATION DES DEVIS · PAR AGENCE | E11: PANIER MOYEN D'UN DEVIS GAGNÉ · PAR TYPE DE CLIENT
B12: =IFERROR(SUMIFS(Devis!$X$2:$X$3053,Devis!$B$2:$B$3053,">="&Paramètres!$C$9,Devis!$B$2:$B$3053,"<="&Paramètres!$C$10)/SUMIFS(Devis!$Y$2:$Y$3053,Devis!$B$2:$B$3053,">="&Paramètres!$C$9,Devis!$B$2:$B$3053,"<="&Paramètres!$C$10),"") | E12: =IFERROR(SUMIFS(Devis!$X$2:$X$3053,Devis!$B$2:$B$3053,">="&Paramètres!$C$9,Devis!$B$2:$B$3053,"<="&Paramètres!$C$10)/SUMIFS(Devis!$W$2:$W$3053,Devis!$B$2:$B$3053,">="&Paramètres!$C$9,Devis!$B$2:$B$3053,"<="&Paramètres!$C$10),"")
B13: =IFERROR((IFERROR(SUMIFS(Devis!$X$2:$X$3053,Devis!$B$2:$B$3053,">="&Paramètres!$C$9,Devis!$B$2:$B$3053,"<="&Paramètres!$C$10)/SUMIFS(Devis!$Y$2:$Y$3053,Devis!$B$2:$B$3053,">="&Paramètres!$C$9,Devis!$B$2:$B$3053,"<="&Paramètres!$C$10),""))/(IFERROR(SUMIFS(Devis!$X$2:$X$3053,Devis!$B$2:$B$3053,">="&Paramètres!$C$11,Devis!$B$2:$B$3053,"<="&Paramètres!$C$12)/SUMIFS(Devis!$Y$2:$Y$3053,Devis!$B$2:$B$3053,">="&Paramètres!$C$11,Devis!$B$2:$B$3053,"<="&Paramètres!$C$12),""))-1,"") | E13: =IFERROR((IFERROR(SUMIFS(Devis!$X$2:$X$3053,Devis!$B$2:$B$3053,">="&Paramètres!$C$9,Devis!$B$2:$B$3053,"<="&Paramètres!$C$10)/SUMIFS(Devis!$W$2:$W$3053,Devis!$B$2:$B$3053,">="&Paramètres!$C$9,Devis!$B$2:$B$3053,"<="&Paramètres!$C$10),""))/(IFERROR(SUMIFS(Devis!$X$2:$X$3053,Devis!$B$2:$B$3053,">="&Paramètres!$C$11,Devis!$B$2:$B$3053,"<="&Paramètres!$C$12)/SUMIFS(Devis!$W$2:$W$3053,Devis!$B$2:$B$3053,">="&Paramètres!$C$11,Devis!$B$2:$B$3053,"<="&Paramètres!$C$12),""))-1,"")
B14: Ligne du haut : socle imposé, comparable d'une édition à l'autre. Ligne du bas : indicateurs retenus pour cette période.
B16: Chiffre d'affaires facturé et taux de marge
B35: Décomposition de l'écart de chiffre d'affaires
B36: Métier | C36: Affaires N-1 | D36: Panier N-1 | E36: Affaires N | F36: Panier N
B37: Chauffage | C37: =COUNTIFS(Factures!$F$2:$F$1085,">="&Paramètres!$C$11,Factures!$F$2:$F$1085,"<="&Paramètres!$C$12,Factures!$Q$2:$Q$1085,$B37) | D37: =IFERROR(SUMIFS(Factures!$K$2:$K$1085,Factures!$F$2:$F$1085,">="&Paramètres!$C$11,Factures!$F$2:$F$1085,"<="&Paramètres!$C$12,Factures!$Q$2:$Q$1085,$B37)/$C37,0) | E37: =COUNTIFS(Factures!$F$2:$F$1085,">="&Paramètres!$C$9,Factures!$F$2:$F$1085,"<="&Paramètres!$C$10,Factures!$Q$2:$Q$1085,$B37) | F37: =IFERROR(SUMIFS(Factures!$K$2:$K$1085,Factures!$F$2:$F$1085,">="&Paramètres!$C$9,Factures!$F$2:$F$1085,"<="&Paramètres!$C$10,Factures!$Q$2:$Q$1085,$B37)/$E37,0)
B38: Dépannage | C38: =COUNTIFS(Factures!$F$2:$F$1085,">="&Paramètres!$C$11,Factures!$F$2:$F$1085,"<="&Paramètres!$C$12,Factures!$Q$2:$Q$1085,$B38) | D38: =IFERROR(SUMIFS(Factures!$K$2:$K$1085,Factures!$F$2:$F$1085,">="&Paramètres!$C$11,Factures!$F$2:$F$1085,"<="&Paramètres!$C$12,Factures!$Q$2:$Q$1085,$B38)/$C38,0) | E38: =COUNTIFS(Factures!$F$2:$F$1085,">="&Paramètres!$C$9,Factures!$F$2:$F$1085,"<="&Paramètres!$C$10,Factures!$Q$2:$Q$1085,$B38) | F38: =IFERROR(SUMIFS(Factures!$K$2:$K$1085,Factures!$F$2:$F$1085,">="&Paramètres!$C$9,Factures!$F$2:$F$1085,"<="&Paramètres!$C$10,Factures!$Q$2:$Q$1085,$B38)/$E38,0)
B39: Plomberie | C39: =COUNTIFS(Factures!$F$2:$F$1085,">="&Paramètres!$C$11,Factures!$F$2:$F$1085,"<="&Paramètres!$C$12,Factures!$Q$2:$Q$1085,$B39) | D39: =IFERROR(SUMIFS(Factures!$K$2:$K$1085,Factures!$F$2:$F$1085,">="&Paramètres!$C$11,Factures!$F$2:$F$1085,"<="&Paramètres!$C$12,Factures!$Q$2:$Q$1085,$B39)/$C39,0) | E39: =COUNTIFS(Factures!$F$2:$F$1085,">="&Paramètres!$C$9,Factures!$F$2:$F$1085,"<="&Paramètres!$C$10,Factures!$Q$2:$Q$1085,$B39) | F39: =IFERROR(SUMIFS(Factures!$K$2:$K$1085,Factures!$F$2:$F$1085,">="&Paramètres!$C$9,Factures!$F$2:$F$1085,"<="&Paramètres!$C$10,Factures!$Q$2:$Q$1085,$B39)/$E39,0)
B40: Salle de bain | C40: =COUNTIFS(Factures!$F$2:$F$1085,">="&Paramètres!$C$11,Factures!$F$2:$F$1085,"<="&Paramètres!$C$12,Factures!$Q$2:$Q$1085,$B40) | D40: =IFERROR(SUMIFS(Factures!$K$2:$K$1085,Factures!$F$2:$F$1085,">="&Paramètres!$C$11,Factures!$F$2:$F$1085,"<="&Paramètres!$C$12,Factures!$Q$2:$Q$1085,$B40)/$C40,0) | E40: =COUNTIFS(Factures!$F$2:$F$1085,">="&Paramètres!$C$9,Factures!$F$2:$F$1085,"<="&Paramètres!$C$10,Factures!$Q$2:$Q$1085,$B40) | F40: =IFERROR(SUMIFS(Factures!$K$2:$K$1085,Factures!$F$2:$F$1085,">="&Paramètres!$C$9,Factures!$F$2:$F$1085,"<="&Paramètres!$C$10,Factures!$Q$2:$Q$1085,$B40)/$E40,0)
B41: Électricité | C41: =COUNTIFS(Factures!$F$2:$F$1085,">="&Paramètres!$C$11,Factures!$F$2:$F$1085,"<="&Paramètres!$C$12,Factures!$Q$2:$Q$1085,$B41) | D41: =IFERROR(SUMIFS(Factures!$K$2:$K$1085,Factures!$F$2:$F$1085,">="&Paramètres!$C$11,Factures!$F$2:$F$1085,"<="&Paramètres!$C$12,Factures!$Q$2:$Q$1085,$B41)/$C41,0) | E41: =COUNTIFS(Factures!$F$2:$F$1085,">="&Paramètres!$C$9,Factures!$F$2:$F$1085,"<="&Paramètres!$C$10,Factures!$Q$2:$Q$1085,$B41) | F41: =IFERROR(SUMIFS(Factures!$K$2:$K$1085,Factures!$F$2:$F$1085,">="&Paramètres!$C$9,Factures!$F$2:$F$1085,"<="&Paramètres!$C$10,Factures!$Q$2:$Q$1085,$B41)/$E41,0)
B42: Ensemble | C42: =SUM($C37:$C41) | D42: =IFERROR(SUMPRODUCT($C37:$C41,$D37:$D41)/$C42,0) | E42: =SUM($E37:$E41) | F42: =IFERROR(SUMPRODUCT($E37:$E41,$F37:$F41)/$E42,0)
B44: Ponts d'écart
B45: Effet | C45: Montant | D45: Lecture
B46: Volume | C46: =($E42-$C42)*$D42 | D46: Davantage d'affaires, au panier moyen de l'an dernier.
B47: Mix | C47: =IFERROR($E42*(SUMPRODUCT($E37:$E41,$D37:$D41)/$E42-$D42),0) | D47: Déformation de la répartition entre métiers, à prix constants.
B48: Prix | C48: =IFERROR($E42*($F42-SUMPRODUCT($E37:$E41,$D37:$D41)/$E42),0) | D48: Variation du panier à structure constante.
B49: Écart total | C49: =SUM($C46:$C48) | D49: Égal, par construction, à la variation du chiffre d'affaires facturé.
B51: Pont commercial — devis gagnés
B52: Effet | C52: Montant | D52: Lecture
B53: Volume devisé | C53: =IFERROR((SUMIFS(Devis!$Y$2:$Y$3053,Devis!$B$2:$B$3053,">="&Paramètres!$C$9,Devis!$B$2:$B$3053,"<="&Paramètres!$C$10)-SUMIFS(Devis!$Y$2:$Y$3053,Devis!$B$2:$B$3053,">="&Paramètres!$C$11,Devis!$B$2:$B$3053,"<="&Paramètres!$C$12))*(SUMIFS(Devis!$X$2:$X$3053,Devis!$B$2:$B$3053,">="&Paramètres!$C$11,Devis!$B$2:$B$3053,"<="&Paramètres!$C$12))/(SUMIFS(Devis!$Y$2:$Y$3053,Devis!$B$2:$B$3053,">="&Paramètres!$C$11,Devis!$B$2:$B$3053,"<="&Paramètres!$C$12)),0) | D53: Effet du volume de devis émis, à taux de transformation constant.
B54: Transformation | C54: =IFERROR((SUMIFS(Devis!$Y$2:$Y$3053,Devis!$B$2:$B$3053,">="&Paramètres!$C$9,Devis!$B$2:$B$3053,"<="&Paramètres!$C$10))*((SUMIFS(Devis!$X$2:$X$3053,Devis!$B$2:$B$3053,">="&Paramètres!$C$9,Devis!$B$2:$B$3053,"<="&Paramètres!$C$10))/(SUMIFS(Devis!$Y$2:$Y$3053,Devis!$B$2:$B$3053,">="&Paramètres!$C$9,Devis!$B$2:$B$3053,"<="&Paramètres!$C$10))-(SUMIFS(Devis!$X$2:$X$3053,Devis!$B$2:$B$3053,">="&Paramètres!$C$11,Devis!$B$2:$B$3053,"<="&Paramètres!$C$12))/(SUMIFS(Devis!$Y$2:$Y$3053,Devis!$B$2:$B$3053,">="&Paramètres!$C$11,Devis!$B$2:$B$3053,"<="&Paramètres!$C$12))),0) | D54: Effet du taux de transformation, à volume constant.
B55: Écart total | C55: =SUM($C53:$C54) | D55: Égal à la variation du chiffre d'affaires gagné sur devis.
B57: Points d'attention
B58: La trajectoire est celle d'une entreprise qui produit davantage mais dont la profitabilité et l'encaissement se dégradient — l'effort commercial doit se concentrer sur les zones de conversion faible et la politique tarifaire doit être revue sur le segment dominant.
B59: Taux de transformation des devis — Revoir le dispositif commercial de l'agence la plus faible, en s'inspirant de l'agence de tête, et fixer un plan de retour à la moyenne.
B60: Panier moyen d'un devis gagné — Repréciser la grille tarifaire et les propositions d'options sur le segment Particulier pour remonter le panier moyen.
B61: Écartée — Le taux de marge brute sur les Particuliers est structurellement plus faible que sur les autres clientèles. : L'écart existe mais la mesure de marge brute est déjà couverte par le socle imposé, doublonner ferait perdre en lisibilité.
B62: Écartée — Le taux de transformation sur Chauffage est dégradé et pèse sur l'ensemble de l'activité. : L'écart est réel mais la Plomberie présente un niveau équivalent : aucun coupable métier isolé, donc aucune décision ciblée possible.
B63: Écartée — Un effet combiné métier × agence existe sur la marge de la Salle de bain. : Le croisement ne révèle aucune cellule Sala de bain × agence suffisamment peuplée et distinctive : l'hypothèse n'est pas démontrable.
B64: Écartée — Le DSO dégradé provient du canal Site web, sur lequel le dirigeant peut agir. : Confirmée mais la mesure DSO est déjà dans le socle imposé : pas un indicateur à choisir.

Sheet Indicateurs
B2: B Â T I - S U D · G R O U P E A R T I S A N A L
B3: Indicateurs retenus | I3: Détail
B4: Un bloc par indicateur : ventilation, comparaison et décision attendue.
B7: Taux de transformation des devis par agence
B8: L'écart entre agences est massif et stable, avec une agence très en retrait qui n'est pas réductible à un effet de volume.
B9: Modalité | C9: Valeur | D9: Effectif | E9: Période précédente | F9: Écart | G9: Part du total
B10: Bordeaux | C10: =IFERROR(SUMIFS(Devis!$X$2:$X$3053,Devis!$B$2:$B$3053,">="&Paramètres!$C$9,Devis!$B$2:$B$3053,"<="&Paramètres!$C$10,Devis!$G$2:$G$3053,"Bordeaux")/SUMIFS(Devis!$Y$2:$Y$3053,Devis!$B$2:$B$3053,">="&Paramètres!$C$9,Devis!$B$2:$B$3053,"<="&Paramètres!$C$10,Devis!$G$2:$G$3053,"Bordeaux"),"") | D10: =COUNTIFS(Devis!$B$2:$B$3053,">="&Paramètres!$C$9,Devis!$B$2:$B$3053,"<="&Paramètres!$C$10,Devis!$G$2:$G$3053,"Bordeaux") | E10: =IFERROR(SUMIFS(Devis!$X$2:$X$3053,Devis!$B$2:$B$3053,">="&Paramètres!$C$11,Devis!$B$2:$B$3053,"<="&Paramètres!$C$12,Devis!$G$2:$G$3053,"Bordeaux")/SUMIFS(Devis!$Y$2:$Y$3053,Devis!$B$2:$B$3053,">="&Paramètres!$C$11,Devis!$B$2:$B$3053,"<="&Paramètres!$C$12,Devis!$G$2:$G$3053,"Bordeaux"),"") | F10: =IFERROR($C10/$E10-1,"") | G10: =IFERROR(SUMIFS(Devis!$X$2:$X$3053,Devis!$B$2:$B$3053,">="&Paramètres!$C$9,Devis!$B$2:$B$3053,"<="&Paramètres!$C$10,Devis!$G$2:$G$3053,"Bordeaux")/SUMIFS(Devis!$X$2:$X$3053,Devis!$B$2:$B$3053,">="&Paramètres!$C$9,Devis!$B$2:$B$3053,"<="&Paramètres!$C$10),"")
B11: Montpellier | C11: =IFERROR(SUMIFS(Devis!$X$2:$X$3053,Devis!$B$2:$B$3053,">="&Paramètres!$C$9,Devis!$B$2:$B$3053,"<="&Paramètres!$C$10,Devis!$G$2:$G$3053,"Montpellier")/SUMIFS(Devis!$Y$2:$Y$3053,Devis!$B$2:$B$3053,">="&Paramètres!$C$9,Devis!$B$2:$B$3053,"<="&Paramètres!$C$10,Devis!$G$2:$G$3053,"Montpellier"),"") | D11: =COUNTIFS(Devis!$B$2:$B$3053,">="&Paramètres!$C$9,Devis!$B$2:$B$3053,"<="&Paramètres!$C$10,Devis!$G$2:$G$3053,"Montpellier") | E11: =IFERROR(SUMIFS(Devis!$X$2:$X$3053,Devis!$B$2:$B$3053,">="&Paramètres!$C$11,Devis!$B$2:$B$3053,"<="&Paramètres!$C$12,Devis!$G$2:$G$3053,"Montpellier")/SUMIFS(Devis!$Y$2:$Y$3053,Devis!$B$2:$B$3053,">="&Paramètres!$C$11,Devis!$B$2:$B$3053,"<="&Paramètres!$C$12,Devis!$G$2:$G$3053,"Montpellier"),"") | F11: =IFERROR($C11/$E11-1,"") | G11: =IFERROR(SUMIFS(Devis!$X$2:$X$3053,Devis!$B$2:$B$3053,">="&Paramètres!$C$9,Devis!$B$2:$B$3053,"<="&Paramètres!$C$10,Devis!$G$2:$G$3053,"Montpellier")/SUMIFS(Devis!$X$2:$X$3053,Devis!$B$2:$B$3053,">="&Paramètres!$C$9,Devis!$B$2:$B$3053,"<="&Paramètres!$C$10),"")
B12: Toulouse | C12: =IFERROR(SUMIFS(Devis!$X$2:$X$3053,Devis!$B$2:$B$3053,">="&Paramètres!$C$9,Devis!$B$2:$B$3053,"<="&Paramètres!$C$10,Devis!$G$2:$G$3053,"Toulouse")/SUMIFS(Devis!$Y$2:$Y$3053,Devis!$B$2:$B$3053,">="&Paramètres!$C$9,Devis!$B$2:$B$3053,"<="&Paramètres!$C$10,Devis!$G$2:$G$3053,"Toulouse"),"") | D12: =COUNTIFS(Devis!$B$2:$B$3053,">="&Paramètres!$C$9,Devis!$B$2:$B$3053,"<="&Paramètres!$C$10,Devis!$G$2:$G$3053,"Toulouse") | E12: =IFERROR(SUMIFS(Devis!$X$2:$X$3053,Devis!$B$2:$B$3053,">="&Paramètres!$C$11,Devis!$B$2:$B$3053,"<="&Paramètres!$C$12,Devis!$G$2:$G$3053,"Toulouse")/SUMIFS(Devis!$Y$2:$Y$3053,Devis!$B$2:$B$3053,">="&Paramètres!$C$11,Devis!$B$2:$B$3053,"<="&Paramètres!$C$12,Devis!$G$2:$G$3053,"Toulouse"),"") | F12: =IFERROR($C12/$E12-1,"") | G12: =IFERROR(SUMIFS(Devis!$X$2:$X$3053,Devis!$B$2:$B$3053,">="&Paramètres!$C$9,Devis!$B$2:$B$3053,"<="&Paramètres!$C$10,Devis!$G$2:$G$3053,"Toulouse")/SUMIFS(Devis!$X$2:$X$3053,Devis!$B$2:$B$3053,">="&Paramètres!$C$9,Devis!$B$2:$B$3053,"<="&Paramètres!$C$10),"")
B13: Ensemble | C13: =IFERROR(SUMIFS(Devis!$X$2:$X$3053,Devis!$B$2:$B$3053,">="&Paramètres!$C$9,Devis!$B$2:$B$3053,"<="&Paramètres!$C$10)/SUMIFS(Devis!$Y$2:$Y$3053,Devis!$B$2:$B$3053,">="&Paramètres!$C$9,Devis!$B$2:$B$3053,"<="&Paramètres!$C$10),"") | D13: =COUNTIFS(Devis!$B$2:$B$3053,">="&Paramètres!$C$9,Devis!$B$2:$B$3053,"<="&Paramètres!$C$10) | E13: =IFERROR(SUMIFS(Devis!$X$2:$X$3053,Devis!$B$2:$B$3053,">="&Paramètres!$C$11,Devis!$B$2:$B$3053,"<="&Paramètres!$C$12)/SUMIFS(Devis!$Y$2:$Y$3053,Devis!$B$2:$B$3053,">="&Paramètres!$C$11,Devis!$B$2:$B$3053,"<="&Paramètres!$C$12),"") | F13: =IFERROR($C13/$E13-1,"") | G13: =1
B14: Décision attendue : Revoir le dispositif commercial de l'agence la plus faible, en s'inspirant de l'agence de tête, et fixer un plan de retour à la moyenne.
B23: Panier moyen d'un devis gagné par type de client
B24: Le segment dominant du portefeuille est nettement en deçà des autres clientèles, confirmant un manque à gagner matériel sur l'année.
B25: Modalité | C25: Valeur | D25: Effectif | E25: Période précédente | F25: Écart | G25: Part du total
B26: Collectivité | C26: =IFERROR(SUMIFS(Devis!$X$2:$X$3053,Devis!$B$2:$B$3053,">="&Paramètres!$C$9,Devis!$B$2:$B$3053,"<="&Paramètres!$C$10,Devis!$F$2:$F$3053,"Collectivité")/SUMIFS(Devis!$W$2:$W$3053,Devis!$B$2:$B$3053,">="&Paramètres!$C$9,Devis!$B$2:$B$3053,"<="&Paramètres!$C$10,Devis!$F$2:$F$3053,"Collectivité"),"") | D26: =COUNTIFS(Devis!$B$2:$B$3053,">="&Paramètres!$C$9,Devis!$B$2:$B$3053,"<="&Paramètres!$C$10,Devis!$F$2:$F$3053,"Collectivité") | E26: =IFERROR(SUMIFS(Devis!$X$2:$X$3053,Devis!$B$2:$B$3053,">="&Paramètres!$C$11,Devis!$B$2:$B$3053,"<="&Paramètres!$C$12,Devis!$F$2:$F$3053,"Collectivité")/SUMIFS(Devis!$W$2:$W$3053,Devis!$B$2:$B$3053,">="&Paramètres!$C$11,Devis!$B$2:$B$3053,"<="&Paramètres!$C$12,Devis!$F$2:$F$3053,"Collectivité"),"") | F26: =IFERROR($C26/$E26-1,"") | G26: =IFERROR(SUMIFS(Devis!$X$2:$X$3053,Devis!$B$2:$B$3053,">="&Paramètres!$C$9,Devis!$B$2:$B$3053,"<="&Paramètres!$C$10,Devis!$F$2:$F$3053,"Collectivité")/SUMIFS(Devis!$X$2:$X$3053,Devis!$B$2:$B$3053,">="&Paramètres!$C$9,Devis!$B$2:$B$3053,"<="&Paramètres!$C$10),"")
B27: Particulier | C27: =IFERROR(SUMIFS(Devis!$X$2:$X$3053,Devis!$B$2:$B$3053,">="&Paramètres!$C$9,Devis!$B$2:$B$3053,"<="&Paramètres!$C$10,Devis!$F$2:$F$3053,"Particulier")/SUMIFS(Devis!$W$2:$W$3053,Devis!$B$2:$B$3053,">="&Paramètres!$C$9,Devis!$B$2:$B$3053,"<="&Paramètres!$C$10,Devis!$F$2:$F$3053,"Particulier"),"") | D27: =COUNTIFS(Devis!$B$2:$B$3053,">="&Paramètres!$C$9,Devis!$B$2:$B$3053,"<="&Paramètres!$C$10,Devis!$F$2:$F$3053,"Particulier") | E27: =IFERROR(SUMIFS(Devis!$X$2:$X$3053,Devis!$B$2:$B$3053,">="&Paramètres!$C$11,Devis!$B$2:$B$3053,"<="&Paramètres!$C$12,Devis!$F$2:$F$3053,"Particulier")/SUMIFS(Devis!$W$2:$W$3053,Devis!$B$2:$B$3053,">="&Paramètres!$C$11,Devis!$B$2:$B$3053,"<="&Paramètres!$C$12,Devis!$F$2:$F$3053,"Particulier"),"") | F27: =IFERROR($C27/$E27-1,"") | G27: =IFERROR(SUMIFS(Devis!$X$2:$X$3053,Devis!$B$2:$B$3053,">="&Paramètres!$C$9,Devis!$B$2:$B$3053,"<="&Paramètres!$C$10,Devis!$F$2:$F$3053,"Particulier")/SUMIFS(Devis!$X$2:$X$3053,Devis!$B$2:$B$3053,">="&Paramètres!$C$9,Devis!$B$2:$B$3053,"<="&Paramètres!$C$10),"")
B28: Professionnel | C28: =IFERROR(SUMIFS(Devis!$X$2:$X$3053,Devis!$B$2:$B$3053,">="&Paramètres!$C$9,Devis!$B$2:$B$3053,"<="&Paramètres!$C$10,Devis!$F$2:$F$3053,"Professionnel")/SUMIFS(Devis!$W$2:$W$3053,Devis!$B$2:$B$3053,">="&Paramètres!$C$9,Devis!$B$2:$B$3053,"<="&Paramètres!$C$10,Devis!$F$2:$F$3053,"Professionnel"),"") | D28: =COUNTIFS(Devis!$B$2:$B$3053,">="&Paramètres!$C$9,Devis!$B$2:$B$3053,"<="&Paramètres!$C$10,Devis!$F$2:$F$3053,"Professionnel") | E28: =IFERROR(SUMIFS(Devis!$X$2:$X$3053,Devis!$B$2:$B$3053,">="&Paramètres!$C$11,Devis!$B$2:$B$3053,"<="&Paramètres!$C$12,Devis!$F$2:$F$3053,"Professionnel")/SUMIFS(Devis!$W$2:$W$3053,Devis!$B$2:$B$3053,">="&Paramètres!$C$11,Devis!$B$2:$B$3053,"<="&Paramètres!$C$12,Devis!$F$2:$F$3053,"Professionnel"),"") | F28: =IFERROR($C28/$E28-1,"") | G28: =IFERROR(SUMIFS(Devis!$X$2:$X$3053,Devis!$B$2:$B$3053,">="&Paramètres!$C$9,Devis!$B$2:$B$3053,"<="&Paramètres!$C$10,Devis!$F$2:$F$3053,"Professionnel")/SUMIFS(Devis!$X$2:$X$3053,Devis!$B$2:$B$3053,">="&Paramètres!$C$9,Devis!$B$2:$B$3053,"<="&Paramètres!$C$10),"")
B29: Syndic | C29: =IFERROR(SUMIFS(Devis!$X$2:$X$3053,Devis!$B$2:$B$3053,">="&Paramètres!$C$9,Devis!$B$2:$B$3053,"<="&Paramètres!$C$10,Devis!$F$2:$F$3053,"Syndic")/SUMIFS(Devis!$W$2:$W$3053,Devis!$B$2:$B$3053,">="&Paramètres!$C$9,Devis!$B$2:$B$3053,"<="&Paramètres!$C$10,Devis!$F$2:$F$3053,"Syndic"),"") | D29: =COUNTIFS(Devis!$B$2:$B$3053,">="&Paramètres!$C$9,Devis!$B$2:$B$3053,"<="&Paramètres!$C$10,Devis!$F$2:$F$3053,"Syndic") | E29: =IFERROR(SUMIFS(Devis!$X$2:$X$3053,Devis!$B$2:$B$3053,">="&Paramètres!$C$11,Devis!$B$2:$B$3053,"<="&Paramètres!$C$12,Devis!$F$2:$F$3053,"Syndic")/SUMIFS(Devis!$W$2:$W$3053,Devis!$B$2:$B$3053,">="&Paramètres!$C$11,Devis!$B$2:$B$3053,"<="&Paramètres!$C$12,Devis!$F$2:$F$3053,"Syndic"),"") | F29: =IFERROR($C29/$E29-1,"") | G29: =IFERROR(SUMIFS(Devis!$X$2:$X$3053,Devis!$B$2:$B$3053,">="&Paramètres!$C$9,Devis!$B$2:$B$3053,"<="&Paramètres!$C$10,Devis!$F$2:$F$3053,"Syndic")/SUMIFS(Devis!$X$2:$X$3053,Devis!$B$2:$B$3053,">="&Paramètres!$C$9,Devis!$B$2:$B$3053,"<="&Paramètres!$C$10),"")
B30: Ensemble | C30: =IFERROR(SUMIFS(Devis!$X$2:$X$3053,Devis!$B$2:$B$3053,">="&Paramètres!$C$9,Devis!$B$2:$B$3053,"<="&Paramètres!$C$10)/SUMIFS(Devis!$W$2:$W$3053,Devis!$B$2:$B$3053,">="&Paramètres!$C$9,Devis!$B$2:$B$3053,"<="&Paramètres!$C$10),"") | D30: =COUNTIFS(Devis!$B$2:$B$3053,">="&Paramètres!$C$9,Devis!$B$2:$B$3053,"<="&Paramètres!$C$10) | E30: =IFERROR(SUMIFS(Devis!$X$2:$X$3053,Devis!$B$2:$B$3053,">="&Paramètres!$C$11,Devis!$B$2:$B$3053,"<="&Paramètres!$C$12)/SUMIFS(Devis!$W$2:$W$3053,Devis!$B$2:$B$3053,">="&Paramètres!$C$11,Devis!$B$2:$B$3053,"<="&Paramètres!$C$12),"") | F30: =IFERROR($C30/$E30-1,"") | G30: =1
B31: Décision attendue : Repréciser la grille tarifaire et les propositions d'options sur le segment Particulier pour remonter le panier moyen.

Sheet Détail mensuel
B2: B Â T I - S U D · G R O U P E A R T I S A N A L
B3: Détail mensuel | J3: Données de série
B4: Source des graphiques de la synthèse. Une ligne par mois, sur toute la période.
B7: Série mensuelle
B8: Mois | C8: CA facturé HT | D8: Coût de revient | E8: Marge brute | F8: Taux de marge | G8: Devis émis HT | H8: Devis arbitrés HT | I8: Devis gagnés HT | J8: Taux de transformation | K8: Encaissements TTC
B9: 2022-07 | C9: =SUMIFS(Factures!$K$2:$K$1085,Factures!$G$2:$G$1085,$B9) | D9: =SUMIFS(Factures!$U$2:$U$1085,Factures!$G$2:$G$1085,$B9) | E9: =$C9-$D9 | F9: =IFERROR($E9/$C9,"") | G9: =SUMIFS(Devis!$M$2:$M$3053,Devis!$C$2:$C$3053,$B9) | H9: =SUMIFS(Devis!$Y$2:$Y$3053,Devis!$C$2:$C$3053,$B9) | I9: =SUMIFS(Devis!$X$2:$X$3053,Devis!$C$2:$C$3053,$B9) | J9: =IFERROR($I9/$H9,"") | K9: =SUMIFS(Factures!$M$2:$M$1085,Factures!$AD$2:$AD$1085,$B9)
B10: 2022-08 | C10: =SUMIFS(Factures!$K$2:$K$1085,Factures!$G$2:$G$1085,$B10) | D10: =SUMIFS(Factures!$U$2:$U$1085,Factures!$G$2:$G$1085,$B10) | E10: =$C10-$D10 | F10: =IFERROR($E10/$C10,"") | G10: =SUMIFS(Devis!$M$2:$M$3053,Devis!$C$2:$C$3053,$B10) | H10: =SUMIFS(Devis!$Y$2:$Y$3053,Devis!$C$2:$C$3053,$B10) | I10: =SUMIFS(Devis!$X$2:$X$3053,Devis!$C$2:$C$3053,$B10) | J10: =IFERROR($I10/$H10,"") | K10: =SUMIFS(Factures!$M$2:$M$1085,Factures!$AD$2:$AD$1085,$B10)
B11: 2022-09 | C11: =SUMIFS(Factures!$K$2:$K$1085,Factures!$G$2:$G$1085,$B11) | D11: =SUMIFS(Factures!$U$2:$U$1085,Factures!$G$2:$G$1085,$B11) | E11: =$C11-$D11 | F11: =IFERROR($E11/$C11,"") | G11: =SUMIFS(Devis!$M$2:$M$3053,Devis!$C$2:$C$3053,$B11) | H11: =SUMIFS(Devis!$Y$2:$Y$3053,Devis!$C$2:$C$3053,$B11) | I11: =SUMIFS(Devis!$X$2:$X$3053,Devis!$C$2:$C$3053,$B11) | J11: =IFERROR($I11/$H11,"") | K11: =SUMIFS(Factures!$M$2:$M$1085,Factures!$AD$2:$AD$1085,$B11)
B12: 2022-10 | C12: =SUMIFS(Factures!$K$2:$K$1085,Factures!$G$2:$G$1085,$B12) | D12: =SUMIFS(Factures!$U$2:$U$1085,Factures!$G$2:$G$1085,$B12) | E12: =$C12-$D12 | F12: =IFERROR($E12/$C12,"") | G12: =SUMIFS(Devis!$M$2:$M$3053,Devis!$C$2:$C$3053,$B12) | H12: =SUMIFS(Devis!$Y$2:$Y$3053,Devis!$C$2:$C$3053,$B12) | I12: =SUMIFS(Devis!$X$2:$X$3053,Devis!$C$2:$C$3053,$B12) | J12: =IFERROR($I12/$H12,"") | K12: =SUMIFS(Factures!$M$2:$M$1085,Factures!$AD$2:$AD$1085,$B12)
B13: 2022-11 | C13: =SUMIFS(Factures!$K$2:$K$1085,Factures!$G$2:$G$1085,$B13) | D13: =SUMIFS(Factures!$U$2:$U$1085,Factures!$G$2:$G$1085,$B13) | E13: =$C13-$D13 | F13: =IFERROR($E13/$C13,"") | G13: =SUMIFS(Devis!$M$2:$M$3053,Devis!$C$2:$C$3053,$B13) | H13: =SUMIFS(Devis!$Y$2:$Y$3053,Devis!$C$2:$C$3053,$B13) | I13: =SUMIFS(Devis!$X$2:$X$3053,Devis!$C$2:$C$3053,$B13) | J13: =IFERROR($I13/$H13,"") | K13: =SUMIFS(Factures!$M$2:$M$1085,Factures!$AD$2:$AD$1085,$B13)
B14: 2022-12 | C14: =SUMIFS(Factures!$K$2:$K$1085,Factures!$G$2:$G$1085,$B14) | D14: =SUMIFS(Factures!$U$2:$U$1085,Factures!$G$2:$G$1085,$B14) | E14: =$C14-$D14 | F14: =IFERROR($E14/$C14,"") | G14: =SUMIFS(Devis!$M$2:$M$3053,Devis!$C$2:$C$3053,$B14) | H14: =SUMIFS(Devis!$Y$2:$Y$3053,Devis!$C$2:$C$3053,$B14) | I14: =SUMIFS(Devis!$X$2:$X$3053,Devis!$C$2:$C$3053,$B14) | J14: =IFERROR($I14/$H14,"") | K14: =SUMIFS(Factures!$M$2:$M$1085,Factures!$AD$2:$AD$1085,$B14)
B15: 2023-01 | C15: =SUMIFS(Factures!$K$2:$K$1085,Factures!$G$2:$G$1085,$B15) | D15: =SUMIFS(Factures!$U$2:$U$1085,Factures!$G$2:$G$1085,$B15) | E15: =$C15-$D15 | F15: =IFERROR($E15/$C15,"") | G15: =SUMIFS(Devis!$M$2:$M$3053,Devis!$C$2:$C$3053,$B15) | H15: =SUMIFS(Devis!$Y$2:$Y$3053,Devis!$C$2:$C$3053,$B15) | I15: =SUMIFS(Devis!$X$2:$X$3053,Devis!$C$2:$C$3053,$B15) | J15: =IFERROR($I15/$H15,"") | K15: =SUMIFS(Factures!$M$2:$M$1085,Factures!$AD$2:$AD$1085,$B15)
B16: 2023-02 | C16: =SUMIFS(Factures!$K$2:$K$1085,Factures!$G$2:$G$1085,$B16) | D16: =SUMIFS(Factures!$U$2:$U$1085,Factures!$G$2:$G$1085,$B16) | E16: =$C16-$D16 | F16: =IFERROR($E16/$C16,"") | G16: =SUMIFS(Devis!$M$2:$M$3053,Devis!$C$2:$C$3053,$B16) | H16: =SUMIFS(Devis!$Y$2:$Y$3053,Devis!$C$2:$C$3053,$B16) | I16: =SUMIFS(Devis!$X$2:$X$3053,Devis!$C$2:$C$3053,$B16) | J16: =IFERROR($I16/$H16,"") | K16: =SUMIFS(Factures!$M$2:$M$1085,Factures!$AD$2:$AD$1085,$B16)
B17: 2023-03 | C17: =SUMIFS(Factures!$K$2:$K$1085,Factures!$G$2:$G$1085,$B17) | D17: =SUMIFS(Factures!$U$2:$U$1085,Factures!$G$2:$G$1085,$B17) | E17: =$C17-$D17 | F17: =IFERROR($E17/$C17,"") | G17: =SUMIFS(Devis!$M$2:$M$3053,Devis!$C$2:$C$3053,$B17) | H17: =SUMIFS(Devis!$Y$2:$Y$3053,Devis!$C$2:$C$3053,$B17) | I17: =SUMIFS(Devis!$X$2:$X$3053,Devis!$C$2:$C$3053,$B17) | J17: =IFERROR($I17/$H17,"") | K17: =SUMIFS(Factures!$M$2:$M$1085,Factures!$AD$2:$AD$1085,$B17)
B18: 2023-04 | C18: =SUMIFS(Factures!$K$2:$K$1085,Factures!$G$2:$G$1085,$B18) | D18: =SUMIFS(Factures!$U$2:$U$1085,Factures!$G$2:$G$1085,$B18) | E18: =$C18-$D18 | F18: =IFERROR($E18/$C18,"") | G18: =SUMIFS(Devis!$M$2:$M$3053,Devis!$C$2:$C$3053,$B18) | H18: =SUMIFS(Devis!$Y$2:$Y$3053,Devis!$C$2:$C$3053,$B18) | I18: =SUMIFS(Devis!$X$2:$X$3053,Devis!$C$2:$C$3053,$B18) | J18: =IFERROR($I18/$H18,"") | K18: =SUMIFS(Factures!$M$2:$M$1085,Factures!$AD$2:$AD$1085,$B18)
B19: 2023-05 | C19: =SUMIFS(Factures!$K$2:$K$1085,Factures!$G$2:$G$1085,$B19) | D19: =SUMIFS(Factures!$U$2:$U$1085,Factures!$G$2:$G$1085,$B19) | E19: =$C19-$D19 | F19: =IFERROR($E19/$C19,"") | G19: =SUMIFS(Devis!$M$2:$M$3053,Devis!$C$2:$C$3053,$B19) | H19: =SUMIFS(Devis!$Y$2:$Y$3053,Devis!$C$2:$C$3053,$B19) | I19: =SUMIFS(Devis!$X$2:$X$3053,Devis!$C$2:$C$3053,$B19) | J19: =IFERROR($I19/$H19,"") | K19: =SUMIFS(Factures!$M$2:$M$1085,Factures!$AD$2:$AD$1085,$B19)
B20: 2023-06 | C20: =SUMIFS(Factures!$K$2:$K$1085,Factures!$G$2:$G$1085,$B20) | D20: =SUMIFS(Factures!$U$2:$U$1085,Factures!$G$2:$G$1085,$B20) | E20: =$C20-$D20 | F20: =IFERROR($E20/$C20,"") | G20: =SUMIFS(Devis!$M$2:$M$3053,Devis!$C$2:$C$3053,$B20) | H20: =SUMIFS(Devis!$Y$2:$Y$3053,Devis!$C$2:$C$3053,$B20) | I20: =SUMIFS(Devis!$X$2:$X$3053,Devis!$C$2:$C$3053,$B20) | J20: =IFERROR($I20/$H20,"") | K20: =SUMIFS(Factures!$M$2:$M$1085,Factures!$AD$2:$AD$1085,$B20)
... B56: 2026-06 | C56: =SUMIFS(Factures!$K$2:$K$1085,Factures!$G$2:$G$1085,$B56) | D56: =SUMIFS(Factures!$U$2:$U$1085,Factures!$G$2:$G$1085,$B56) | E56: =$C56-$D56 | F56: =IFERROR($E56/$C56,"") | G56: =SUMIFS(Devis!$M$2:$M$3053,Devis!$C$2:$C$3053,$B56) | H56: =SUMIFS(Devis!$Y$2:$Y$3053,Devis!$C$2:$C$3053,$B56) | I56: =SUMIFS(Devis!$X$2:$X$3053,Devis!$C$2:$C$3053,$B56) | J56: =IFERROR($I56/$H56,"") | K56: =SUMIFS(Factures!$M$2:$M$1085,Factures!$AD$2:$AD$1085,$B56)
B57: Total | C57: =SUM(C9:C56) | D57: =SUM(D9:D56) | E57: =$C57-$D57 | F57: =IFERROR($E57/$C57,"") | G57: =SUM(G9:G56) | H57: =SUM(H9:H56) | I57: =SUM(I9:I56) | J57: =IFERROR($I57/$H57,"") | K57: =SUM($K9:$K56)

Sheet Ce qui a été regardé
B2: B Â T I - S U D · G R O U P E A R T I S A N A L
B3: Ce qui a été regardé | G3: Traçabilité
B4: 23 croisements examinés, 21 recevables, 2 écartés avant scoring.
B7: Candidats les mieux placés
B8: Croisement | C8: Matérialité (€/an) | D8: Dispersion | E8: Stabilité | F8: Monotonie | G8: Score | H8: Retenu
B9: Panier moyen d'un devis gagné par type de client | C9: 83284.471 | D9: 0.29979548 | E9: 0.98360075 | F9: 0 | G9: 0.717531 | H9: oui
B10: Panier moyen d'un devis gagné par agence | C10: 47840.362 | D10: 0.34524803 | E10: 0.98797028 | F10: 0 | G10: 0.53763
B11: Taux de transformation des devis par agence | C11: 31811.189 | D11: 0.50586219 | E11: 0.99699684 | F11: 0 | G11: 0.490764 | H11: oui
B12: Taux de transformation des devis par type de client | C12: 26486.945 | D12: 0.44112778 | E12: 0.98929817 | F12: 0 | G12: 0.445166
B13: Taux de transformation des devis par métier | C13: 27335.282 | D13: 0.27782421 | E13: 0.91196824 | F13: 0 | G13: 0.395712
B14: Taux de marge brute par type de client | C14: 28135.787 | D14: 0.12647596 | E14: 0.95457206 | F14: 0 | G14: 0.37281
B15: Taux de transformation des devis par canal d'acquisition | C15: 16301.722 | D15: 0.35174154 | E15: 0.96010041 | F15: 0 | G15: 0.363181
B16: DSO — délai moyen d'encaissement par canal d'acquisition | D16: 0.6018258 | E16: 0.9549964 | F16: 0 | G16: 0.333149
B17: Taux de marge brute par métier | C17: 15754.907 | D17: 0.15274065 | E17: 0.91420419 | F17: 0 | G17: 0.304044
B18: Chiffre d'affaires facturé HT par métier | D18: 0.84674981 | E18: 0.5 | F18: 0 | G18: 0.3
B19: Taux de marge brute par agence | C19: 23175.911 | D19: 0.092748995 | E19: 0.74850414 | F19: 0 | G19: 0.296831
B20: Chiffre d'affaires facturé HT par agence | D20: 0.79845642 | E20: 0.5 | F20: 0 | G20: 0.288593
B22: Écartés avant scoring
B23: Croisement | C23: Motif
B24: Taux de marge brute par canal d'acquisition | C24: écart de 4.2%, sous le plancher de 5%
B25: DSO — délai moyen d'encaissement par type de client | C25: les modalités retenues ne couvrent que 70% du total
B27: Hypothèses explorées puis abandonnées
B28: Hypothèse | C28: Motif d'abandon
B29: Le taux de marge brute sur les Particuliers est structurellement plus faible que sur les autres clientèles. | C29: L'écart existe mais la mesure de marge brute est déjà couverte par le socle imposé, doublonner ferait perdre en lisibilité.
B30: Le taux de transformation sur Chauffage est dégradé et pèse sur l'ensemble de l'activité. | C30: L'écart est réel mais la Plomberie présente un niveau équivalent : aucun coupable métier isolé, donc aucune décision ciblée possible.
B31: Un effet combiné métier × agence existe sur la marge de la Salle de bain. | C31: Le croisement ne révèle aucune cellule Sala de bain × agence suffisamment peuplée et distinctive : l'hypothèse n'est pas démontrable.
B32: Le DSO dégradé provient du canal Site web, sur lequel le dirigeant peut agir. | C32: Confirmée mais la mesure DSO est déjà dans le socle imposé : pas un indicateur à choisir.

Sheet Paramètres
B2: B Â T I - S U D · G R O U P E A R T I S A N A L
B3: Paramètres, empreinte et méthode | H3: Feuille de contrôle
B4: Les cellules bleues sur fond jaune sont les seules à modifier.
B7: Paramètres de calcul
B8: Date de situation | C8: 46203 | D8: Référence de tous les calculs d'âge et de retard. La modifier recalcule le rapport.
B9: Début de la fenêtre | C9: =$C$8-364 | D9: Douze mois glissants.
B10: Fin de la fenêtre | C10: =$C$8
B11: Début de la comparaison | C11: =$C$8-729 | D11: Les douze mois précédents.
B12: Fin de la comparaison | C12: =$C$8-365
B13: Seuil de créance à risque | C13: 90 | D13: Ancienneté à partir de laquelle une créance passe en recouvrement.
B14: Délai de relance visé | C14: 3 | D14: Au-delà, le taux de transformation chute nettement.
B16: Conventions
B17: Bleu sur fond jaune | D17: Cellule de saisie — modifiable
B18: Noir | D18: Résultat de formule — ne pas écraser
B19: En-tête vert | D19: Colonne calculée ajoutée aux sources
B20: En-tête bleu nuit | D20: Donnée importée des CSV
B23: Empreinte du jeu de données
B24: Fichier | C24: Enregistrements | D24: SHA-256
B25: catalogue_prestations.csv | C25: 20 | D25: 40381635001b30885941e47a907d3c48…
B26: clients.csv | C26: 1019 | D26: 7d2022f6983fe3ef9d068227ddffd26c…
B27: devis.csv | C27: 3052 | D27: 0e8d4fbef0b01f2b8018e37d2bc59dad…
B28: factures.csv | C28: 1084 | D28: 7ab4af0426975929e48e5439f96db217…
B29: interventions.csv | C29: 1105 | D29: a9481f4482ad4f138bc242de79132086…
B30: relances.csv | C30: 3167 | D30: 74d3134700730081db2f02564b6be823…
B31: techniciens.csv | C31: 12 | D31: 743fdfd49eb2407bf9113c567686ccc7…
B32: Ensemble | C32: 9459 | D32: 2660 77f0 91a1 3a48 8501 45d4 c652 c30d
B34: Méthode
B35: • JEU DE DONNÉES FICTIF, généré pour démonstration. Aucune donnée réelle.
B36: • Période couverte : quatre exercices. Fenêtre d'analyse : exercice 2025-2026.
B37: • Le chiffre d'affaires est hors taxes ; l'encours en TTC, montant réellement dû.
B38: • Le coût de revient d'une facture est celui de l'intervention liée : heures réelles fois coût horaire du technicien, plus matériel. Aucun frais de structure.
B39: • La marge est donc une marge sur coûts directs, et non un résultat d'exploitation.
B40: • Les taux somment numérateurs et dénominateurs AVANT de diviser. La moyenne de trois taux de marge n'est pas le taux de marge de trois agences.
B41: • L'encours et le DSO sont des états à la date de situation : ils n'ont pas de version « période précédente », et aucune variation n'est affichée pour eux.
B42: • L'empreinte établit que le rapport porte sur ces fichiers exacts. Elle n'établit aucune antériorité : il y faudrait un horodatage par un tiers.
B43: • Toutes les cellules chiffrées sont des formules. Corriger une donnée source met à jour l'ensemble du rapport.

Sheet Devis
A1: Devis id | B1: Date emission | C1: Mois | D1: Exercice | E1: Client id | F1: Type client | G1: Agence | H1: Commercial | I1: Categorie | J1: Code prestation | K1: Libelle prestation | L1: Quantite | M1: Montant ht | N1: Statut | O1: Date decision | P1: Delai 1ere relance j | Q1: Nb relances | R1: Métier | S1: Prestation | T1: Canal d'acquisition | U1: Profil de paiement | V1: Ligne | W1: Gagné | X1: CA gagné HT | Y1: Montant arbitré HT | Z1: Relancé | AA1: Délai relance pondéré | AB1: Relance sous seuil | AC1: Tranche de relance | AD1: Tranche de montant
A2: DEV-00001 | B2: 44743 | C2: 2022-07 | D2: 2022-2023 | E2: CLI-0170 | F2: Particulier | G2: Toulouse | H2: Julien Fabre | I2: Plomberie | J2: PR-003 | K2: Réfection réseau eau appartement | L2: 1 | M2: 3434.79 | N2: Sans réponse | O2: 44770 | P2: 4 | Q2: 2 | R2: =$I2 | S2: =$K2 | T2: =IFERROR(INDEX(Clients!$G$2:$G$1020,MATCH($E2,Clients!$A$2:$A$1020,0)),"") | U2: =IFERROR(INDEX(Clients!$I$2:$I$1020,MATCH($E2,Clients!$A$2:$A$1020,0)),"") | V2: =1 | W2: =IF($N2="Accepté",1,0) | X2: =$M2*$W2 | Y2: =IF($N2="En cours",0,$M2) | Z2: =IF($P2="",0,1) | AA2: =IF($P2="",0,$P2) | AB2: =IF(AND($P2<>"",$P2<=Paramètres!$C$14),1,0) | AC2: =IF($P2="","Jamais relancé",IF($P2<=3,"0-3 j",IF($P2<=7,"4-7 j",IF($P2<=15,"8-15 j","Plus de 15 j")))) | AD2: =IF($M2<=1000,"Moins de 1 k€",IF($M2<=5000,"1 à 5 k€",IF($M2<=15000,"5 à 15 k€","Plus de 15 k€")))
A3: DEV-00002 | B3: 44743 | C3: 2022-07 | D3: 2022-2023 | E3: CLI-0150 | F3: Particulier | G3: Bordeaux | H3: Sophie Marchand | I3: Plomberie | J3: PR-002 | K3: Recherche de fuite + réparation | L3: 1 | M3: 420.94 | N3: Refusé | O3: 44746 | P3: 1 | Q3: 1 | R3: =$I3 | S3: =$K3 | T3: =IFERROR(INDEX(Clients!$G$2:$G$1020,MATCH($E3,Clients!$A$2:$A$1020,0)),"") | U3: =IFERROR(INDEX(Clients!$I$2:$I$1020,MATCH($E3,Clients!$A$2:$A$1020,0)),"") | V3: =1 | W3: =IF($N3="Accepté",1,0) | X3: =$M3*$W3 | Y3: =IF($N3="En cours",0,$M3) | Z3: =IF($P3="",0,1) | AA3: =IF($P3="",0,$P3) | AB3: =IF(AND($P3<>"",$P3<=Paramètres!$C$14),1,0) | AC3: =IF($P3="","Jamais relancé",IF($P3<=3,"0-3 j",IF($P3<=7,"4-7 j",IF($P3<=15,"8-15 j","Plus de 15 j")))) | AD3: =IF($M3<=1000,"Moins de 1 k€",IF($M3<=5000,"1 à 5 k€",IF($M3<=15000,"5 à 15 k€","Plus de 15 k€")))
A4: DEV-00003 | B4: 44743 | C4: 2022-07 | D4: 2022-2023 | E4: CLI-0145 | F4: Collectivité | G4: Bordeaux | H4: Karim Belkacem | I4: Salle de bain | J4: SB-001 | K4: Rénovation salle de bain complète | L4: 1 | M4: 20469.82 | N4: Refusé | O4: 44754 | Q4: 0 | R4: =$I4 | S4: =$K4 | T4: =IFERROR(INDEX(Clients!$G$2:$G$1020,MATCH($E4,Clients!$A$2:$A$1020,0)),"") | U4: =IFERROR(INDEX(Clients!$I$2:$I$1020,MATCH($E4,Clients!$A$2:$A$1020,0)),"") | V4: =1 | W4: =IF($N4="Accepté",1,0) | X4: =$M4*$W4 | Y4: =IF($N4="En cours",0,$M4) | Z4: =IF($P4="",0,1) | AA4: =IF($P4="",0,$P4) | AB4: =IF(AND($P4<>"",$P4<=Paramètres!$C$14),1,0) | AC4: =IF($P4="","Jamais relancé",IF($P4<=3,"0-3 j",IF($P4<=7,"4-7 j",IF($P4<=15,"8-15 j","Plus de 15 j")))) | AD4: =IF($M4<=1000,"Moins de 1 k€",IF($M4<=5000,"1 à 5 k€",IF($M4<=15000,"5 à 15 k€","Plus de 15 k€")))
A5: DEV-00004 | B5: 44746 | C5: 2022-07 | D5: 2022-2023 | E5: CLI-0120 | F5: Particulier | G5: Toulouse | H5: Julien Fabre | I5: Plomberie | J5: PR-003 | K5: Réfection réseau eau appartement | L5: 1 | M5: 2836.66 | N5: Refusé | O5: 44770 | P5: 10 | Q5: 2 | R5: =$I5 | S5: =$K5 | T5: =IFERROR(INDEX(Clients!$G$2:$G$1020,MATCH($E5,Clients!$A$2:$A$1020,0)),"") | U5: =IFERROR(INDEX(Clients!$I$2:$I$1020,MATCH($E5,Clients!$A$2:$A$1020,0)),"") | V5: =1 | W5: =IF($N5="Accepté",1,0) | X5: =$M5*$W5 | Y5: =IF($N5="En cours",0,$M5) | Z5: =IF($P5="",0,1) | AA5: =IF($P5="",0,$P5) | AB5: =IF(AND($P5<>"",$P5<=Paramètres!$C$14),1,0) | AC5: =IF($P5="","Jamais relancé",IF($P5<=3,"0-3 j",IF($P5<=7,"4-7 j",IF($P5<=15,"8-15 j","Plus de 15 j")))) | AD5: =IF($M5<=1000,"Moins de 1 k€",IF($M5<=5000,"1 à 5 k€",IF($M5<=15000,"5 à 15 k€","Plus de 15 k€")))
A6: DEV-00005 | B6: 44747 | C6: 2022-07 | D6: 2022-2023 | E6: CLI-0004 | F6: Particulier | G6: Bordeaux | H6: Karim Belkacem | I6: Chauffage | J6: CH-003 | K6: Installation pompe à chaleur air/eau | L6: 1 | M6: 13409.78 | N6: Refusé | O6: 44750 | P6: 9 | Q6: 0 | R6: =$I6 | S6: =$K6 | T6: =IFERROR(INDEX(Clients!$G$2:$G$1020,MATCH($E6,Clients!$A$2:$A$1020,0)),"") | U6: =IFERROR(INDEX(Clients!$I$2:$I$1020,MATCH($E6,Clients!$A$2:$A$1020,0)),"") | V6: =1 | W6: =IF($N6="Accepté",1,0) | X6: =$M6*$W6 | Y6: =IF($N6="En cours",0,$M6) | Z6: =IF($P6="",0,1) | AA6: =IF($P6="",0,$P6) | AB6: =IF(AND($P6<>"",$P6<=Paramètres!$C$14),1,0) | AC6: =IF($P6="","Jamais relancé",IF($P6<=3,"0-3 j",IF($P6<=7,"4-7 j",IF($P6<=15,"8-15 j","Plus de 15 j")))) | AD6: =IF($M6<=1000,"Moins de 1 k€",IF($M6<=5000,"1 à 5 k€",IF($M6<=15000,"5 à 15 k€","Plus de 15 k€")))
A7: DEV-00006 | B7: 44747 | C7: 2022-07 | D7: 2022-2023 | E7: CLI-0114 | F7: Particulier | G7: Bordeaux | H7: Sophie Marchand | I7: Plomberie | J7: PR-002 | K7: Recherche de fuite + réparation | L7: 1 | M7: 408.99 | N7: Accepté | O7: 44759 | P7: 1 | Q7: 2 | R7: =$I7 | S7: =$K7 | T7: =IFERROR(INDEX(Clients!$G$2:$G$1020,MATCH($E7,Clients!$A$2:$A$1020,0)),"") | U7: =IFERROR(INDEX(Clients!$I$2:$I$1020,MATCH($E7,Clients!$A$2:$A$1020,0)),"") | V7: =1 | W7: =IF($N7="Accepté",1,0) | X7: =$M7*$W7 | Y7: =IF($N7="En cours",0,$M7) | Z7: =IF($P7="",0,1) | AA7: =IF($P7="",0,$P7) | AB7: =IF(AND($P7<>"",$P7<=Paramètres!$C$14),1,0) | AC7: =IF($P7="","Jamais relancé",IF($P7<=3,"0-3 j",IF($P7<=7,"4-7 j",IF($P7<=15,"8-15 j","Plus de 15 j")))) | AD7: =IF($M7<=1000,"Moins de 1 k€",IF($M7<=5000,"1 à 5 k€",IF($M7<=15000,"5 à 15 k€","Plus de 15 k€")))
A8: DEV-00007 | B8: 44748 | C8: 2022-07 | D8: 2022-2023 | E8: CLI-0068 | F8: Particulier | G8: Bordeaux | H8: Karim Belkacem | I8: Plomberie | J8: PR-001 | K8: Remplacement chauffe-eau 200 L | L8: 1 | M8: 1043.35 | N8: Refusé | O8: 44777 | P8: 1 | Q8: 1 | R8: =$I8 | S8: =$K8 | T8: =IFERROR(INDEX(Clients!$G$2:$G$1020,MATCH($E8,Clients!$A$2:$A$1020,0)),"") | U8: =IFERROR(INDEX(Clients!$I$2:$I$1020,MATCH($E8,Clients!$A$2:$A$1020,0)),"") | V8: =1 | W8: =IF($N8="Accepté",1,0) | X8: =$M8*$W8 | Y8: =IF($N8="En cours",0,$M8) | Z8: =IF($P8="",0,1) | AA8: =IF($P8="",0,$P8) | AB8: =IF(AND($P8<>"",$P8<=Paramètres!$C$14),1,0) | AC8: =IF($P8="","Jamais relancé",IF($P8<=3,"0-3 j",IF($P8<=7,"4-7 j",IF($P8<=15,"8-15 j","Plus de 15 j")))) | AD8: =IF($M8<=1000,"Moins de 1 k€",IF($M8<=5000,"1 à 5 k€",IF($M8<=15000,"5 à 15 k€","Plus de 15 k€")))
A9: DEV-00008 | B9: 44748 | C9: 2022-07 | D9: 2022-2023 | E9: CLI-0160 | F9: Particulier | G9: Bordeaux | H9: Karim Belkacem | I9: Plomberie | J9: PR-004 | K9: Remplacement colonne d'évacuation | L9: 1 | M9: 5812.36 | N9: Accepté | O9: 44780 | P9: 3 | Q9: 1 | R9: =$I9 | S9: =$K9 | T9: =IFERROR(INDEX(Clients!$G$2:$G$1020,MATCH($E9,Clients!$A$2:$A$1020,0)),"") | U9: =IFERROR(INDEX(Clients!$I$2:$I$1020,MATCH($E9,Clients!$A$2:$A$1020,0)),"") | V9: =1 | W9: =IF($N9="Accepté",1,0) | X9: =$M9*$W9 | Y9: =IF($N9="En cours",0,$M9) | Z9: =IF($P9="",0,1) | AA9: =IF($P9="",0,$P9) | AB9: =IF(AND($P9<>"",$P9<=Paramètres!$C$14),1,0) | AC9: =IF($P9="","Jamais relancé",IF($P9<=3,"0-3 j",IF($P9<=7,"4-7 j",IF($P9<=15,"8-15 j","Plus de 15 j")))) | AD9: =IF($M9<=1000,"Moins de 1 k€",IF($M9<=5000,"1 à 5 k€",IF($M9<=15000,"5 à 15 k€","Plus de 15 k€")))
A10: DEV-00009 | B10: 44748 | C10: 2022-07 | D10: 2022-2023 | E10: CLI-0102 | F10: Particulier | G10: Toulouse | H10: Julien Fabre | I10: Plomberie | J10: PR-002 | K10: Recherche de fuite + réparation | L10: 1 | M10: 420.81 | N10: Refusé | O10: 44770 | P10: 8 | Q10: 2 | R10: =$I10 | S10: =$K10 | T10: =IFERROR(INDEX(Clients!$G$2:$G$1020,MATCH($E10,Clients!$A$2:$A$1020,0)),"") | U10: =IFERROR(INDEX(Clients!$I$2:$I$1020,MATCH($E10,Clients!$A$2:$A$1020,0)),"") | V10: =1 | W10: =IF($N10="Accepté",1,0) | X10: =$M10*$W10 | Y10: =IF($N10="En cours",0,$M10) | Z10: =IF($P10="",0,1) | AA10: =IF($P10="",0,$P10) | AB10: =IF(AND($P10<>"",$P10<=Paramètres!$C$14),1,0) | AC10: =IF($P10="","Jamais relancé",IF($P10<=3,"0-3 j",IF($P10<=7,"4-7 j",IF($P10<=15,"8-15 j","Plus de 15 j")))) | AD10: =IF($M10<=1000,"Moins de 1 k€",IF($M10<=5000,"1 à 5 k€",IF($M10<=15000,"5 à 15 k€","Plus de 15 k€")))
A11: DEV-00010 | B11: 44750 | C11: 2022-07 | D11: 2022-2023 | E11: CLI-0089 | F11: Particulier | G11: Bordeaux | H11: Karim Belkacem | I11: Salle de bain | J11: SB-003 | K11: Pose meuble vasque + robinetterie | L11: 1 | M11: 1332.2 | N11: Accepté | O11: 44777 | P11: 1 | Q11: 3 | R11: =$I11 | S11: =$K11 | T11: =IFERROR(INDEX(Clients!$G$2:$G$1020,MATCH($E11,Clients!$A$2:$A$1020,0)),"") | U11: =IFERROR(INDEX(Clients!$I$2:$I$1020,MATCH($E11,Clients!$A$2:$A$1020,0)),"") | V11: =1 | W11: =IF($N11="Accepté",1,0) | X11: =$M11*$W11 | Y11: =IF($N11="En cours",0,$M11) | Z11: =IF($P11="",0,1) | AA11: =IF($P11="",0,$P11) | AB11: =IF(AND($P11<>"",$P11<=Paramètres!$C$14),1,0) | AC11: =IF($P11="","Jamais relancé",IF($P11<=3,"0-3 j",IF($P11<=7,"4-7 j",IF($P11<=15,"8-15 j","Plus de 15 j")))) | AD11: =IF($M11<=1000,"Moins de 1 k€",IF($M11<=5000,"1 à 5 k€",IF($M11<=15000,"5 à 15 k€","Plus de 15 k€")))
A12: DEV-00011 | B12: 44750 | C12: 2022-07 | D12: 2022-2023 | E12: CLI-0043 | F12: Particulier | G12: Toulouse | H12: Julien Fabre | I12: Salle de bain | J12: SB-001 | K12: Rénovation salle de bain complète | L12: 1 | M12: 9816.44 | N12: Sans réponse | O12: 44754 | P12: 5 | Q12: 0 | R12: =$I12 | S12: =$K12 | T12: =IFERROR(INDEX(Clients!$G$2:$G$1020,MATCH($E12,Clients!$A$2:$A$1020,0)),"") | U12: =IFERROR(INDEX(Clients!$I$2:$I$1020,MATCH($E12,Clients!$A$2:$A$1020,0)),"") | V12: =1 | W12: =IF($N12="Accepté",1,0) | X12: =$M12*$W12 | Y12: =IF($N12="En cours",0,$M12) | Z12: =IF($P12="",0,1) | AA12: =IF($P12="",0,$P12) | AB12: =IF(AND($P12<>"",$P12<=Paramètres!$C$14),1,0) | AC12: =IF($P12="","Jamais relancé",IF($P12<=3,"0-3 j",IF($P12<=7,"4-7 j",IF($P12<=15,"8-15 j","Plus de 15 j")))) | AD12: =IF($M12<=1000,"Moins de 1 k€",IF($M12<=5000,"1 à 5 k€",IF($M12<=15000,"5 à 15 k€","Plus de 15 k€")))
A13: DEV-00012 | B13: 44753 | C13: 2022-07 | D13: 2022-2023 | E13: CLI-0151 | F13: Syndic | G13: Bordeaux | H13: Karim Belkacem | I13: Salle de bain | J13: SB-002 | K13: Remplacement baignoire par douche | L13: 1 | M13: 7815.09 | N13: Refusé | O13: 44780 | Q13: 0 | R13: =$I13 | S13: =$K13 | T13: =IFERROR(INDEX(Clients!$G$2:$G$1020,MATCH($E13,Clients!$A$2:$A$1020,0)),"") | U13: =IFERROR(INDEX(Clients!$I$2:$I$1020,MATCH($E13,Clients!$A$2:$A$1020,0)),"") | V13: =1 | W13: =IF($N13="Accepté",1,0) | X13: =$M13*$W13 | Y13: =IF($N13="En cours",0,$M13) | Z13: =IF($P13="",0,1) | AA13: =IF($P13="",0,$P13) | AB13: =IF(AND($P13<>"",$P13<=Paramètres!$C$14),1,0) | AC13: =IF($P13="","Jamais relancé",IF($P13<=3,"0-3 j",IF($P13<=7,"4-7 j",IF($P13<=15,"8-15 j","Plus de 15 j")))) | AD13: =IF($M13<=1000,"Moins de 1 k€",IF($M13<=5000,"1 à 5 k€",IF($M13<=15000,"5 à 15 k€","Plus de 15 k€")))
A14: DEV-00013 | B14: 44753 | C14: 2022-07 | D14: 2022-2023 | E14: CLI-0051 | F14: Particulier | G14: Toulouse | H14: Julien Fabre | I14: Salle de bain | J14: SB-001 | K14: Rénovation salle de bain complète | L14: 1 | M14: 8570.48 | N14: Refusé | O14: 44781 | P14: 1 | Q14: 1 | R14: =$I14 | S14: =$K14 | T14: =IFERROR(INDEX(Clients!$G$2:$G$1020,MATCH($E14,Clients!$A$2:$A$1020,0)),"") | U14: =IFERROR(INDEX(Clients!$I$2:$I$1020,MATCH($E14,Clients!$A$2:$A$1020,0)),"") | V14: =1 | W14: =IF($N14="Accepté",1,0) | X14: =$M14*$W14 | Y14: =IF($N14="En cours",0,$M14) | Z14: =IF($P14="",0,1) | AA14: =IF($P14="",0,$P14) | AB14: =IF(AND($P14<>"",$P14<=Paramètres!$C$14),1,0) | AC14: =IF($P14="","Jamais relancé",IF($P14<=3,"0-3 j",IF($P14<=7,"4-7 j",IF($P14<=15,"8-15 j","Plus de 15 j")))) | AD14: =IF($M14<=1000,"Moins de 1 k€",IF($M14<=5000,"1 à 5 k€",IF($M14<=15000,"5 à 15 k€","Plus de 15 k€")))
A15: DEV-00014 | B15: 44753 | C15: 2022-07 | D15: 2022-2023 | E15: CLI-0098 | F15: Particulier | G15: Bordeaux | H15: Karim Belkacem | I15: Dépannage | J15: DP-004 | K15: Remise en service chaudière | L15: 1 | M15: 223.45 | N15: Accepté | O15: 44772 | P15: 2 | Q15: 1 | R15: =$I15 | S15: =$K15 | T15: =IFERROR(INDEX(Clients!$G$2:$G$1020,MATCH($E15,Clients!$A$2:$A$1020,0)),"") | U15: =IFERROR(INDEX(Clients!$I$2:$I$1020,MATCH($E15,Clients!$A$2:$A$1020,0)),"") | V15: =1 | W15: =IF($N15="Accepté",1,0) | X15: =$M15*$W15 | Y15: =IF($N15="En cours",0,$M15) | Z15: =IF($P15="",0,1) | AA15: =IF($P15="",0,$P15) | AB15: =IF(AND($P15<>"",$P15<=Paramètres!$C$14),1,0) | AC15: =IF($P15="","Jamais relancé",IF($P15<=3,"0-3 j",IF($P15<=7,"4-7 j",IF($P15<=15,"8-15 j","Plus de 15 j")))) | AD15: =IF($M15<=1000,"Moins de 1 k€",IF($M15<=5000,"1 à 5 k€",IF($M15<=15000,"5 à 15 k€","Plus de 15 k€")))
A16: DEV-00015 | B16: 44754 | C16: 2022-07 | D16: 2022-2023 | E16: CLI-0042 | F16: Particulier | G16: Bordeaux | H16: Sophie Marchand | I16: Dépannage | J16: DP-002 | K16: Débouchage canalisation | L16: 1 | M16: 331.48 | N16: Accepté | O16: 44762 | P16: 3 | Q16: 1 | R16: =$I16 | S16: =$K16 | T16: =IFERROR(INDEX(Clients!$G$2:$G$1020,MATCH($E16,Clients!$A$2:$A$1020,0)),"") | U16: =IFERROR(INDEX(Clients!$I$2:$I$1020,MATCH($E16,Clients!$A$2:$A$1020,0)),"") | V16: =1 | W16: =IF($N16="Accepté",1,0) | X16: =$M16*$W16 | Y16: =IF($N16="En cours",0,$M16) | Z16: =IF($P16="",0,1) | AA16: =IF($P16="",0,$P16) | AB16: =IF(AND($P16<>"",$P16<=Paramètres!$C$14),1,0) | AC16: =IF($P16="","Jamais relancé",IF($P16<=3,"0-3 j",IF($P16<=7,"4-7 j",IF($P16<=15,"8-15 j","Plus de 15 j")))) | AD16: =IF($M16<=1000,"Moins de 1 k€",IF($M16<=5000,"1 à 5 k€",IF($M16<=15000,"5 à 15 k€","Plus de 15 k€")))
A17: DEV-00016 | B17: 44754 | C17: 2022-07 | D17: 2022-2023 | E17: CLI-0049 | F17: Particulier | G17: Bordeaux | H17: Karim Belkacem | I17: Chauffage | J17: CH-005 | K17: Désembouage circuit chauffage | L17: 1 | M17: 730.54 | N17: Sans réponse | O17: 44774 | P17: 6 | Q17: 1 | R17: =$I17 | S17: =$K17 | T17: =IFERROR(INDEX(Clients!$G$2:$G$1020,MATCH($E17,Clients!$A$2:$A$1020,0)),"") | U17: =IFERROR(INDEX(Clients!$I$2:$I$1020,MATCH($E17,Clients!$A$2:$A$1020,0)),"") | V17: =1 | W17: =IF($N17="Accepté",1,0) | X17: =$M17*$W17 | Y17: =IF($N17="En cours",0,$M17) | Z17: =IF($P17="",0,1) | AA17: =IF($P17="",0,$P17) | AB17: =IF(AND($P17<>"",$P17<=Paramètres!$C$14),1,0) | AC17: =IF($P17="","Jamais relancé",IF($P17<=3,"0-3 j",IF($P17<=7,"4-7 j",IF($P17<=15,"8-15 j","Plus de 15 j")))) | AD17: =IF($M17<=1000,"Moins de 1 k€",IF($M17<=5000,"1 à 5 k€",IF($M17<=15000,"5 à 15 k€","Plus de 15 k€")))
A18: DEV-00017 | B18: 44754 | C18: 2022-07 | D18: 2022-2023 | E18: CLI-0083 | F18: Collectivité | G18: Toulouse | H18: Julien Fabre | I18: Salle de bain | J18: SB-001 | K18: Rénovation salle de bain complète | L18: 1 | M18: 25587.26 | N18: Sans réponse | O18: 44770 | P18: 10 | Q18: 1 | R18: =$I18 | S18: =$K18 | T18: =IFERROR(INDEX(Clients!$G$2:$G$1020,MATCH($E18,Clients!$A$2:$A$1020,0)),"") | U18: =IFERROR(INDEX(Clients!$I$2:$I$1020,MATCH($E18,Clients!$A$2:$A$1020,0)),"") | V18: =1 | W18: =IF($N18="Accepté",1,0) | X18: =$M18*$W18 | Y18: =IF($N18="En cours",0,$M18) | Z18: =IF($P18="",0,1) | AA18: =IF($P18="",0,$P18) | AB18: =IF(AND($P18<>"",$P18<=Paramètres!$C$14),1,0) | AC18: =IF($P18="","Jamais relancé",IF($P18<=3,"0-3 j",IF($P18<=7,"4-7 j",IF($P18<=15,"8-15 j","Plus de 15 j")))) | AD18: =IF($M18<=1000,"Moins de 1 k€",IF($M18<=5000,"1 à 5 k€",IF($M18<=15000,"5 à 15 k€","Plus de 15 k€")))
A19: DEV-00018 | B19: 44755 | C19: 2022-07 | D19: 2022-2023 | E19: CLI-0079 | F19: Particulier | G19: Bordeaux | H19: Karim Belkacem | I19: Électricité | J19: EL-004 | K19: Éclairage LED locaux professionnels | L19: 1 | M19: 3374.26 | N19: Refusé | O19: 44777 | P19: 7 | Q19: 2 | R19: =$I19 | S19: =$K19 | T19: =IFERROR(INDEX(Clients!$G$2:$G$1020,MATCH($E19,Clients!$A$2:$A$1020,0)),"") | U19: =IFERROR(INDEX(Clients!$I$2:$I$1020,MATCH($E19,Clients!$A$2:$A$1020,0)),"") | V19: =1 | W19: =IF($N19="Accepté",1,0) | X19: =$M19*$W19 | Y19: =IF($N19="En cours",0,$M19) | Z19: =IF($P19="",0,1) | AA19: =IF($P19="",0,$P19) | AB19: =IF(AND($P19<>"",$P19<=Paramètres!$C$14),1,0) | AC19: =IF($P19="","Jamais relancé",IF($P19<=3,"0-3 j",IF($P19<=7,"4-7 j",IF($P19<=15,"8-15 j","Plus de 15 j")))) | AD19: =IF($M19<=1000,"Moins de 1 k€",IF($M19<=5000,"1 à 5 k€",IF($M19<=15000,"5 à 15 k€","Plus de 15 k€")))
A20: DEV-00019 | B20: 44755 | C20: 2022-07 | D20: 2022-2023 | E20: CLI-0168 | F20: Particulier | G20: Bordeaux | H20: Karim Belkacem | I20: Plomberie | J20: PR-004 | K20: Remplacement colonne d'évacuation | L20: 1 | M20: 5021.61 | N20: Sans réponse | O20: 44772 | Q20: 0 | R20: =$I20 | S20: =$K20 | T20: =IFERROR(INDEX(Clients!$G$2:$G$1020,MATCH($E20,Clients!$A$2:$A$1020,0)),"") | U20: =IFERROR(INDEX(Clients!$I$2:$I$1020,MATCH($E20,Clients!$A$2:$A$1020,0)),"") | V20: =1 | W20: =IF($N20="Accepté",1,0) | X20: =$M20*$W20 | Y20: =IF($N20="En cours",0,$M20) | Z20: =IF($P20="",0,1) | AA20: =IF($P20="",0,$P20) | AB20: =IF(AND($P20<>"",$P20<=Paramètres!$C$14),1,0) | AC20: =IF($P20="","Jamais relancé",IF($P20<=3,"0-3 j",IF($P20<=7,"4-7 j",IF($P20<=15,"8-15 j","Plus de 15 j")))) | AD20: =IF($M20<=1000,"Moins de 1 k€",IF($M20<=5000,"1 à 5 k€",IF($M20<=15000,"5 à 15 k€","Plus de 15 k€")))
A21: DEV-00020 | B21: 44757 | C21: 2022-07 | D21: 2022-2023 | E21: CLI-0133 | F21: Syndic | G21: Bordeaux | H21: Sophie Marchand | I21: Dépannage | J21: DP-002 | K21: Débouchage canalisation | L21: 1 | M21: 737.31 | N21: Refusé | O21: 44790 | P21: 8 | Q21: 2 | R21: =$I21 | S21: =$K21 | T21: =IFERROR(INDEX(Clients!$G$2:$G$1020,MATCH($E21,Clients!$A$2:$A$1020,0)),"") | U21: =IFERROR(INDEX(Clients!$I$2:$I$1020,MATCH($E21,Clients!$A$2:$A$1020,0)),"") | V21: =1 | W21: =IF($N21="Accepté",1,0) | X21: =$M21*$W21 | Y21: =IF($N21="En cours",0,$M21) | Z21: =IF($P21="",0,1) | AA21: =IF($P21="",0,$P21) | AB21: =IF(AND($P21<>"",$P21<=Paramètres!$C$14),1,0) | AC21: =IF($P21="","Jamais relancé",IF($P21<=3,"0-3 j",IF($P21<=7,"4-7 j",IF($P21<=15,"8-15 j","Plus de 15 j")))) | AD21: =IF($M21<=1000,"Moins de 1 k€",IF($M21<=5000,"1 à 5 k€",IF($M21<=15000,"5 à 15 k€","Plus de 15 k€")))
A22: DEV-00021 | B22: 44757 | C22: 2022-07 | D22: 2022-2023 | E22: CLI-0056 | F22: Particulier | G22: Bordeaux | H22: Sophie Marchand | I22: Plomberie | J22: PR-002 | K22: Recherche de fuite + réparation | L22: 1 | M22: 491.43 | N22: Sans réponse | O22: 44765 | P22: 9 | Q22: 0 | R22: =$I22 | S22: =$K22 | T22: =IFERROR(INDEX(Clients!$G$2:$G$1020,MATCH($E22,Clients!$A$2:$A$1020,0)),"") | U22: =IFERROR(INDEX(Clients!$I$2:$I$1020,MATCH($E22,Clients!$A$2:$A$1020,0)),"") | V22: =1 | W22: =IF($N22="Accepté",1,0) | X22: =$M22*$W22 | Y22: =IF($N22="En cours",0,$M22) | Z22: =IF($P22="",0,1) | AA22: =IF($P22="",0,$P22) | AB22: =IF(AND($P22<>"",$P22<=Paramètres!$C$14),1,0) | AC22: =IF($P22="","Jamais relancé",IF($P22<=3,"0-3 j",IF($P22<=7,"4-7 j",IF($P22<=15,"8-15 j","Plus de 15 j")))) | AD22: =IF($M22<=1000,"Moins de 1 k€",IF($M22<=5000,"1 à 5 k€",IF($M22<=15000,"5 à 15 k€","Plus de 15 k€")))
A23: DEV-00022 | B23: 44757 | C23: 2022-07 | D23: 2022-2023 | E23: CLI-0014 | F23: Particulier | G23: Bordeaux | H23: Karim Belkacem | I23: Plomberie | J23: PR-003 | K23: Réfection réseau eau appartement | L23: 1 | M23: 3207.71 | N23: Sans réponse | O23: 44769 | P23: 4 | Q23: 2 | R23: =$I23 | S23: =$K23 | T23: =IFERROR(INDEX(Clients!$G$2:$G$1020,MATCH($E23,Clients!$A$2:$A$1020,0)),"") | U23: =IFERROR(INDEX(Clients!$I$2:$I$1020,MATCH($E23,Clients!$A$2:$A$1020,0)),"") | V23: =1 | W23: =IF($N23="Accepté",1,0) | X23: =$M23*$W23 | Y23: =IF($N23="En cours",0,$M23) | Z23: =IF($P23="",0,1) | AA23: =IF($P23="",0,$P23) | AB23: =IF(AND($P23<>"",$P23<=Paramètres!$C$14),1,0) | AC23: =IF($P23="","Jamais relancé",IF($P23<=3,"0-3 j",IF($P23<=7,"4-7 j",IF($P23<=15,"8-15 j","Plus de 15 j")))) | AD23: =IF($M23<=1000,"Moins de 1 k€",IF($M23<=5000,"1 à 5 k€",IF($M23<=15000,"5 à 15 k€","Plus de 15 k€")))
A24: DEV-00023 | B24: 44760 | C24: 2022-07 | D24: 2022-2023 | E24: CLI-0061 | F24: Professionnel | G24: Toulouse | H24: Julien Fabre | I24: Électricité | J24: EL-002 | K24: Installation borne de recharge VE | L24: 1 | M24: 2265.82 | N24: Sans réponse | O24: 44798 | P24: 3 | Q24: 3 | R24: =$I24 | S24: =$K24 | T24: =IFERROR(INDEX(Clients!$G$2:$G$1020,MATCH($E24,Clients!$A$2:$A$1020,0)),"") | U24: =IFERROR(INDEX(Clients!$I$2:$I$1020,MATCH($E24,Clients!$A$2:$A$1020,0)),"") | V24: =1 | W24: =IF($N24="Accepté",1,0) | X24: =$M24*$W24 | Y24: =IF($N24="En cours",0,$M24) | Z24: =IF($P24="",0,1) | AA24: =IF($P24="",0,$P24) | AB24: =IF(AND($P24<>"",$P24<=Paramètres!$C$14),1,0) | AC24: =IF($P24="","Jamais relancé",IF($P24<=3,"0-3 j",IF($P24<=7,"4-7 j",IF($P24<=15,"8-15 j","Plus de 15 j")))) | AD24: =IF($M24<=1000,"Moins de 1 k€",IF($M24<=5000,"1 à 5 k€",IF($M24<=15000,"5 à 15 k€","Plus de 15 k€")))
A25: DEV-00024 | B25: 44762 | C25: 2022-07 | D25: 2022-2023 | E25: CLI-0026 | F25: Particulier | G25: Bordeaux | H25: Sophie Marchand | I25: Salle de bain | J25: SB-001 | K25: Rénovation salle de bain complète | L25: 1 | M25: 10132.95 | N25: Sans réponse | O25: 44806 | P25: 12 | Q25: 1 | R25: =$I25 | S25: =$K25 | T25: =IFERROR(INDEX(Clients!$G$2:$G$1020,MATCH($E25,Clients!$A$2:$A$1020,0)),"") | U25: =IFERROR(INDEX(Clients!$I$2:$I$1020,MATCH($E25,Clients!$A$2:$A$1020,0)),"") | V25: =1 | W25: =IF($N25="Accepté",1,0) | X25: =$M25*$W25 | Y25: =IF($N25="En cours",0,$M25) | Z25: =IF($P25="",0,1) | AA25: =IF($P25="",0,$P25) | AB25: =IF(AND($P25<>"",$P25<=Paramètres!$C$14),1,0) | AC25: =IF($P25="","Jamais relancé",IF($P25<=3,"0-3 j",IF($P25<=7,"4-7 j",IF($P25<=15,"8-15 j","Plus de 15 j")))) | AD25: =IF($M25<=1000,"Moins de 1 k€",IF($M25<=5000,"1 à 5 k€",IF($M25<=15000,"5 à 15 k€","Plus de 15 k€")))
A26: DEV-00025 | B26: 44763 | C26: 2022-07 | D26: 2022-2023 | E26: CLI-0002 | F26: Particulier | G26: Bordeaux | H26: Sophie Marchand | I26: Dépannage | J26: DP-003 | K26: Dépannage électrique urgence | L26: 1 | M26: 311.16 | N26: Sans réponse | O26: 44787 | Q26: 0 | R26: =$I26 | S26: =$K26 | T26: =IFERROR(INDEX(Clients!$G$2:$G$1020,MATCH($E26,Clients!$A$2:$A$1020,0)),"") | U26: =IFERROR(INDEX(Clients!$I$2:$I$1020,MATCH($E26,Clients!$A$2:$A$1020,0)),"") | V26: =1 | W26: =IF($N26="Accepté",1,0) | X26: =$M26*$W26 | Y26: =IF($N26="En cours",0,$M26) | Z26: =IF($P26="",0,1) | AA26: =IF($P26="",0,$P26) | AB26: =IF(AND($P26<>"",$P26<=Paramètres!$C$14),1,0) | AC26: =IF($P26="","Jamais relancé",IF($P26<=3,"0-3 j",IF($P26<=7,"4-7 j",IF($P26<=15,"8-15 j","Plus de 15 j")))) | AD26: =IF($M26<=1000,"Moins de 1 k€",IF($M26<=5000,"1 à 5 k€",IF($M26<=15000,"5 à 15 k€","Plus de 15 k€")))
A27: DEV-00026 | B27: 44763 | C27: 2022-07 | D27: 2022-2023 | E27: CLI-0156 | F27: Particulier | G27: Bordeaux | H27: Karim Belkacem | I27: Plomberie | J27: PR-003 | K27: Réfection réseau eau appartement | L27: 1 | M27: 3476.87 | N27: Accepté | O27: 44786 | P27: 1 | Q27: 1 | R27: =$I27 | S27: =$K27 | T27: =IFERROR(INDEX(Clients!$G$2:$G$1020,MATCH($E27,Clients!$A$2:$A$1020,0)),"") | U27: =IFERROR(INDEX(Clients!$I$2:$I$1020,MATCH($E27,Clients!$A$2:$A$1020,0)),"") | V27: =1 | W27: =IF($N27="Accepté",1,0) | X27: =$M27*$W27 | Y27: =IF($N27="En cours",0,$M27) | Z27: =IF($P27="",0,1) | AA27: =IF($P27="",0,$P27) | AB27: =IF(AND($P27<>"",$P27<=Paramètres!$C$14),1,0) | AC27: =IF($P27="","Jamais relancé",IF($P27<=3,"0-3 j",IF($P27<=7,"4-7 j",IF($P27<=15,"8-15 j","Plus de 15 j")))) | AD27: =IF($M27<=1000,"Moins de 1 k€",IF($M27<=5000,"1 à 5 k€",IF($M27<=15000,"5 à 15 k€","Plus de 15 k€")))
A28: DEV-00027 | B28: 44763 | C28: 2022-07 | D28: 2022-2023 | E28: CLI-0094 | F28: Professionnel | G28: Toulouse | H28: Julien Fabre | I28: Électricité | J28: EL-003 | K28: Rénovation électrique complète | L28: 1 | M28: 16995.08 | N28: Sans réponse | O28: 44787 | P28: 6 | Q28: 3 | R28: =$I28 | S28: =$K28 | T28: =IFERROR(INDEX(Clients!$G$2:$G$1020,MATCH($E28,Clients!$A$2:$A$1020,0)),"") | U28: =IFERROR(INDEX(Clients!$I$2:$I$1020,MATCH($E28,Clients!$A$2:$A$1020,0)),"") | V28: =1 | W28: =IF($N28="Accepté",1,0) | X28: =$M28*$W28 | Y28: =IF($N28="En cours",0,$M28) | Z28: =IF($P28="",0,1) | AA28: =IF($P28="",0,$P28) | AB28: =IF(AND($P28<>"",$P28<=Paramètres!$C$14),1,0) | AC28: =IF($P28="","Jamais relancé",IF($P28<=3,"0-3 j",IF($P28<=7,"4-7 j",IF($P28<=15,"8-15 j","Plus de 15 j")))) | AD28: =IF($M28<=1000,"Moins de 1 k€",IF($M28<=5000,"1 à 5 k€",IF($M28<=15000,"5 à 15 k€","Plus de 15 k€")))
A29: DEV-00028 | B29: 44763 | C29: 2022-07 | D29: 2022-2023 | E29: CLI-0005 | F29: Particulier | G29: Bordeaux | H29: Sophie Marchand | I29: Dépannage | J29: DP-001 | K29: Dépannage plomberie urgence | L29: 1 | M29: 262.87 | N29: Accepté | O29: 44774 | P29: 2 | Q29: 1 | R29: =$I29 | S29: =$K29 | T29: =IFERROR(INDEX(Clients!$G$2:$G$1020,MATCH($E29,Clients!$A$2:$A$1020,0)),"") | U29: =IFERROR(INDEX(Clients!$I$2:$I$1020,MATCH($E29,Clients!$A$2:$A$1020,0)),"") | V29: =1 | W29: =IF($N29="Accepté",1,0) | X29: =$M29*$W29 | Y29: =IF($N29="En cours",0,$M29) | Z29: =IF($P29="",0,1) | AA29: =IF($P29="",0,$P29) | AB29: =IF(AND($P29<>"",$P29<=Paramètres!$C$14),1,0) | AC29: =IF($P29="","Jamais relancé",IF($P29<=3,"0-3 j",IF($P29<=7,"4-7 j",IF($P29<=15,"8-15 j","Plus de 15 j")))) | AD29: =IF($M29<=1000,"Moins de 1 k€",IF($M29<=5000,"1 à 5 k€",IF($M29<=15000,"5 à 15 k€","Plus de 15 k€")))
A30: DEV-00029 | B30: 44764 | C30: 2022-07 | D30: 2022-2023 | E30: CLI-0059 | F30: Particulier | G30: Bordeaux | H30: Karim Belkacem | I30: Électricité | J30: EL-001 | K30: Mise aux normes tableau électrique | L30: 1 | M30: 1839.23 | N30: Sans réponse | O30: 44804 | P30: 1 | Q30: 3 | R30: =$I30 | S30: =$K30 | T30: =IFERROR(INDEX(Clients!$G$2:$G$1020,MATCH($E30,Clients!$A$2:$A$1020,0)),"") | U30: =IFERROR(INDEX(Clients!$I$2:$I$1020,MATCH($E30,Clients!$A$2:$A$1020,0)),"") | V30: =1 | W30: =IF($N30="Accepté",1,0) | X30: =$M30*$W30 | Y30: =IF($N30="En cours",0,$M30) | Z30: =IF($P30="",0,1) | AA30: =IF($P30="",0,$P30) | AB30: =IF(AND($P30<>"",$P30<=Paramètres!$C$14),1,0) | AC30: =IF($P30="","Jamais relancé",IF($P30<=3,"0-3 j",IF($P30<=7,"4-7 j",IF($P30<=15,"8-15 j","Plus de 15 j")))) | AD30: =IF($M30<=1000,"Moins de 1 k€",IF($M30<=5000,"1 à 5 k€",IF($M30<=15000,"5 à 15 k€","Plus de 15 k€")))
A31: DEV-00030 | B31: 44764 | C31: 2022-07 | D31: 2022-2023 | E31: CLI-0133 | F31: Syndic | G31: Bordeaux | H31: Karim Belkacem | I31: Salle de bain | J31: SB-001 | K31: Rénovation salle de bain complète | L31: 1 | M31: 17449.94 | N31: Sans réponse | O31: 44808 | P31: 5 | Q31: 4 | R31: =$I31 | S31: =$K31 | T31: =IFERROR(INDEX(Clients!$G$2:$G$1020,MATCH($E31,Clients!$A$2:$A$1020,0)),"") | U31: =IFERROR(INDEX(Clients!$I$2:$I$1020,MATCH($E31,Clients!$A$2:$A$1020,0)),"") | V31: =1 | W31: =IF($N31="Accepté",1,0) | X31: =$M31*$W31 | Y31: =IF($N31="En cours",0,$M31) | Z31: =IF($P31="",0,1) | AA31: =IF($P31="",0,$P31) | AB31: =IF(AND($P31<>"",$P31<=Paramètres!$C$14),1,0) | AC31: =IF($P31="","Jamais relancé",IF($P31<=3,"0-3 j",IF($P31<=7,"4-7 j",IF($P31<=15,"8-15 j","Plus de 15 j")))) | AD31: =IF($M31<=1000,"Moins de 1 k€",IF($M31<=5000,"1 à 5 k€",IF($M31<=15000,"5 à 15 k€","Plus de 15 k€")))
A32: DEV-00031 | B32: 44767 | C32: 2022-07 | D32: 2022-2023 | E32: CLI-0196 | F32: Particulier | G32: Bordeaux | H32: Karim Belkacem | I32: Salle de bain | J32: SB-001 | K32: Rénovation salle de bain complète | L32: 1 | M32: 10167.81 | N32: Accepté | O32: 44795 | P32: 1 | Q32: 4 | R32: =$I32 | S32: =$K32 | T32: =IFERROR(INDEX(Clients!$G$2:$G$1020,MATCH($E32,Clients!$A$2:$A$1020,0)),"") | U32: =IFERROR(INDEX(Clients!$I$2:$I$1020,MATCH($E32,Clients!$A$2:$A$1020,0)),"") | V32: =1 | W32: =IF($N32="Accepté",1,0) | X32: =$M32*$W32 | Y32: =IF($N32="En cours",0,$M32) | Z32: =IF($P32="",0,1) | AA32: =IF($P32="",0,$P32) | AB32: =IF(AND($P32<>"",$P32<=Paramètres!$C$14),1,0) | AC32: =IF($P32="","Jamais relancé",IF($P32<=3,"0-3 j",IF($P32<=7,"4-7 j",IF($P32<=15,"8-15 j","Plus de 15 j")))) | AD32: =IF($M32<=1000,"Moins de 1 k€",IF($M32<=5000,"1 à 5 k€",IF($M32<=15000,"5 à 15 k€","Plus de 15 k€")))
A33: DEV-00032 | B33: 44767 | C33: 2022-07 | D33: 2022-2023 | E33: CLI-0139 | F33: Particulier | G33: Bordeaux | H33: Sophie Marchand | I33: Salle de bain | J33: SB-001 | K33: Rénovation salle de bain complète | L33: 1 | M33: 10695.42 | N33: Sans réponse | O33: 44790 | P33: 6 | Q33: 1 | R33: =$I33 | S33: =$K33 | T33: =IFERROR(INDEX(Clients!$G$2:$G$1020,MATCH($E33,Clients!$A$2:$A$1020,0)),"") | U33: =IFERROR(INDEX(Clients!$I$2:$I$1020,MATCH($E33,Clients!$A$2:$A$1020,0)),"") | V33: =1 | W33: =IF($N33="Accepté",1,0) | X33: =$M33*$W33 | Y33: =IF($N33="En cours",0,$M33) | Z33: =IF($P33="",0,1) | AA33: =IF($P33="",0,$P33) | AB33: =IF(AND($P33<>"",$P33<=Paramètres!$C$14),1,0) | AC33: =IF($P33="","Jamais relancé",IF($P33<=3,"0-3 j",IF($P33<=7,"4-7 j",IF($P33<=15,"8-15 j","Plus de 15 j")))) | AD33: =IF($M33<=1000,"Moins de 1 k€",IF($M33<=5000,"1 à 5 k€",IF($M33<=15000,"5 à 15 k€","Plus de 15 k€")))
A34: DEV-00033 | B34: 44767 | C34: 2022-07 | D34: 2022-2023 | E34: CLI-0042 | F34: Particulier | G34: Bordeaux | H34: Karim Belkacem | I34: Salle de bain | J34: SB-001 | K34: Rénovation salle de bain complète | L34: 1 | M34: 10068.38 | N34: Refusé | O34: 44778 | Q34: 0 | R34: =$I34 | S34: =$K34 | T34: =IFERROR(INDEX(Clients!$G$2:$G$1020,MATCH($E34,Clients!$A$2:$A$1020,0)),"") | U34: =IFERROR(INDEX(Clients!$I$2:$I$1020,MATCH($E34,Clients!$A$2:$A$1020,0)),"") | V34: =1 | W34: =IF($N34="Accepté",1,0) | X34: =$M34*$W34 | Y34: =IF($N34="En cours",0,$M34) | Z34: =IF($P34="",0,1) | AA34: =IF($P34="",0,$P34) | AB34: =IF(AND($P34<>"",$P34<=Paramètres!$C$14),1,0) | AC34: =IF($P34="","Jamais relancé",IF($P34<=3,"0-3 j",IF($P34<=7,"4-7 j",IF($P34<=15,"8-15 j","Plus de 15 j")))) | AD34: =IF($M34<=1000,"Moins de 1 k€",IF($M34<=5000,"1 à 5 k€",IF($M34<=15000,"5 à 15 k€","Plus de 15 k€")))
A35: DEV-00034 | B35: 44768 | C35: 2022-07 | D35: 2022-2023 | E35: CLI-0025 | F35: Syndic | G35: Bordeaux | H35: Karim Belkacem | I35: Chauffage | J35: CH-001 | K35: Installation chaudière gaz condensation | L35: 1 | M35: 8733 | N35: Accepté | O35: 44783 | P35: 3 | Q35: 2 | R35: =$I35 | S35: =$K35 | T35: =IFERROR(INDEX(Clients!$G$2:$G$1020,MATCH($E35,Clients!$A$2:$A$1020,0)),"") | U35: =IFERROR(INDEX(Clients!$I$2:$I$1020,MATCH($E35,Clients!$A$2:$A$1020,0)),"") | V35: =1 | W35: =IF($N35="Accepté",1,0) | X35: =$M35*$W35 | Y35: =IF($N35="En cours",0,$M35) | Z35: =IF($P35="",0,1) | AA35: =IF($P35="",0,$P35) | AB35: =IF(AND($P35<>"",$P35<=Paramètres!$C$14),1,0) | AC35: =IF($P35="","Jamais relancé",IF($P35<=3,"0-3 j",IF($P35<=7,"4-7 j",IF($P35<=15,"8-15 j","Plus de 15 j")))) | AD35: =IF($M35<=1000,"Moins de 1 k€",IF($M35<=5000,"1 à 5 k€",IF($M35<=15000,"5 à 15 k€","Plus de 15 k€")))
A36: DEV-00035 | B36: 44769 | C36: 2022-07 | D36: 2022-2023 | E36: CLI-0082 | F36: Particulier | G36: Toulouse | H36: Julien Fabre | I36: Électricité | J36: EL-004 | K36: Éclairage LED locaux professionnels | L36: 1 | M36: 3416.7 | N36: Sans réponse | O36: 44783 | P36: 6 | Q36: 2 | R36: =$I36 | S36: =$K36 | T36: =IFERROR(INDEX(Clients!$G$2:$G$1020,MATCH($E36,Clients!$A$2:$A$1020,0)),"") | U36: =IFERROR(INDEX(Clients!$I$2:$I$1020,MATCH($E36,Clients!$A$2:$A$1020,0)),"") | V36: =1 | W36: =IF($N36="Accepté",1,0) | X36: =$M36*$W36 | Y36: =IF($N36="En cours",0,$M36) | Z36: =IF($P36="",0,1) | AA36: =IF($P36="",0,$P36) | AB36: =IF(AND($P36<>"",$P36<=Paramètres!$C$14),1,0) | AC36: =IF($P36="","Jamais relancé",IF($P36<=3,"0-3 j",IF($P36<=7,"4-7 j",IF($P36<=15,"8-15 j","Plus de 15 j")))) | AD36: =IF($M36<=1000,"Moins de 1 k€",IF($M36<=5000,"1 à 5 k€",IF($M36<=15000,"5 à 15 k€","Plus de 15 k€")))
A37: DEV-00036 | B37: 44769 | C37: 2022-07 | D37: 2022-2023 | E37: CLI-0052 | F37: Particulier | G37: Toulouse | H37: Julien Fabre | I37: Salle de bain | J37: SB-002 | K37: Remplacement baignoire par douche | L37: 1 | M37: 3641.62 | N37: Accepté | O37: 44801 | P37: 1 | Q37: 1 | R37: =$I37 | S37: =$K37 | T37: =IFERROR(INDEX(Clients!$G$2:$G$1020,MATCH($E37,Clients!$A$2:$A$1020,0)),"") | U37: =IFERROR(INDEX(Clients!$I$2:$I$1020,MATCH($E37,Clients!$A$2:$A$1020,0)),"") | V37: =1 | W37: =IF($N37="Accepté",1,0) | X37: =$M37*$W37 | Y37: =IF($N37="En cours",0,$M37) | Z37: =IF($P37="",0,1) | AA37: =IF($P37="",0,$P37) | AB37: =IF(AND($P37<>"",$P37<=Paramètres!$C$14),1,0) | AC37: =IF($P37="","Jamais relancé",IF($P37<=3,"0-3 j",IF($P37<=7,"4-7 j",IF($P37<=15,"8-15 j","Plus de 15 j")))) | AD37: =IF($M37<=1000,"Moins de 1 k€",IF($M37<=5000,"1 à 5 k€",IF($M37<=15000,"5 à 15 k€","Plus de 15 k€")))
A38: DEV-00037 | B38: 44770 | C38: 2022-07 | D38: 2022-2023 | E38: CLI-0036 | F38: Particulier | G38: Toulouse | H38: Julien Fabre | I38: Plomberie | J38: PR-002 | K38: Recherche de fuite + réparation | L38: 1 | M38: 422.16 | N38: Accepté | O38: 44791 | P38: 1 | Q38: 2 | R38: =$I38 | S38: =$K38 | T38: =IFERROR(INDEX(Clients!$G$2:$G$1020,MATCH($E38,Clients!$A$2:$A$1020,0)),"") | U38: =IFERROR(INDEX(Clients!$I$2:$I$1020,MATCH($E38,Clients!$A$2:$A$1020,0)),"") | V38: =1 | W38: =IF($N38="Accepté",1,0) | X38: =$M38*$W38 | Y38: =IF($N38="En cours",0,$M38) | Z38: =IF($P38="",0,1) | AA38: =IF($P38="",0,$P38) | AB38: =IF(AND($P38<>"",$P38<=Paramètres!$C$14),1,0) | AC38: =IF($P38="","Jamais relancé",IF($P38<=3,"0-3 j",IF($P38<=7,"4-7 j",IF($P38<=15,"8-15 j","Plus de 15 j")))) | AD38: =IF($M38<=1000,"Moins de 1 k€",IF($M38<=5000,"1 à 5 k€",IF($M38<=15000,"5 à 15 k€","Plus de 15 k€")))
A39: DEV-00038 | B39: 44770 | C39: 2022-07 | D39: 2022-2023 | E39: CLI-0158 | F39: Particulier | G39: Bordeaux | H39: Karim Belkacem | I39: Électricité | J39: EL-002 | K39: Installation borne de recharge VE | L39: 1 | M39: 1418.22 | N39: Accepté | O39: 44773 | P39: 1 | Q39: 1 | R39: =$I39 | S39: =$K39 | T39: =IFERROR(INDEX(Clients!$G$2:$G$1020,MATCH($E39,Clients!$A$2:$A$1020,0)),"") | U39: =IFERROR(INDEX(Clients!$I$2:$I$1020,MATCH($E39,Clients!$A$2:$A$1020,0)),"") | V39: =1 | W39: =IF($N39="Accepté",1,0) | X39: =$M39*$W39 | Y39: =IF($N39="En cours",0,$M39) | Z39: =IF($P39="",0,1) | AA39: =IF($P39="",0,$P39) | AB39: =IF(AND($P39<>"",$P39<=Paramètres!$C$14),1,0) | AC39: =IF($P39="","Jamais relancé",IF($P39<=3,"0-3 j",IF($P39<=7,"4-7 j",IF($P39<=15,"8-15 j","Plus de 15 j")))) | AD39: =IF($M39<=1000,"Moins de 1 k€",IF($M39<=5000,"1 à 5 k€",IF($M39<=15000,"5 à 15 k€","Plus de 15 k€")))
A40: DEV-00039 | B40: 44771 | C40: 2022-07 | D40: 2022-2023 | E40: CLI-0005 | F40: Particulier | G40: Bordeaux | H40: Karim Belkacem | I40: Salle de bain | J40: SB-001 | K40: Rénovation salle de bain complète | L40: 1 | M40: 10620.92 | N40: Sans réponse | O40: 44800 | Q40: 0 | R40: =$I40 | S40: =$K40 | T40: =IFERROR(INDEX(Clients!$G$2:$G$1020,MATCH($E40,Clients!$A$2:$A$1020,0)),"") | U40: =IFERROR(INDEX(Clients!$I$2:$I$1020,MATCH($E40,Clients!$A$2:$A$1020,0)),"") | V40: =1 | W40: =IF($N40="Accepté",1,0) | X40: =$M40*$W40 | Y40: =IF($N40="En cours",0,$M40) | Z40: =IF($P40="",0,1) | AA40: =IF($P40="",0,$P40) | AB40: =IF(AND($P40<>"",$P40<=Paramètres!$C$14),1,0) | AC40: =IF($P40="","Jamais relancé",IF($P40<=3,"0-3 j",IF($P40<=7,"4-7 j",IF($P40<=15,"8-15 j","Plus de 15 j")))) | AD40: =IF($M40<=1000,"Moins de 1 k€",IF($M40<=5000,"1 à 5 k€",IF($M40<=15000,"5 à 15 k€","Plus de 15 k€")))
A41: DEV-00040 | B41: 44774 | C41: 2022-08 | D41: 2022-2023 | E41: CLI-0178 | F41: Particulier | G41: Toulouse | H41: Julien Fabre | I41: Plomberie | J41: PR-002 | K41: Recherche de fuite + réparation | L41: 1 | M41: 395.72 | N41: Sans réponse | O41: 44808 | P41: 7 | Q41: 3 | R41: =$I41 | S41: =$K41 | T41: =IFERROR(INDEX(Clients!$G$2:$G$1020,MATCH($E41,Clients!$A$2:$A$1020,0)),"") | U41: =IFERROR(INDEX(Clients!$I$2:$I$1020,MATCH($E41,Clients!$A$2:$A$1020,0)),"") | V41: =1 | W41: =IF($N41="Accepté",1,0) | X41: =$M41*$W41 | Y41: =IF($N41="En cours",0,$M41) | Z41: =IF($P41="",0,1) | AA41: =IF($P41="",0,$P41) | AB41: =IF(AND($P41<>"",$P41<=Paramètres!$C$14),1,0) | AC41: =IF($P41="","Jamais relancé",IF($P41<=3,"0-3 j",IF($P41<=7,"4-7 j",IF($P41<=15,"8-15 j","Plus de 15 j")))) | AD41: =IF($M41<=1000,"Moins de 1 k€",IF($M41<=5000,"1 à 5 k€",IF($M41<=15000,"5 à 15 k€","Plus de 15 k€")))
A42: DEV-00041 | B42: 44774 | C42: 2022-08 | D42: 2022-2023 | E42: CLI-0105 | F42: Particulier | G42: Toulouse | H42: Julien Fabre | I42: Chauffage | J42: CH-005 | K42: Désembouage circuit chauffage | L42: 2 | M42: 1528.12 | N42: Sans réponse | O42: 44801 | Q42: 0 | R42: =$I42 | S42: =$K42 | T42: =IFERROR(INDEX(Clients!$G$2:$G$1020,MATCH($E42,Clients!$A$2:$A$1020,0)),"") | U42: =IFERROR(INDEX(Clients!$I$2:$I$1020,MATCH($E42,Clients!$A$2:$A$1020,0)),"") | V42: =1 | W42: =IF($N42="Accepté",1,0) | X42: =$M42*$W42 | Y42: =IF($N42="En cours",0,$M42) | Z42: =IF($P42="",0,1) | AA42: =IF($P42="",0,$P42) | AB42: =IF(AND($P42<>"",$P42<=Paramètres!$C$14),1,0) | AC42: =IF($P42="","Jamais relancé",IF($P42<=3,"0-3 j",IF($P42<=7,"4-7 j",IF($P42<=15,"8-15 j","Plus de 15 j")))) | AD42: =IF($M42<=1000,"Moins de 1 k€",IF($M42<=5000,"1 à 5 k€",IF($M42<=15000,"5 à 15 k€","Plus de 15 k€")))
A43: DEV-00042 | B43: 44774 | C43: 2022-08 | D43: 2022-2023 | E43: CLI-0177 | F43: Particulier | G43: Toulouse | H43: Julien Fabre | I43: Plomberie | J43: PR-002 | K43: Recherche de fuite + réparation | L43: 1 | M43: 387 | N43: Sans réponse | O43: 44792 | P43: 8 | Q43: 1 | R43: =$I43 | S43: =$K43 | T43: =IFERROR(INDEX(Clients!$G$2:$G$1020,MATCH($E43,Clients!$A$2:$A$1020,0)),"") | U43: =IFERROR(INDEX(Clients!$I$2:$I$1020,MATCH($E43,Clients!$A$2:$A$1020,0)),"") | V43: =1 | W43: =IF($N43="Accepté",1,0) | X43: =$M43*$W43 | Y43: =IF($N43="En cours",0,$M43) | Z43: =IF($P43="",0,1) | AA43: =IF($P43="",0,$P43) | AB43: =IF(AND($P43<>"",$P43<=Paramètres!$C$14),1,0) | AC43: =IF($P43="","Jamais relancé",IF($P43<=3,"0-3 j",IF($P43<=7,"4-7 j",IF($P43<=15,"8-15 j","Plus de 15 j")))) | AD43: =IF($M43<=1000,"Moins de 1 k€",IF($M43<=5000,"1 à 5 k€",IF($M43<=15000,"5 à 15 k€","Plus de 15 k€")))
A44: DEV-00043 | B44: 44774 | C44: 2022-08 | D44: 2022-2023 | E44: CLI-0127 | F44: Particulier | G44: Toulouse | H44: Julien Fabre | I44: Plomberie | J44: PR-001 | K44: Remplacement chauffe-eau 200 L | L44: 2 | M44: 2377.95 | N44: Accepté | O44: 44815 | P44: 4 | Q44: 1 | R44: =$I44 | S44: =$K44 | T44: =IFERROR(INDEX(Clients!$G$2:$G$1020,MATCH($E44,Clients!$A$2:$A$1020,0)),"") | U44: =IFERROR(INDEX(Clients!$I$2:$I$1020,MATCH($E44,Clients!$A$2:$A$1020,0)),"") | V44: =1 | W44: =IF($N44="Accepté",1,0) | X44: =$M44*$W44 | Y44: =IF($N44="En cours",0,$M44) | Z44: =IF($P44="",0,1) | AA44: =IF($P44="",0,$P44) | AB44: =IF(AND($P44<>"",$P44<=Paramètres!$C$14),1,0) | AC44: =IF($P44="","Jamais relancé",IF($P44<=3,"0-3 j",IF($P44<=7,"4-7 j",IF($P44<=15,"8-15 j","Plus de 15 j")))) | AD44: =IF($M44<=1000,"Moins de 1 k€",IF($M44<=5000,"1 à 5 k€",IF($M44<=15000,"5 à 15 k€","Plus de 15 k€")))
A45: DEV-00044 | B45: 44775 | C45: 2022-08 | D45: 2022-2023 | E45: CLI-0069 | F45: Professionnel | G45: Toulouse | H45: Julien Fabre | I45: Plomberie | J45: PR-001 | K45: Remplacement chauffe-eau 200 L | L45: 2 | M45: 3750.58 | N45: Refusé | O45: 44788 | P45: 2 | Q45: 2 | R45: =$I45 | S45: =$K45 | T45: =IFERROR(INDEX(Clients!$G$2:$G$1020,MATCH($E45,Clients!$A$2:$A$1020,0)),"") | U45: =IFERROR(INDEX(Clients!$I$2:$I$1020,MATCH($E45,Clients!$A$2:$A$1020,0)),"") | V45: =1 | W45: =IF($N45="Accepté",1,0) | X45: =$M45*$W45 | Y45: =IF($N45="En cours",0,$M45) | Z45: =IF($P45="",0,1) | AA45: =IF($P45="",0,$P45) | AB45: =IF(AND($P45<>"",$P45<=Paramètres!$C$14),1,0) | AC45: =IF($P45="","Jamais relancé",IF($P45<=3,"0-3 j",IF($P45<=7,"4-7 j",IF($P45<=15,"8-15 j","Plus de 15 j")))) | AD45: =IF($M45<=1000,"Moins de 1 k€",IF($M45<=5000,"1 à 5 k€",IF($M45<=15000,"5 à 15 k€","Plus de 15 k€")))
A46: DEV-00045 | B46: 44775 | C46: 2022-08 | D46: 2022-2023 | E46: CLI-0159 | F46: Syndic | G46: Bordeaux | H46: Karim Belkacem | I46: Plomberie | J46: PR-004 | K46: Remplacement colonne d'évacuation | L46: 1 | M46: 11164.87 | N46: Sans réponse | O46: 44789 | P46: 1 | Q46: 2 | R46: =$I46 | S46: =$K46 | T46: =IFERROR(INDEX(Clients!$G$2:$G$1020,MATCH($E46,Clients!$A$2:$A$1020,0)),"") | U46: =IFERROR(INDEX(Clients!$I$2:$I$1020,MATCH($E46,Clients!$A$2:$A$1020,0)),"") | V46: =1 | W46: =IF($N46="Accepté",1,0) | X46: =$M46*$W46 | Y46: =IF($N46="En cours",0,$M46) | Z46: =IF($P46="",0,1) | AA46: =IF($P46="",0,$P46) | AB46: =IF(AND($P46<>"",$P46<=Paramètres!$C$14),1,0) | AC46: =IF($P46="","Jamais relancé",IF($P46<=3,"0-3 j",IF($P46<=7,"4-7 j",IF($P46<=15,"8-15 j","Plus de 15 j")))) | AD46: =IF($M46<=1000,"Moins de 1 k€",IF($M46<=5000,"1 à 5 k€",IF($M46<=15000,"5 à 15 k€","Plus de 15 k€")))
A47: DEV-00046 | B47: 44775 | C47: 2022-08 | D47: 2022-2023 | E47: CLI-0153 | F47: Particulier | G47: Bordeaux | H47: Karim Belkacem | I47: Chauffage | J47: CH-004 | K47: Remplacement radiateurs (lot de 5) | L47: 1 | M47: 2211.72 | N47: Refusé | O47: 44812 | P47: 1 | Q47: 2 | R47: =$I47 | S47: =$K47 | T47: =IFERROR(INDEX(Clients!$G$2:$G$1020,MATCH($E47,Clients!$A$2:$A$1020,0)),"") | U47: =IFERROR(INDEX(Clients!$I$2:$I$1020,MATCH($E47,Clients!$A$2:$A$1020,0)),"") | V47: =1 | W47: =IF($N47="Accepté",1,0) | X47: =$M47*$W47 | Y47: =IF($N47="En cours",0,$M47) | Z47: =IF($P47="",0,1) | AA47: =IF($P47="",0,$P47) | AB47: =IF(AND($P47<>"",$P47<=Paramètres!$C$14),1,0) | AC47: =IF($P47="","Jamais relancé",IF($P47<=3,"0-3 j",IF($P47<=7,"4-7 j",IF($P47<=15,"8-15 j","Plus de 15 j")))) | AD47: =IF($M47<=1000,"Moins de 1 k€",IF($M47<=5000,"1 à 5 k€",IF($M47<=15000,"5 à 15 k€","Plus de 15 k€")))
A48: DEV-00047 | B48: 44776 | C48: 2022-08 | D48: 2022-2023 | E48: CLI-0114 | F48: Particulier | G48: Bordeaux | H48: Karim Belkacem | I48: Électricité | J48: EL-001 | K48: Mise aux normes tableau électrique | L48: 3 | M48: 4741.05 | N48: Accepté | O48: 44800 | P48: 3 | Q48: 1 | R48: =$I48 | S48: =$K48 | T48: =IFERROR(INDEX(Clients!$G$2:$G$1020,MATCH($E48,Clients!$A$2:$A$1020,0)),"") | U48: =IFERROR(INDEX(Clients!$I$2:$I$1020,MATCH($E48,Clients!$A$2:$A$1020,0)),"") | V48: =1 | W48: =IF($N48="Accepté",1,0) | X48: =$M48*$W48 | Y48: =IF($N48="En cours",0,$M48) | Z48: =IF($P48="",0,1) | AA48: =IF($P48="",0,$P48) | AB48: =IF(AND($P48<>"",$P48<=Paramètres!$C$14),1,0) | AC48: =IF($P48="","Jamais relancé",IF($P48<=3,"0-3 j",IF($P48<=7,"4-7 j",IF($P48<=15,"8-15 j","Plus de 15 j")))) | AD48: =IF($M48<=1000,"Moins de 1 k€",IF($M48<=5000,"1 à 5 k€",IF($M48<=15000,"5 à 15 k€","Plus de 15 k€")))
A49: DEV-00048 | B49: 44776 | C49: 2022-08 | D49: 2022-2023 | E49: CLI-0095 | F49: Particulier | G49: Bordeaux | H49: Sophie Marchand | I49: Dépannage | J49: DP-001 | K49: Dépannage plomberie urgence | L49: 1 | M49: 269.28 | N49: Accepté | O49: 44792 | P49: 6 | Q49: 1 | R49: =$I49 | S49: =$K49 | T49: =IFERROR(INDEX(Clients!$G$2:$G$1020,MATCH($E49,Clients!$A$2:$A$1020,0)),"") | U49: =IFERROR(INDEX(Clients!$I$2:$I$1020,MATCH($E49,Clients!$A$2:$A$1020,0)),"") | V49: =1 | W49: =IF($N49="Accepté",1,0) | X49: =$M49*$W49 | Y49: =IF($N49="En cours",0,$M49) | Z49: =IF($P49="",0,1) | AA49: =IF($P49="",0,$P49) | AB49: =IF(AND($P49<>"",$P49<=Paramètres!$C$14),1,0) | AC49: =IF($P49="","Jamais relancé",IF($P49<=3,"0-3 j",IF($P49<=7,"4-7 j",IF($P49<=15,"8-15 j","Plus de 15 j")))) | AD49: =IF($M49<=1000,"Moins de 1 k€",IF($M49<=5000,"1 à 5 k€",IF($M49<=15000,"5 à 15 k€","Plus de 15 k€")))
A50: DEV-00049 | B50: 44777 | C50: 2022-08 | D50: 2022-2023 | E50: CLI-0070 | F50: Particulier | G50: Toulouse | H50: Julien Fabre | I50: Chauffage | J50: CH-001 | K50: Installation chaudière gaz condensation | L50: 1 | M50: 5151.21 | N50: Refusé | O50: 44797 | P50: 2 | Q50: 2 | R50: =$I50 | S50: =$K50 | T50: =IFERROR(INDEX(Clients!$G$2:$G$1020,MATCH($E50,Clients!$A$2:$A$1020,0)),"") | U50: =IFERROR(INDEX(Clients!$I$2:$I$1020,MATCH($E50,Clients!$A$2:$A$1020,0)),"") | V50: =1 | W50: =IF($N50="Accepté",1,0) | X50: =$M50*$W50 | Y50: =IF($N50="En cours",0,$M50) | Z50: =IF($P50="",0,1) | AA50: =IF($P50="",0,$P50) | AB50: =IF(AND($P50<>"",$P50<=Paramètres!$C$14),1,0) | AC50: =IF($P50="","Jamais relancé",IF($P50<=3,"0-3 j",IF($P50<=7,"4-7 j",IF($P50<=15,"8-15 j","Plus de 15 j")))) | AD50: =IF($M50<=1000,"Moins de 1 k€",IF($M50<=5000,"1 à 5 k€",IF($M50<=15000,"5 à 15 k€","Plus de 15 k€")))
A51: DEV-00050 | B51: 44777 | C51: 2022-08 | D51: 2022-2023 | E51: CLI-0097 | F51: Particulier | G51: Toulouse | H51: Julien Fabre | I51: Salle de bain | J51: SB-002 | K51: Remplacement baignoire par douche | L51: 1 | M51: 3084.15 | N51: Refusé | O51: 44806 | P51: 11 | Q51: 2 | R51: =$I51 | S51: =$K51 | T51: =IFERROR(INDEX(Clients!$G$2:$G$1020,MATCH($E51,Clients!$A$2:$A$1020,0)),"") | U51: =IFERROR(INDEX(Clients!$I$2:$I$1020,MATCH($E51,Clients!$A$2:$A$1020,0)),"") | V51: =1 | W51: =IF($N51="Accepté",1,0) | X51: =$M51*$W51 | Y51: =IF($N51="En cours",0,$M51) | Z51: =IF($P51="",0,1) | AA51: =IF($P51="",0,$P51) | AB51: =IF(AND($P51<>"",$P51<=Paramètres!$C$14),1,0) | AC51: =IF($P51="","Jamais relancé",IF($P51<=3,"0-3 j",IF($P51<=7,"4-7 j",IF($P51<=15,"8-15 j","Plus de 15 j")))) | AD51: =IF($M51<=1000,"Moins de 1 k€",IF($M51<=5000,"1 à 5 k€",IF($M51<=15000,"5 à 15 k€","Plus de 15 k€")))
A52: DEV-00051 | B52: 44781 | C52: 2022-08 | D52: 2022-2023 | E52: CLI-0055 | F52: Professionnel | G52: Bordeaux | H52: Karim Belkacem | I52: Dépannage | J52: DP-001 | K52: Dépannage plomberie urgence | L52: 1 | M52: 446.64 | N52: Refusé | O52: 44798 | P52: 5 | Q52: 1 | R52: =$I52 | S52: =$K52 | T52: =IFERROR(INDEX(Clients!$G$2:$G$1020,MATCH($E52,Clients!$A$2:$A$1020,0)),"") | U52: =IFERROR(INDEX(Clients!$I$2:$I$1020,MATCH($E52,Clients!$A$2:$A$1020,0)),"") | V52: =1 | W52: =IF($N52="Accepté",1,0) | X52: =$M52*$W52 | Y52: =IF($N52="En cours",0,$M52) | Z52: =IF($P52="",0,1) | AA52: =IF($P52="",0,$P52) | AB52: =IF(AND($P52<>"",$P52<=Paramètres!$C$14),1,0) | AC52: =IF($P52="","Jamais relancé",IF($P52<=3,"0-3 j",IF($P52<=7,"4-7 j",IF($P52<=15,"8-15 j","Plus de 15 j")))) | AD52: =IF($M52<=1000,"Moins de 1 k€",IF($M52<=5000,"1 à 5 k€",IF($M52<=15000,"5 à 15 k€","Plus de 15 k€")))
A53: DEV-00052 | B53: 44782 | C53: 2022-08 | D53: 2022-2023 | E53: CLI-0154 | F53: Particulier | G53: Bordeaux | H53: Karim Belkacem | I53: Dépannage | J53: DP-004 | K53: Remise en service chaudière | L53: 1 | M53: 222.49 | N53: Accepté | O53: 44805 | P53: 1 | Q53: 2 | R53: =$I53 | S53: =$K53 | T53: =IFERROR(INDEX(Clients!$G$2:$G$1020,MATCH($E53,Clients!$A$2:$A$1020,0)),"") | U53: =IFERROR(INDEX(Clients!$I$2:$I$1020,MATCH($E53,Clients!$A$2:$A$1020,0)),"") | V53: =1 | W53: =IF($N53="Accepté",1,0) | X53: =$M53*$W53 | Y53: =IF($N53="En cours",0,$M53) | Z53: =IF($P53="",0,1) | AA53: =IF($P53="",0,$P53) | AB53: =IF(AND($P53<>"",$P53<=Paramètres!$C$14),1,0) | AC53: =IF($P53="","Jamais relancé",IF($P53<=3,"0-3 j",IF($P53<=7,"4-7 j",IF($P53<=15,"8-15 j","Plus de 15 j")))) | AD53: =IF($M53<=1000,"Moins de 1 k€",IF($M53<=5000,"1 à 5 k€",IF($M53<=15000,"5 à 15 k€","Plus de 15 k€")))
A54: DEV-00053 | B54: 44782 | C54: 2022-08 | D54: 2022-2023 | E54: CLI-0155 | F54: Particulier | G54: Bordeaux | H54: Sophie Marchand | I54: Chauffage | J54: CH-004 | K54: Remplacement radiateurs (lot de 5) | L54: 1 | M54: 2634.9 | N54: Sans réponse | O54: 44815 | P54: 5 | Q54: 3 | R54: =$I54 | S54: =$K54 | T54: =IFERROR(INDEX(Clients!$G$2:$G$1020,MATCH($E54,Clients!$A$2:$A$1020,0)),"") | U54: =IFERROR(INDEX(Clients!$I$2:$I$1020,MATCH($E54,Clients!$A$2:$A$1020,0)),"") | V54: =1 | W54: =IF($N54="Accepté",1,0) | X54: =$M54*$W54 | Y54: =IF($N54="En cours",0,$M54) | Z54: =IF($P54="",0,1) | AA54: =IF($P54="",0,$P54) | AB54: =IF(AND($P54<>"",$P54<=Paramètres!$C$14),1,0) | AC54: =IF($P54="","Jamais relancé",IF($P54<=3,"0-3 j",IF($P54<=7,"4-7 j",IF($P54<=15,"8-15 j","Plus de 15 j")))) | AD54: =IF($M54<=1000,"Moins de 1 k€",IF($M54<=5000,"1 à 5 k€",IF($M54<=15000,"5 à 15 k€","Plus de 15 k€")))
A55: DEV-00054 | B55: 44783 | C55: 2022-08 | D55: 2022-2023 | E55: CLI-0067 | F55: Professionnel | G55: Bordeaux | H55: Karim Belkacem | I55: Salle de bain | J55: SB-001 | K55: Rénovation salle de bain complète | L55: 1 | M55: 16749.18 | N55: Accepté | O55: 44805 | P55: 3 | Q55: 2 | R55: =$I55 | S55: =$K55 | T55: =IFERROR(INDEX(Clients!$G$2:$G$1020,MATCH($E55,Clients!$A$2:$A$1020,0)),"") | U55: =IFERROR(INDEX(Clients!$I$2:$I$1020,MATCH($E55,Clients!$A$2:$A$1020,0)),"") | V55: =1 | W55: =IF($N55="Accepté",1,0) | X55: =$M55*$W55 | Y55: =IF($N55="En cours",0,$M55) | Z55: =IF($P55="",0,1) | AA55: =IF($P55="",0,$P55) | AB55: =IF(AND($P55<>"",$P55<=Paramètres!$C$14),1,0) | AC55: =IF($P55="","Jamais relancé",IF($P55<=3,"0-3 j",IF($P55<=7,"4-7 j",IF($P55<=15,"8-15 j","Plus de 15 j")))) | AD55: =IF($M55<=1000,"Moins de 1 k€",IF($M55<=5000,"1 à 5 k€",IF($M55<=15000,"5 à 15 k€","Plus de 15 k€")))
A56: DEV-00055 | B56: 44784 | C56: 2022-08 | D56: 2022-2023 | E56: CLI-0079 | F56: Particulier | G56: Bordeaux | H56: Karim Belkacem | I56: Dépannage | J56: DP-004 | K56: Remise en service chaudière | L56: 1 | M56: 196.89 | N56: Accepté | O56: 44819 | Q56: 0 | R56: =$I56 | S56: =$K56 | T56: =IFERROR(INDEX(Clients!$G$2:$G$1020,MATCH($E56,Clients!$A$2:$A$1020,0)),"") | U56: =IFERROR(INDEX(Clients!$I$2:$I$1020,MATCH($E56,Clients!$A$2:$A$1020,0)),"") | V56: =1 | W56: =IF($N56="Accepté",1,0) | X56: =$M56*$W56 | Y56: =IF($N56="En cours",0,$M56) | Z56: =IF($P56="",0,1) | AA56: =IF($P56="",0,$P56) | AB56: =IF(AND($P56<>"",$P56<=Paramètres!$C$14),1,0) | AC56: =IF($P56="","Jamais relancé",IF($P56<=3,"0-3 j",IF($P56<=7,"4-7 j",IF($P56<=15,"8-15 j","Plus de 15 j")))) | AD56: =IF($M56<=1000,"Moins de 1 k€",IF($M56<=5000,"1 à 5 k€",IF($M56<=15000,"5 à 15 k€","Plus de 15 k€")))
A57: DEV-00056 | B57: 44785 | C57: 2022-08 | D57: 2022-2023 | E57: CLI-0052 | F57: Particulier | G57: Toulouse | H57: Julien Fabre | I57: Dépannage | J57: DP-002 | K57: Débouchage canalisation | L57: 2 | M57: 702.51 | N57: Refusé | O57: 44806 | P57: 5 | Q57: 1 | R57: =$I57 | S57: =$K57 | T57: =IFERROR(INDEX(Clients!$G$2:$G$1020,MATCH($E57,Clients!$A$2:$A$1020,0)),"") | U57: =IFERROR(INDEX(Clients!$I$2:$I$1020,MATCH($E57,Clients!$A$2:$A$1020,0)),"") | V57: =1 | W57: =IF($N57="Accepté",1,0) | X57: =$M57*$W57 | Y57: =IF($N57="En cours",0,$M57) | Z57: =IF($P57="",0,1) | AA57: =IF($P57="",0,$P57) | AB57: =IF(AND($P57<>"",$P57<=Paramètres!$C$14),1,0) | AC57: =IF($P57="","Jamais relancé",IF($P57<=3,"0-3 j",IF($P57<=7,"4-7 j",IF($P57<=15,"8-15 j","Plus de 15 j")))) | AD57: =IF($M57<=1000,"Moins de 1 k€",IF($M57<=5000,"1 à 5 k€",IF($M57<=15000,"5 à 15 k€","Plus de 15 k€")))
A58: DEV-00057 | B58: 44788 | C58: 2022-08 | D58: 2022-2023 | E58: CLI-0085 | F58: Particulier | G58: Toulouse | H58: Julien Fabre | I58: Chauffage | J58: CH-003 | K58: Installation pompe à chaleur air/eau | L58: 1 | M58: 14114.35 | N58: Refusé | O58: 44809 | Q58: 0 | R58: =$I58 | S58: =$K58 | T58: =IFERROR(INDEX(Clients!$G$2:$G$1020,MATCH($E58,Clients!$A$2:$A$1020,0)),"") | U58: =IFERROR(INDEX(Clients!$I$2:$I$1020,MATCH($E58,Clients!$A$2:$A$1020,0)),"") | V58: =1 | W58: =IF($N58="Accepté",1,0) | X58: =$M58*$W58 | Y58: =IF($N58="En cours",0,$M58) | Z58: =IF($P58="",0,1) | AA58: =IF($P58="",0,$P58) | AB58: =IF(AND($P58<>"",$P58<=Paramètres!$C$14),1,0) | AC58: =IF($P58="","Jamais relancé",IF($P58<=3,"0-3 j",IF($P58<=7,"4-7 j",IF($P58<=15,"8-15 j","Plus de 15 j")))) | AD58: =IF($M58<=1000,"Moins de 1 k€",IF($M58<=5000,"1 à 5 k€",IF($M58<=15000,"5 à 15 k€","Plus de 15 k€")))
A59: DEV-00058 | B59: 44788 | C59: 2022-08 | D59: 2022-2023 | E59: CLI-0109 | F59: Professionnel | G59: Toulouse | H59: Julien Fabre | I59: Électricité | J59: EL-001 | K59: Mise aux normes tableau électrique | L59: 1 | M59: 3135.61 | N59: Accepté | O59: 44823 | P59: 2 | Q59: 3 | R59: =$I59 | S59: =$K59 | T59: =IFERROR(INDEX(Clients!$G$2:$G$1020,MATCH($E59,Clients!$A$2:$A$1020,0)),"") | U59: =IFERROR(INDEX(Clients!$I$2:$I$1020,MATCH($E59,Clients!$A$2:$A$1020,0)),"") | V59: =1 | W59: =IF($N59="Accepté",1,0) | X59: =$M59*$W59 | Y59: =IF($N59="En cours",0,$M59) | Z59: =IF($P59="",0,1) | AA59: =IF($P59="",0,$P59) | AB59: =IF(AND($P59<>"",$P59<=Paramètres!$C$14),1,0) | AC59: =IF($P59="","Jamais relancé",IF($P59<=3,"0-3 j",IF($P59<=7,"4-7 j",IF($P59<=15,"8-15 j","Plus de 15 j")))) | AD59: =IF($M59<=1000,"Moins de 1 k€",IF($M59<=5000,"1 à 5 k€",IF($M59<=15000,"5 à 15 k€","Plus de 15 k€")))
A60: DEV-00059 | B60: 44789 | C60: 2022-08 | D60: 2022-2023 | E60: CLI-0122 | F60: Particulier | G60: Toulouse | H60: Julien Fabre | I60: Dépannage | J60: DP-004 | K60: Remise en service chaudière | L60: 1 | M60: 199.33 | N60: Accepté | O60: 44800 | P60: 1 | Q60: 1 | R60: =$I60 | S60: =$K60 | T60: =IFERROR(INDEX(Clients!$G$2:$G$1020,MATCH($E60,Clients!$A$2:$A$1020,0)),"") | U60: =IFERROR(INDEX(Clients!$I$2:$I$1020,MATCH($E60,Clients!$A$2:$A$1020,0)),"") | V60: =1 | W60: =IF($N60="Accepté",1,0) | X60: =$M60*$W60 | Y60: =IF($N60="En cours",0,$M60) | Z60: =IF($P60="",0,1) | AA60: =IF($P60="",0,$P60) | AB60: =IF(AND($P60<>"",$P60<=Paramètres!$C$14),1,0) | AC60: =IF($P60="","Jamais relancé",IF($P60<=3,"0-3 j",IF($P60<=7,"4-7 j",IF($P60<=15,"8-15 j","Plus de 15 j")))) | AD60: =IF($M60<=1000,"Moins de 1 k€",IF($M60<=5000,"1 à 5 k€",IF($M60<=15000,"5 à 15 k€","Plus de 15 k€")))
A61: DEV-00060 | B61: 44789 | C61: 2022-08 | D61: 2022-2023 | E61: CLI-0185 | F61: Particulier | G61: Bordeaux | H61: Karim Belkacem | I61: Dépannage | J61: DP-001 | K61: Dépannage plomberie urgence | L61: 2 | M61: 544.21 | N61: Accepté | O61: 44815 | P61: 3 | Q61: 1 | R61: =$I61 | S61: =$K61 | T61: =IFERROR(INDEX(Clients!$G$2:$G$1020,MATCH($E61,Clients!$A$2:$A$1020,0)),"") | U61: =IFERROR(INDEX(Clients!$I$2:$I$1020,MATCH($E61,Clients!$A$2:$A$1020,0)),"") | V61: =1 | W61: =IF($N61="Accepté",1,0) | X61: =$M61*$W61 | Y61: =IF($N61="En cours",0,$M61) | Z61: =IF($P61="",0,1) | AA61: =IF($P61="",0,$P61) | AB61: =IF(AND($P61<>"",$P61<=Paramètres!$C$14),1,0) | AC61: =IF($P61="","Jamais relancé",IF($P61<=3,"0-3 j",IF($P61<=7,"4-7 j",IF($P61<=15,"8-15 j","Plus de 15 j")))) | AD61: =IF($M61<=1000,"Moins de 1 k€",IF($M61<=5000,"1 à 5 k€",IF($M61<=15000,"5 à 15 k€","Plus de 15 k€")))
A62: DEV-00061 | B62: 44789 | C62: 2022-08 | D62: 2022-2023 | E62: CLI-0163 | F62: Particulier | G62: Toulouse | H62: Julien Fabre | I62: Dépannage | J62: DP-003 | K62: Dépannage électrique urgence | L62: 2 | M62: 542.8 | N62: Accepté | O62: 44820 | P62: 7 | Q62: 2 | R62: =$I62 | S62: =$K62 | T62: =IFERROR(INDEX(Clients!$G$2:$G$1020,MATCH($E62,Clients!$A$2:$A$1020,0)),"") | U62: =IFERROR(INDEX(Clients!$I$2:$I$1020,MATCH($E62,Clients!$A$2:$A$1020,0)),"") | V62: =1 | W62: =IF($N62="Accepté",1,0) | X62: =$M62*$W62 | Y62: =IF($N62="En cours",0,$M62) | Z62: =IF($P62="",0,1) | AA62: =IF($P62="",0,$P62) | AB62: =IF(AND($P62<>"",$P62<=Paramètres!$C$14),1,0) | AC62: =IF($P62="","Jamais relancé",IF($P62<=3,"0-3 j",IF($P62<=7,"4-7 j",IF($P62<=15,"8-15 j","Plus de 15 j")))) | AD62: =IF($M62<=1000,"Moins de 1 k€",IF($M62<=5000,"1 à 5 k€",IF($M62<=15000,"5 à 15 k€","Plus de 15 k€")))
A63: DEV-00062 | B63: 44790 | C63: 2022-08 | D63: 2022-2023 | E63: CLI-0140 | F63: Syndic | G63: Toulouse | H63: Julien Fabre | I63: Électricité | J63: EL-002 | K63: Installation borne de recharge VE | L63: 1 | M63: 3465.25 | N63: Accepté | O63: 44802 | P63: 1 | Q63: 1 | R63: =$I63 | S63: =$K63 | T63: =IFERROR(INDEX(Clients!$G$2:$G$1020,MATCH($E63,Clients!$A$2:$A$1020,0)),"") | U63: =IFERROR(INDEX(Clients!$I$2:$I$1020,MATCH($E63,Clients!$A$2:$A$1020,0)),"") | V63: =1 | W63: =IF($N63="Accepté",1,0) | X63: =$M63*$W63 | Y63: =IF($N63="En cours",0,$M63) | Z63: =IF($P63="",0,1) | AA63: =IF($P63="",0,$P63) | AB63: =IF(AND($P63<>"",$P63<=Paramètres!$C$14),1,0) | AC63: =IF($P63="","Jamais relancé",IF($P63<=3,"0-3 j",IF($P63<=7,"4-7 j",IF($P63<=15,"8-15 j","Plus de 15 j")))) | AD63: =IF($M63<=1000,"Moins de 1 k€",IF($M63<=5000,"1 à 5 k€",IF($M63<=15000,"5 à 15 k€","Plus de 15 k€")))
A64: DEV-00063 | B64: 44790 | C64: 2022-08 | D64: 2022-2023 | E64: CLI-0040 | F64: Professionnel | G64: Bordeaux | H64: Sophie Marchand | I64: Chauffage | J64: CH-005 | K64: Désembouage circuit chauffage | L64: 1 | M64: 1249.77 | N64: Sans réponse | O64: 44803 | Q64: 0 | R64: =$I64 | S64: =$K64 | T64: =IFERROR(INDEX(Clients!$G$2:$G$1020,MATCH($E64,Clients!$A$2:$A$1020,0)),"") | U64: =IFERROR(INDEX(Clients!$I$2:$I$1020,MATCH($E64,Clients!$A$2:$A$1020,0)),"") | V64: =1 | W64: =IF($N64="Accepté",1,0) | X64: =$M64*$W64 | Y64: =IF($N64="En cours",0,$M64) | Z64: =IF($P64="",0,1) | AA64: =IF($P64="",0,$P64) | AB64: =IF(AND($P64<>"",$P64<=Paramètres!$C$14),1,0) | AC64: =IF($P64="","Jamais relancé",IF($P64<=3,"0-3 j",IF($P64<=7,"4-7 j",IF($P64<=15,"8-15 j","Plus de 15 j")))) | AD64: =IF($M64<=1000,"Moins de 1 k€",IF($M64<=5000,"1 à 5 k€",IF($M64<=15000,"5 à 15 k€","Plus de 15 k€")))
A65: DEV-00064 | B65: 44791 | C65: 2022-08 | D65: 2022-2023 | E65: CLI-0003 | F65: Professionnel | G65: Toulouse | H65: Julien Fabre | I65: Plomberie | J65: PR-003 | K65: Réfection réseau eau appartement | L65: 1 | M65: 5777.72 | N65: Accepté | O65: 44798 | P65: 6 | Q65: 1 | R65: =$I65 | S65: =$K65 | T65: =IFERROR(INDEX(Clients!$G$2:$G$1020,MATCH($E65,Clients!$A$2:$A$1020,0)),"") | U65: =IFERROR(INDEX(Clients!$I$2:$I$1020,MATCH($E65,Clients!$A$2:$A$1020,0)),"") | V65: =1 | W65: =IF($N65="Accepté",1,0) | X65: =$M65*$W65 | Y65: =IF($N65="En cours",0,$M65) | Z65: =IF($P65="",0,1) | AA65: =IF($P65="",0,$P65) | AB65: =IF(AND($P65<>"",$P65<=Paramètres!$C$14),1,0) | AC65: =IF($P65="","Jamais relancé",IF($P65<=3,"0-3 j",IF($P65<=7,"4-7 j",IF($P65<=15,"8-15 j","Plus de 15 j")))) | AD65: =IF($M65<=1000,"Moins de 1 k€",IF($M65<=5000,"1 à 5 k€",IF($M65<=15000,"5 à 15 k€","Plus de 15 k€")))
A66: DEV-00065 | B66: 44791 | C66: 2022-08 | D66: 2022-2023 | E66: CLI-0141 | F66: Particulier | G66: Bordeaux | H66: Karim Belkacem | I66: Salle de bain | J66: SB-001 | K66: Rénovation salle de bain complète | L66: 1 | M66: 9765.22 | N66: Refusé | O66: 44802 | Q66: 0 | R66: =$I66 | S66: =$K66 | T66: =IFERROR(INDEX(Clients!$G$2:$G$1020,MATCH($E66,Clients!$A$2:$A$1020,0)),"") | U66: =IFERROR(INDEX(Clients!$I$2:$I$1020,MATCH($E66,Clients!$A$2:$A$1020,0)),"") | V66: =1 | W66: =IF($N66="Accepté",1,0) | X66: =$M66*$W66 | Y66: =IF($N66="En cours",0,$M66) | Z66: =IF($P66="",0,1) | AA66: =IF($P66="",0,$P66) | AB66: =IF(AND($P66<>"",$P66<=Paramètres!$C$14),1,0) | AC66: =IF($P66="","Jamais relancé",IF($P66<=3,"0-3 j",IF($P66<=7,"4-7 j",IF($P66<=15,"8-15 j","Plus de 15 j")))) | AD66: =IF($M66<=1000,"Moins de 1 k€",IF($M66<=5000,"1 à 5 k€",IF($M66<=15000,"5 à 15 k€","Plus de 15 k€")))
A67: DEV-00066 | B67: 44792 | C67: 2022-08 | D67: 2022-2023 | E67: CLI-0140 | F67: Syndic | G67: Toulouse | H67: Julien Fabre | I67: Chauffage | J67: CH-005 | K67: Désembouage circuit chauffage | L67: 1 | M67: 1629.88 | N67: Sans réponse | O67: 44823 | Q67: 0 | R67: =$I67 | S67: =$K67 | T67: =IFERROR(INDEX(Clients!$G$2:$G$1020,MATCH($E67,Clients!$A$2:$A$1020,0)),"") | U67: =IFERROR(INDEX(Clients!$I$2:$I$1020,MATCH($E67,Clients!$A$2:$A$1020,0)),"") | V67: =1 | W67: =IF($N67="Accepté",1,0) | X67: =$M67*$W67 | Y67: =IF($N67="En cours",0,$M67) | Z67: =IF($P67="",0,1) | AA67: =IF($P67="",0,$P67) | AB67: =IF(AND($P67<>"",$P67<=Paramètres!$C$14),1,0) | AC67: =IF($P67="","Jamais relancé",IF($P67<=3,"0-3 j",IF($P67<=7,"4-7 j",IF($P67<=15,"8-15 j","Plus de 15 j")))) | AD67: =IF($M67<=1000,"Moins de 1 k€",IF($M67<=5000,"1 à 5 k€",IF($M67<=15000,"5 à 15 k€","Plus de 15 k€")))
A68: DEV-00067 | B68: 44795 | C68: 2022-08 | D68: 2022-2023 | E68: CLI-0121 | F68: Syndic | G68: Toulouse | H68: Julien Fabre | I68: Salle de bain | J68: SB-001 | K68: Rénovation salle de bain complète | L68: 1 | M68: 20649.1 | N68: Sans réponse | O68: 44838 | P68: 11 | Q68: 2 | R68: =$I68 | S68: =$K68 | T68: =IFERROR(INDEX(Clients!$G$2:$G$1020,MATCH($E68,Clients!$A$2:$A$1020,0)),"") | U68: =IFERROR(INDEX(Clients!$I$2:$I$1020,MATCH($E68,Clients!$A$2:$A$1020,0)),"") | V68: =1 | W68: =IF($N68="Accepté",1,0) | X68: =$M68*$W68 | Y68: =IF($N68="En cours",0,$M68) | Z68: =IF($P68="",0,1) | AA68: =IF($P68="",0,$P68) | AB68: =IF(AND($P68<>"",$P68<=Paramètres!$C$14),1,0) | AC68: =IF($P68="","Jamais relancé",IF($P68<=3,"0-3 j",IF($P68<=7,"4-7 j",IF($P68<=15,"8-15 j","Plus de 15 j")))) | AD68: =IF($M68<=1000,"Moins de 1 k€",IF($M68<=5000,"1 à 5 k€",IF($M68<=15000,"5 à 15 k€","Plus de 15 k€")))
A69: DEV-00068 | B69: 44795 | C69: 2022-08 | D69: 2022-2023 | E69: CLI-0027 | F69: Particulier | G69: Toulouse | H69: Julien Fabre | I69: Plomberie | J69: PR-001 | K69: Remplacement chauffe-eau 200 L | L69: 1 | M69: 1089.83 | N69: Sans réponse | O69: 44800 | P69: 3 | Q69: 1 | R69: =$I69 | S69: =$K69 | T69: =IFERROR(INDEX(Clients!$G$2:$G$1020,MATCH($E69,Clients!$A$2:$A$1020,0)),"") | U69: =IFERROR(INDEX(Clients!$I$2:$I$1020,MATCH($E69,Clients!$A$2:$A$1020,0)),"") | V69: =1 | W69: =IF($N69="Accepté",1,0) | X69: =$M69*$W69 | Y69: =IF($N69="En cours",0,$M69) | Z69: =IF($P69="",0,1) | AA69: =IF($P69="",0,$P69) | AB69: =IF(AND($P69<>"",$P69<=Paramètres!$C$14),1,0) | AC69: =IF($P69="","Jamais relancé",IF($P69<=3,"0-3 j",IF($P69<=7,"4-7 j",IF($P69<=15,"8-15 j","Plus de 15 j")))) | AD69: =IF($M69<=1000,"Moins de 1 k€",IF($M69<=5000,"1 à 5 k€",IF($M69<=15000,"5 à 15 k€","Plus de 15 k€")))
A70: DEV-00069 | B70: 44797 | C70: 2022-08 | D70: 2022-2023 | E70: CLI-0182 | F70: Professionnel | G70: Bordeaux | H70: Karim Belkacem | I70: Plomberie | J70: PR-004 | K70: Remplacement colonne d'évacuation | L70: 1 | M70: 10086.79 | N70: Refusé | O70: 44800 | P70: 1 | Q70: 1 | R70: =$I70 | S70: =$K70 | T70: =IFERROR(INDEX(Clients!$G$2:$G$1020,MATCH($E70,Clients!$A$2:$A$1020,0)),"") | U70: =IFERROR(INDEX(Clients!$I$2:$I$1020,MATCH($E70,Clients!$A$2:$A$1020,0)),"") | V70: =1 | W70: =IF($N70="Accepté",1,0) | X70: =$M70*$W70 | Y70: =IF($N70="En cours",0,$M70) | Z70: =IF($P70="",0,1) | AA70: =IF($P70="",0,$P70) | AB70: =IF(AND($P70<>"",$P70<=Paramètres!$C$14),1,0) | AC70: =IF($P70="","Jamais relancé",IF($P70<=3,"0-3 j",IF($P70<=7,"4-7 j",IF($P70<=15,"8-15 j","Plus de 15 j")))) | AD70: =IF($M70<=1000,"Moins de 1 k€",IF($M70<=5000,"1 à 5 k€",IF($M70<=15000,"5 à 15 k€","Plus de 15 k€")))
A71: DEV-00070 | B71: 44797 | C71: 2022-08 | D71: 2022-2023 | E71: CLI-0160 | F71: Particulier | G71: Bordeaux | H71: Sophie Marchand | I71: Salle de bain | J71: SB-002 | K71: Remplacement baignoire par douche | L71: 1 | M71: 3772.29 | N71: Sans réponse | O71: 44802 | Q71: 0 | R71: =$I71 | S71: =$K71 | T71: =IFERROR(INDEX(Clients!$G$2:$G$1020,MATCH($E71,Clients!$A$2:$A$1020,0)),"") | U71: =IFERROR(INDEX(Clients!$I$2:$I$1020,MATCH($E71,Clients!$A$2:$A$1020,0)),"") | V71: =1 | W71: =IF($N71="Accepté",1,0) | X71: =$M71*$W71 | Y71: =IF($N71="En cours",0,$M71) | Z71: =IF($P71="",0,1) | AA71: =IF($P71="",0,$P71) | AB71: =IF(AND($P71<>"",$P71<=Paramètres!$C$14),1,0) | AC71: =IF($P71="","Jamais relancé",IF($P71<=3,"0-3 j",IF($P71<=7,"4-7 j",IF($P71<=15,"8-15 j","Plus de 15 j")))) | AD71: =IF($M71<=1000,"Moins de 1 k€",IF($M71<=5000,"1 à 5 k€",IF($M71<=15000,"5 à 15 k€","Plus de 15 k€")))
A72: DEV-00071 | B72: 44798 | C72: 2022-08 | D72: 2022-2023 | E72: CLI-0036 | F72: Particulier | G72: Toulouse | H72: Julien Fabre | I72: Plomberie | J72: PR-003 | K72: Réfection réseau eau appartement | L72: 1 | M72: 2720.69 | N72: Refusé | O72: 44816 | P72: 5 | Q72: 1 | R72: =$I72 | S72: =$K72 | T72: =IFERROR(INDEX(Clients!$G$2:$G$1020,MATCH($E72,Clients!$A$2:$A$1020,0)),"") | U72: =IFERROR(INDEX(Clients!$I$2:$I$1020,MATCH($E72,Clients!$A$2:$A$1020,0)),"") | V72: =1 | W72: =IF($N72="Accepté",1,0) | X72: =$M72*$W72 | Y72: =IF($N72="En cours",0,$M72) | Z72: =IF($P72="",0,1) | AA72: =IF($P72="",0,$P72) | AB72: =IF(AND($P72<>"",$P72<=Paramètres!$C$14),1,0) | AC72: =IF($P72="","Jamais relancé",IF($P72<=3,"0-3 j",IF($P72<=7,"4-7 j",IF($P72<=15,"8-15 j","Plus de 15 j")))) | AD72: =IF($M72<=1000,"Moins de 1 k€",IF($M72<=5000,"1 à 5 k€",IF($M72<=15000,"5 à 15 k€","Plus de 15 k€")))
A73: DEV-00072 | B73: 44798 | C73: 2022-08 | D73: 2022-2023 | E73: CLI-0167 | F73: Particulier | G73: Toulouse | H73: Julien Fabre | I73: Plomberie | J73: PR-002 | K73: Recherche de fuite + réparation | L73: 3 | M73: 1235.22 | N73: Sans réponse | O73: 44809 | P73: 5 | Q73: 1 | R73: =$I73 | S73: =$K73 | T73: =IFERROR(INDEX(Clients!$G$2:$G$1020,MATCH($E73,Clients!$A$2:$A$1020,0)),"") | U73: =IFERROR(INDEX(Clients!$I$2:$I$1020,MATCH($E73,Clients!$A$2:$A$1020,0)),"") | V73: =1 | W73: =IF($N73="Accepté",1,0) | X73: =$M73*$W73 | Y73: =IF($N73="En cours",0,$M73) | Z73: =IF($P73="",0,1) | AA73: =IF($P73="",0,$P73) | AB73: =IF(AND($P73<>"",$P73<=Paramètres!$C$14),1,0) | AC73: =IF($P73="","Jamais relancé",IF($P73<=3,"0-3 j",IF($P73<=7,"4-7 j",IF($P73<=15,"8-15 j","Plus de 15 j")))) | AD73: =IF($M73<=1000,"Moins de 1 k€",IF($M73<=5000,"1 à 5 k€",IF($M73<=15000,"5 à 15 k€","Plus de 15 k€")))
A74: DEV-00073 | B74: 44802 | C74: 2022-08 | D74: 2022-2023 | E74: CLI-0008 | F74: Particulier | G74: Toulouse | H74: Julien Fabre | I74: Chauffage | J74: CH-005 | K74: Désembouage circuit chauffage | L74: 1 | M74: 736.14 | N74: Accepté | O74: 44828 | P74: 1 | Q74: 1 | R74: =$I74 | S74: =$K74 | T74: =IFERROR(INDEX(Clients!$G$2:$G$1020,MATCH($E74,Clients!$A$2:$A$1020,0)),"") | U74: =IFERROR(INDEX(Clients!$I$2:$I$1020,MATCH($E74,Clients!$A$2:$A$1020,0)),"") | V74: =1 | W74: =IF($N74="Accepté",1,0) | X74: =$M74*$W74 | Y74: =IF($N74="En cours",0,$M74) | Z74: =IF($P74="",0,1) | AA74: =IF($P74="",0,$P74) | AB74: =IF(AND($P74<>"",$P74<=Paramètres!$C$14),1,0) | AC74: =IF($P74="","Jamais relancé",IF($P74<=3,"0-3 j",IF($P74<=7,"4-7 j",IF($P74<=15,"8-15 j","Plus de 15 j")))) | AD74: =IF($M74<=1000,"Moins de 1 k€",IF($M74<=5000,"1 à 5 k€",IF($M74<=15000,"5 à 15 k€","Plus de 15 k€")))
A75: DEV-00074 | B75: 44802 | C75: 2022-08 | D75: 2022-2023 | E75: CLI-0080 | F75: Particulier | G75: Bordeaux | H75: Karim Belkacem | I75: Plomberie | J75: PR-003 | K75: Réfection réseau eau appartement | L75: 1 | M75: 3456.85 | N75: Sans réponse | O75: 44825 | P75: 2 | Q75: 1 | R75: =$I75 | S75: =$K75 | T75: =IFERROR(INDEX(Clients!$G$2:$G$1020,MATCH($E75,Clients!$A$2:$A$1020,0)),"") | U75: =IFERROR(INDEX(Clients!$I$2:$I$1020,MATCH($E75,Clients!$A$2:$A$1020,0)),"") | V75: =1 | W75: =IF($N75="Accepté",1,0) | X75: =$M75*$W75 | Y75: =IF($N75="En cours",0,$M75) | Z75: =IF($P75="",0,1) | AA75: =IF($P75="",0,$P75) | AB75: =IF(AND($P75<>"",$P75<=Paramètres!$C$14),1,0) | AC75: =IF($P75="","Jamais relancé",IF($P75<=3,"0-3 j",IF($P75<=7,"4-7 j",IF($P75<=15,"8-15 j","Plus de 15 j")))) | AD75: =IF($M75<=1000,"Moins de 1 k€",IF($M75<=5000,"1 à 5 k€",IF($M75<=15000,"5 à 15 k€","Plus de 15 k€")))
A76: DEV-00075 | B76: 44802 | C76: 2022-08 | D76: 2022-2023 | E76: CLI-0063 | F76: Particulier | G76: Bordeaux | H76: Karim Belkacem | I76: Électricité | J76: EL-004 | K76: Éclairage LED locaux professionnels | L76: 1 | M76: 3634.55 | N76: Sans réponse | O76: 44819 | P76: 1 | Q76: 2 | R76: =$I76 | S76: =$K76 | T76: =IFERROR(INDEX(Clients!$G$2:$G$1020,MATCH($E76,Clients!$A$2:$A$1020,0)),"") | U76: =IFERROR(INDEX(Clients!$I$2:$I$1020,MATCH($E76,Clients!$A$2:$A$1020,0)),"") | V76: =1 | W76: =IF($N76="Accepté",1,0) | X76: =$M76*$W76 | Y76: =IF($N76="En cours",0,$M76) | Z76: =IF($P76="",0,1) | AA76: =IF($P76="",0,$P76) | AB76: =IF(AND($P76<>"",$P76<=Paramètres!$C$14),1,0) | AC76: =IF($P76="","Jamais relancé",IF($P76<=3,"0-3 j",IF($P76<=7,"4-7 j",IF($P76<=15,"8-15 j","Plus de 15 j")))) | AD76: =IF($M76<=1000,"Moins de 1 k€",IF($M76<=5000,"1 à 5 k€",IF($M76<=15000,"5 à 15 k€","Plus de 15 k€")))
A77: DEV-00076 | B77: 44803 | C77: 2022-08 | D77: 2022-2023 | E77: CLI-0209 | F77: Particulier | G77: Toulouse | H77: Julien Fabre | I77: Électricité | J77: EL-004 | K77: Éclairage LED locaux professionnels | L77: 1 | M77: 3348.7 | N77: Sans réponse | O77: 44809 | P77: 6 | Q77: 1 | R77: =$I77 | S77: =$K77 | T77: =IFERROR(INDEX(Clients!$G$2:$G$1020,MATCH($E77,Clients!$A$2:$A$1020,0)),"") | U77: =IFERROR(INDEX(Clients!$I$2:$I$1020,MATCH($E77,Clients!$A$2:$A$1020,0)),"") | V77: =1 | W77: =IF($N77="Accepté",1,0) | X77: =$M77*$W77 | Y77: =IF($N77="En cours",0,$M77) | Z77: =IF($P77="",0,1) | AA77: =IF($P77="",0,$P77) | AB77: =IF(AND($P77<>"",$P77<=Paramètres!$C$14),1,0) | AC77: =IF($P77="","Jamais relancé",IF($P77<=3,"0-3 j",IF($P77<=7,"4-7 j",IF($P77<=15,"8-15 j","Plus de 15 j")))) | AD77: =IF($M77<=1000,"Moins de 1 k€",IF($M77<=5000,"1 à 5 k€",IF($M77<=15000,"5 à 15 k€","Plus de 15 k€")))
A78: DEV-00077 | B78: 44804 | C78: 2022-08 | D78: 2022-2023 | E78: CLI-0046 | F78: Syndic | G78: Toulouse | H78: Julien Fabre | I78: Dépannage | J78: DP-001 | K78: Dépannage plomberie urgence | L78: 1 | M78: 529.64 | N78: Accepté | O78: 44822 | P78: 6 | Q78: 3 | R78: =$I78 | S78: =$K78 | T78: =IFERROR(INDEX(Clients!$G$2:$G$1020,MATCH($E78,Clients!$A$2:$A$1020,0)),"") | U78: =IFERROR(INDEX(Clients!$I$2:$I$1020,MATCH($E78,Clients!$A$2:$A$1020,0)),"") | V78: =1 | W78: =IF($N78="Accepté",1,0) | X78: =$M78*$W78 | Y78: =IF($N78="En cours",0,$M78) | Z78: =IF($P78="",0,1) | AA78: =IF($P78="",0,$P78) | AB78: =IF(AND($P78<>"",$P78<=Paramètres!$C$14),1,0) | AC78: =IF($P78="","Jamais relancé",IF($P78<=3,"0-3 j",IF($P78<=7,"4-7 j",IF($P78<=15,"8-15 j","Plus de 15 j")))) | AD78: =IF($M78<=1000,"Moins de 1 k€",IF($M78<=5000,"1 à 5 k€",IF($M78<=15000,"5 à 15 k€","Plus de 15 k€")))
A79: DEV-00078 | B79: 44804 | C79: 2022-08 | D79: 2022-2023 | E79: CLI-0005 | F79: Particulier | G79: Bordeaux | H79: Karim Belkacem | I79: Plomberie | J79: PR-001 | K79: Remplacement chauffe-eau 200 L | L79: 2 | M79: 2693.16 | N79: Sans réponse | O79: 44829 | P79: 13 | Q79: 1 | R79: =$I79 | S79: =$K79 | T79: =IFERROR(INDEX(Clients!$G$2:$G$1020,MATCH($E79,Clients!$A$2:$A$1020,0)),"") | U79: =IFERROR(INDEX(Clients!$I$2:$I$1020,MATCH($E79,Clients!$A$2:$A$1020,0)),"") | V79: =1 | W79: =IF($N79="Accepté",1,0) | X79: =$M79*$W79 | Y79: =IF($N79="En cours",0,$M79) | Z79: =IF($P79="",0,1) | AA79: =IF($P79="",0,$P79) | AB79: =IF(AND($P79<>"",$P79<=Paramètres!$C$14),1,0) | AC79: =IF($P79="","Jamais relancé",IF($P79<=3,"0-3 j",IF($P79<=7,"4-7 j",IF($P79<=15,"8-15 j","Plus de 15 j")))) | AD79: =IF($M79<=1000,"Moins de 1 k€",IF($M79<=5000,"1 à 5 k€",IF($M79<=15000,"5 à 15 k€","Plus de 15 k€")))
A80: DEV-00079 | B80: 44805 | C80: 2022-09 | D80: 2022-2023 | E80: CLI-0166 | F80: Particulier | G80: Bordeaux | H80: Sophie Marchand | I80: Électricité | J80: EL-001 | K80: Mise aux normes tableau électrique | L80: 1 | M80: 1575.87 | N80: Accepté | O80: 44841 | P80: 6 | Q80: 1 | R80: =$I80 | S80: =$K80 | T80: =IFERROR(INDEX(Clients!$G$2:$G$1020,MATCH($E80,Clients!$A$2:$A$1020,0)),"") | U80: =IFERROR(INDEX(Clients!$I$2:$I$1020,MATCH($E80,Clients!$A$2:$A$1020,0)),"") | V80: =1 | W80: =IF($N80="Accepté",1,0) | X80: =$M80*$W80 | Y80: =IF($N80="En cours",0,$M80) | Z80: =IF($P80="",0,1) | AA80: =IF($P80="",0,$P80) | AB80: =IF(AND($P80<>"",$P80<=Paramètres!$C$14),1,0) | AC80: =IF($P80="","Jamais relancé",IF($P80<=3,"0-3 j",IF($P80<=7,"4-7 j",IF($P80<=15,"8-15 j","Plus de 15 j")))) | AD80: =IF($M80<=1000,"Moins de 1 k€",IF($M80<=5000,"1 à 5 k€",IF($M80<=15000,"5 à 15 k€","Plus de 15 k€")))
A81: DEV-00080 | B81: 44806 | C81: 2022-09 | D81: 2022-2023 | E81: CLI-0047 | F81: Particulier | G81: Bordeaux | H81: Karim Belkacem | I81: Chauffage | J81: CH-003 | K81: Installation pompe à chaleur air/eau | L81: 1 | M81: 12318.47 | N81: Accepté | O81: 44833 | P81: 4 | Q81: 3 | R81: =$I81 | S81: =$K81 | T81: =IFERROR(INDEX(Clients!$G$2:$G$1020,MATCH($E81,Clients!$A$2:$A$1020,0)),"") | U81: =IFERROR(INDEX(Clients!$I$2:$I$1020,MATCH($E81,Clients!$A$2:$A$1020,0)),"") | V81: =1 | W81: =IF($N81="Accepté",1,0) | X81: =$M81*$W81 | Y81: =IF($N81="En cours",0,$M81) | Z81: =IF($P81="",0,1) | AA81: =IF($P81="",0,$P81) | AB81: =IF(AND($P81<>"",$P81<=Paramètres!$C$14),1,0) | AC81: =IF($P81="","Jamais relancé",IF($P81<=3,"0-3 j",IF($P81<=7,"4-7 j",IF($P81<=15,"8-15 j","Plus de 15 j")))) | AD81: =IF($M81<=1000,"Moins de 1 k€",IF($M81<=5000,"1 à 5 k€",IF($M81<=15000,"5 à 15 k€","Plus de 15 k€")))
A82: DEV-00081 | B82: 44806 | C82: 2022-09 | D82: 2022-2023 | E82: CLI-0068 | F82: Particulier | G82: Bordeaux | H82: Sophie Marchand | I82: Chauffage | J82: CH-001 | K82: Installation chaudière gaz condensation | L82: 1 | M82: 5067.76 | N82: Accepté | O82: 44822 | P82: 8 | Q82: 2 | R82: =$I82 | S82: =$K82 | T82: =IFERROR(INDEX(Clients!$G$2:$G$1020,MATCH($E82,Clients!$A$2:$A$1020,0)),"") | U82: =IFERROR(INDEX(Clients!$I$2:$I$1020,MATCH($E82,Clients!$A$2:$A$1020,0)),"") | V82: =1 | W82: =IF($N82="Accepté",1,0) | X82: =$M82*$W82 | Y82: =IF($N82="En cours",0,$M82) | Z82: =IF($P82="",0,1) | AA82: =IF($P82="",0,$P82) | AB82: =IF(AND($P82<>"",$P82<=Paramètres!$C$14),1,0) | AC82: =IF($P82="","Jamais relancé",IF($P82<=3,"0-3 j",IF($P82<=7,"4-7 j",IF($P82<=15,"8-15 j","Plus de 15 j")))) | AD82: =IF($M82<=1000,"Moins de 1 k€",IF($M82<=5000,"1 à 5 k€",IF($M82<=15000,"5 à 15 k€","Plus de 15 k€")))
A83: DEV-00082 | B83: 44806 | C83: 2022-09 | D83: 2022-2023 | E83: CLI-0065 | F83: Particulier | G83: Bordeaux | H83: Karim Belkacem | I83: Chauffage | J83: CH-005 | K83: Désembouage circuit chauffage | L83: 1 | M83: 644.61 | N83: Sans réponse | O83: 44833 | Q83: 0 | R83: =$I83 | S83: =$K83 | T83: =IFERROR(INDEX(Clients!$G$2:$G$1020,MATCH($E83,Clients!$A$2:$A$1020,0)),"") | U83: =IFERROR(INDEX(Clients!$I$2:$I$1020,MATCH($E83,Clients!$A$2:$A$1020,0)),"") | V83: =1 | W83: =IF($N83="Accepté",1,0) | X83: =$M83*$W83 | Y83: =IF($N83="En cours",0,$M83) | Z83: =IF($P83="",0,1) | AA83: =IF($P83="",0,$P83) | AB83: =IF(AND($P83<>"",$P83<=Paramètres!$C$14),1,0) | AC83: =IF($P83="","Jamais relancé",IF($P83<=3,"0-3 j",IF($P83<=7,"4-7 j",IF($P83<=15,"8-15 j","Plus de 15 j")))) | AD83: =IF($M83<=1000,"Moins de 1 k€",IF($M83<=5000,"1 à 5 k€",IF($M83<=15000,"5 à 15 k€","Plus de 15 k€")))
A84: DEV-00083 | B84: 44809 | C84: 2022-09 | D84: 2022-2023 | E84: CLI-0213 | F84: Professionnel | G84: Bordeaux | H84: Sophie Marchand | I84: Salle de bain | J84: SB-002 | K84: Remplacement baignoire par douche | L84: 1 | M84: 6485.38 | N84: Sans réponse | O84: 44829 | Q84: 0 | R84: =$I84 | S84: =$K84 | T84: =IFERROR(INDEX(Clients!$G$2:$G$1020,MATCH($E84,Clients!$A$2:$A$1020,0)),"") | U84: =IFERROR(INDEX(Clients!$I$2:$I$1020,MATCH($E84,Clients!$A$2:$A$1020,0)),"") | V84: =1 | W84: =IF($N84="Accepté",1,0) | X84: =$M84*$W84 | Y84: =IF($N84="En cours",0,$M84) | Z84: =IF($P84="",0,1) | AA84: =IF($P84="",0,$P84) | AB84: =IF(AND($P84<>"",$P84<=Paramètres!$C$14),1,0) | AC84: =IF($P84="","Jamais relancé",IF($P84<=3,"0-3 j",IF($P84<=7,"4-7 j",IF($P84<=15,"8-15 j","Plus de 15 j")))) | AD84: =IF($M84<=1000,"Moins de 1 k€",IF($M84<=5000,"1 à 5 k€",IF($M84<=15000,"5 à 15 k€","Plus de 15 k€")))
A85: DEV-00084 | B85: 44809 | C85: 2022-09 | D85: 2022-2023 | E85: CLI-0008 | F85: Particulier | G85: Toulouse | H85: Julien Fabre | I85: Électricité | J85: EL-002 | K85: Installation borne de recharge VE | L85: 1 | M85: 1276.18 | N85: Accepté | O85: 44840 | P85: 3 | Q85: 1 | R85: =$I85 | S85: =$K85 | T85: =IFERROR(INDEX(Clients!$G$2:$G$1020,MATCH($E85,Clients!$A$2:$A$1020,0)),"") | U85: =IFERROR(INDEX(Clients!$I$2:$I$1020,MATCH($E85,Clients!$A$2:$A$1020,0)),"") | V85: =1 | W85: =IF($N85="Accepté",1,0) | X85: =$M85*$W85 | Y85: =IF($N85="En cours",0,$M85) | Z85: =IF($P85="",0,1) | AA85: =IF($P85="",0,$P85) | AB85: =IF(AND($P85<>"",$P85<=Paramètres!$C$14),1,0) | AC85: =IF($P85="","Jamais relancé",IF($P85<=3,"0-3 j",IF($P85<=7,"4-7 j",IF($P85<=15,"8-15 j","Plus de 15 j")))) | AD85: =IF($M85<=1000,"Moins de 1 k€",IF($M85<=5000,"1 à 5 k€",IF($M85<=15000,"5 à 15 k€","Plus de 15 k€")))
A86: DEV-00085 | B86: 44810 | C86: 2022-09 | D86: 2022-2023 | E86: CLI-0170 | F86: Particulier | G86: Toulouse | H86: Julien Fabre | I86: Salle de bain | J86: SB-002 | K86: Remplacement baignoire par douche | L86: 1 | M86: 3220.4 | N86: Accepté | O86: 44829 | P86: 5 | Q86: 2 | R86: =$I86 | S86: =$K86 | T86: =IFERROR(INDEX(Clients!$G$2:$G$1020,MATCH($E86,Clients!$A$2:$A$1020,0)),"") | U86: =IFERROR(INDEX(Clients!$I$2:$I$1020,MATCH($E86,Clients!$A$2:$A$1020,0)),"") | V86: =1 | W86: =IF($N86="Accepté",1,0) | X86: =$M86*$W86 | Y86: =IF($N86="En cours",0,$M86) | Z86: =IF($P86="",0,1) | AA86: =IF($P86="",0,$P86) | AB86: =IF(AND($P86<>"",$P86<=Paramètres!$C$14),1,0) | AC86: =IF($P86="","Jamais relancé",IF($P86<=3,"0-3 j",IF($P86<=7,"4-7 j",IF($P86<=15,"8-15 j","Plus de 15 j")))) | AD86: =IF($M86<=1000,"Moins de 1 k€",IF($M86<=5000,"1 à 5 k€",IF($M86<=15000,"5 à 15 k€","Plus de 15 k€")))
A87: DEV-00086 | B87: 44810 | C87: 2022-09 | D87: 2022-2023 | E87: CLI-0131 | F87: Particulier | G87: Toulouse | H87: Julien Fabre | I87: Chauffage | J87: CH-005 | K87: Désembouage circuit chauffage | L87: 1 | M87: 733.99 | N87: Accepté | O87: 44837 | P87: 2 | Q87: 2 | R87: =$I87 | S87: =$K87 | T87: =IFERROR(INDEX(Clients!$G$2:$G$1020,MATCH($E87,Clients!$A$2:$A$1020,0)),"") | U87: =IFERROR(INDEX(Clients!$I$2:$I$1020,MATCH($E87,Clients!$A$2:$A$1020,0)),"") | V87: =1 | W87: =IF($N87="Accepté",1,0) | X87: =$M87*$W87 | Y87: =IF($N87="En cours",0,$M87) | Z87: =IF($P87="",0,1) | AA87: =IF($P87="",0,$P87) | AB87: =IF(AND($P87<>"",$P87<=Paramètres!$C$14),1,0) | AC87: =IF($P87="","Jamais relancé",IF($P87<=3,"0-3 j",IF($P87<=7,"4-7 j",IF($P87<=15,"8-15 j","Plus de 15 j")))) | AD87: =IF($M87<=1000,"Moins de 1 k€",IF($M87<=5000,"1 à 5 k€",IF($M87<=15000,"5 à 15 k€","Plus de 15 k€")))
A88: DEV-00087 | B88: 44811 | C88: 2022-09 | D88: 2022-2023 | E88: CLI-0148 | F88: Particulier | G88: Bordeaux | H88: Karim Belkacem | I88: Plomberie | J88: PR-001 | K88: Remplacement chauffe-eau 200 L | L88: 1 | M88: 1053.03 | N88: Sans réponse | O88: 44825 | P88: 4 | Q88: 1 | R88: =$I88 | S88: =$K88 | T88: =IFERROR(INDEX(Clients!$G$2:$G$1020,MATCH($E88,Clients!$A$2:$A$1020,0)),"") | U88: =IFERROR(INDEX(Clients!$I$2:$I$1020,MATCH($E88,Clients!$A$2:$A$1020,0)),"") | V88: =1 | W88: =IF($N88="Accepté",1,0) | X88: =$M88*$W88 | Y88: =IF($N88="En cours",0,$M88) | Z88: =IF($P88="",0,1) | AA88: =IF($P88="",0,$P88) | AB88: =IF(AND($P88<>"",$P88<=Paramètres!$C$14),1,0) | AC88: =IF($P88="","Jamais relancé",IF($P88<=3,"0-3 j",IF($P88<=7,"4-7 j",IF($P88<=15,"8-15 j","Plus de 15 j")))) | AD88: =IF($M88<=1000,"Moins de 1 k€",IF($M88<=5000,"1 à 5 k€",IF($M88<=15000,"5 à 15 k€","Plus de 15 k€")))
A89: DEV-00088 | B89: 44812 | C89: 2022-09 | D89: 2022-2023 | E89: CLI-0002 | F89: Particulier | G89: Bordeaux | H89: Sophie Marchand | I89: Plomberie | J89: PR-003 | K89: Réfection réseau eau appartement | L89: 1 | M89: 3179.39 | N89: Refusé | O89: 44828 | P89: 1 | Q89: 2 | R89: =$I89 | S89: =$K89 | T89: =IFERROR(INDEX(Clients!$G$2:$G$1020,MATCH($E89,Clients!$A$2:$A$1020,0)),"") | U89: =IFERROR(INDEX(Clients!$I$2:$I$1020,MATCH($E89,Clients!$A$2:$A$1020,0)),"") | V89: =1 | W89: =IF($N89="Accepté",1,0) | X89: =$M89*$W89 | Y89: =IF($N89="En cours",0,$M89) | Z89: =IF($P89="",0,1) | AA89: =IF($P89="",0,$P89) | AB89: =IF(AND($P89<>"",$P89<=Paramètres!$C$14),1,0) | AC89: =IF($P89="","Jamais relancé",IF($P89<=3,"0-3 j",IF($P89<=7,"4-7 j",IF($P89<=15,"8-15 j","Plus de 15 j")))) | AD89: =IF($M89<=1000,"Moins de 1 k€",IF($M89<=5000,"1 à 5 k€",IF($M89<=15000,"5 à 15 k€","Plus de 15 k€")))
A90: DEV-00089 | B90: 44816 | C90: 2022-09 | D90: 2022-2023 | E90: CLI-0103 | F90: Particulier | G90: Toulouse | H90: Julien Fabre | I90: Salle de bain | J90: SB-003 | K90: Pose meuble vasque + robinetterie | L90: 1 | M90: 1265.01 | N90: Refusé | O90: 44840 | Q90: 0 | R90: =$I90 | S90: =$K90 | T90: =IFERROR(INDEX(Clients!$G$2:$G$1020,MATCH($E90,Clients!$A$2:$A$1020,0)),"") | U90: =IFERROR(INDEX(Clients!$I$2:$I$1020,MATCH($E90,Clients!$A$2:$A$1020,0)),"") | V90: =1 | W90: =IF($N90="Accepté",1,0) | X90: =$M90*$W90 | Y90: =IF($N90="En cours",0,$M90) | Z90: =IF($P90="",0,1) | AA90: =IF($P90="",0,$P90) | AB90: =IF(AND($P90<>"",$P90<=Paramètres!$C$14),1,0) | AC90: =IF($P90="","Jamais relancé",IF($P90<=3,"0-3 j",IF($P90<=7,"4-7 j",IF($P90<=15,"8-15 j","Plus de 15 j")))) | AD90: =IF($M90<=1000,"Moins de 1 k€",IF($M90<=5000,"1 à 5 k€",IF($M90<=15000,"5 à 15 k€","Plus de 15 k€")))
A91: DEV-00090 | B91: 44816 | C91: 2022-09 | D91: 2022-2023 | E91: CLI-0025 | F91: Syndic | G91: Bordeaux | H91: Sophie Marchand | I91: Dépannage | J91: DP-003 | K91: Dépannage électrique urgence | L91: 1 | M91: 580.54 | N91: Sans réponse | O91: 44831 | Q91: 0 | R91: =$I91 | S91: =$K91 | T91: =IFERROR(INDEX(Clients!$G$2:$G$1020,MATCH($E91,Clients!$A$2:$A$1020,0)),"") | U91: =IFERROR(INDEX(Clients!$I$2:$I$1020,MATCH($E91,Clients!$A$2:$A$1020,0)),"") | V91: =1 | W91: =IF($N91="Accepté",1,0) | X91: =$M91*$W91 | Y91: =IF($N91="En cours",0,$M91) | Z91: =IF($P91="",0,1) | AA91: =IF($P91="",0,$P91) | AB91: =IF(AND($P91<>"",$P91<=Paramètres!$C$14),1,0) | AC91: =IF($P91="","Jamais relancé",IF($P91<=3,"0-3 j",IF($P91<=7,"4-7 j",IF($P91<=15,"8-15 j","Plus de 15 j")))) | AD91: =IF($M91<=1000,"Moins de 1 k€",IF($M91<=5000,"1 à 5 k€",IF($M91<=15000,"5 à 15 k€","Plus de 15 k€")))
A92: DEV-00091 | B92: 44816 | C92: 2022-09 | D92: 2022-2023 | E92: CLI-0169 | F92: Professionnel | G92: Bordeaux | H92: Sophie Marchand | I92: Électricité | J92: EL-004 | K92: Éclairage LED locaux professionnels | L92: 1 | M92: 4820.6 | N92: Sans réponse | O92: 44820 | P92: 6 | Q92: 0 | R92: =$I92 | S92: =$K92 | T92: =IFERROR(INDEX(Clients!$G$2:$G$1020,MATCH($E92,Clients!$A$2:$A$1020,0)),"") | U92: =IFERROR(INDEX(Clients!$I$2:$I$1020,MATCH($E92,Clients!$A$2:$A$1020,0)),"") | V92: =1 | W92: =IF($N92="Accepté",1,0) | X92: =$M92*$W92 | Y92: =IF($N92="En cours",0,$M92) | Z92: =IF($P92="",0,1) | AA92: =IF($P92="",0,$P92) | AB92: =IF(AND($P92<>"",$P92<=Paramètres!$C$14),1,0) | AC92: =IF($P92="","Jamais relancé",IF($P92<=3,"0-3 j",IF($P92<=7,"4-7 j",IF($P92<=15,"8-15 j","Plus de 15 j")))) | AD92: =IF($M92<=1000,"Moins de 1 k€",IF($M92<=5000,"1 à 5 k€",IF($M92<=15000,"5 à 15 k€","Plus de 15 k€")))
A93: DEV-00092 | B93: 44817 | C93: 2022-09 | D93: 2022-2023 | E93: CLI-0117 | F93: Particulier | G93: Toulouse | H93: Julien Fabre | I93: Salle de bain | J93: SB-001 | K93: Rénovation salle de bain complète | L93: 1 | M93: 9970.87 | N93: Accepté | O93: 44826 | P93: 3 | Q93: 1 | R93: =$I93 | S93: =$K93 | T93: =IFERROR(INDEX(Clients!$G$2:$G$1020,MATCH($E93,Clients!$A$2:$A$1020,0)),"") | U93: =IFERROR(INDEX(Clients!$I$2:$I$1020,MATCH($E93,Clients!$A$2:$A$1020,0)),"") | V93: =1 | W93: =IF($N93="Accepté",1,0) | X93: =$M93*$W93 | Y93: =IF($N93="En cours",0,$M93) | Z93: =IF($P93="",0,1) | AA93: =IF($P93="",0,$P93) | AB93: =IF(AND($P93<>"",$P93<=Paramètres!$C$14),1,0) | AC93: =IF($P93="","Jamais relancé",IF($P93<=3,"0-3 j",IF($P93<=7,"4-7 j",IF($P93<=15,"8-15 j","Plus de 15 j")))) | AD93: =IF($M93<=1000,"Moins de 1 k€",IF($M93<=5000,"1 à 5 k€",IF($M93<=15000,"5 à 15 k€","Plus de 15 k€")))
A94: DEV-00093 | B94: 44817 | C94: 2022-09 | D94: 2022-2023 | E94: CLI-0065 | F94: Particulier | G94: Bordeaux | H94: Sophie Marchand | I94: Dépannage | J94: DP-004 | K94: Remise en service chaudière | L94: 1 | M94: 209.36 | N94: Accepté | O94: 44848 | P94: 5 | Q94: 3 | R94: =$I94 | S94: =$K94 | T94: =IFERROR(INDEX(Clients!$G$2:$G$1020,MATCH($E94,Clients!$A$2:$A$1020,0)),"") | U94: =IFERROR(INDEX(Clients!$I$2:$I$1020,MATCH($E94,Clients!$A$2:$A$1020,0)),"") | V94: =1 | W94: =IF($N94="Accepté",1,0) | X94: =$M94*$W94 | Y94: =IF($N94="En cours",0,$M94) | Z94: =IF($P94="",0,1) | AA94: =IF($P94="",0,$P94) | AB94: =IF(AND($P94<>"",$P94<=Paramètres!$C$14),1,0) | AC94: =IF($P94="","Jamais relancé",IF($P94<=3,"0-3 j",IF($P94<=7,"4-7 j",IF($P94<=15,"8-15 j","Plus de 15 j")))) | AD94: =IF($M94<=1000,"Moins de 1 k€",IF($M94<=5000,"1 à 5 k€",IF($M94<=15000,"5 à 15 k€","Plus de 15 k€")))
A95: DEV-00094 | B95: 44817 | C95: 2022-09 | D95: 2022-2023 | E95: CLI-0025 | F95: Syndic | G95: Bordeaux | H95: Sophie Marchand | I95: Chauffage | J95: CH-001 | K95: Installation chaudière gaz condensation | L95: 1 | M95: 11006.55 | N95: Sans réponse | O95: 44835 | P95: 13 | Q95: 1 | R95: =$I95 | S95: =$K95 | T95: =IFERROR(INDEX(Clients!$G$2:$G$1020,MATCH($E95,Clients!$A$2:$A$1020,0)),"") | U95: =IFERROR(INDEX(Clients!$I$2:$I$1020,MATCH($E95,Clients!$A$2:$A$1020,0)),"") | V95: =1 | W95: =IF($N95="Accepté",1,0) | X95: =$M95*$W95 | Y95: =IF($N95="En cours",0,$M95) | Z95: =IF($P95="",0,1) | AA95: =IF($P95="",0,$P95) | AB95: =IF(AND($P95<>"",$P95<=Paramètres!$C$14),1,0) | AC95: =IF($P95="","Jamais relancé",IF($P95<=3,"0-3 j",IF($P95<=7,"4-7 j",IF($P95<=15,"8-15 j","Plus de 15 j")))) | AD95: =IF($M95<=1000,"Moins de 1 k€",IF($M95<=5000,"1 à 5 k€",IF($M95<=15000,"5 à 15 k€","Plus de 15 k€")))
A96: DEV-00095 | B96: 44818 | C96: 2022-09 | D96: 2022-2023 | E96: CLI-0218 | F96: Syndic | G96: Bordeaux | H96: Karim Belkacem | I96: Salle de bain | J96: SB-003 | K96: Pose meuble vasque + robinetterie | L96: 1 | M96: 2400.78 | N96: Accepté | O96: 44864 | P96: 1 | Q96: 2 | R96: =$I96 | S96: =$K96 | T96: =IFERROR(INDEX(Clients!$G$2:$G$1020,MATCH($E96,Clients!$A$2:$A$1020,0)),"") | U96: =IFERROR(INDEX(Clients!$I$2:$I$1020,MATCH($E96,Clients!$A$2:$A$1020,0)),"") | V96: =1 | W96: =IF($N96="Accepté",1,0) | X96: =$M96*$W96 | Y96: =IF($N96="En cours",0,$M96) | Z96: =IF($P96="",0,1) | AA96: =IF($P96="",0,$P96) | AB96: =IF(AND($P96<>"",$P96<=Paramètres!$C$14),1,0) | AC96: =IF($P96="","Jamais relancé",IF($P96<=3,"0-3 j",IF($P96<=7,"4-7 j",IF($P96<=15,"8-15 j","Plus de 15 j")))) | AD96: =IF($M96<=1000,"Moins de 1 k€",IF($M96<=5000,"1 à 5 k€",IF($M96<=15000,"5 à 15 k€","Plus de 15 k€")))
A97: DEV-00096 | B97: 44818 | C97: 2022-09 | D97: 2022-2023 | E97: CLI-0009 | F97: Particulier | G97: Toulouse | H97: Julien Fabre | I97: Chauffage | J97: CH-004 | K97: Remplacement radiateurs (lot de 5) | L97: 1 | M97: 2556.52 | N97: Sans réponse | O97: 44826 | P97: 11 | Q97: 0 | R97: =$I97 | S97: =$K97 | T97: =IFERROR(INDEX(Clients!$G$2:$G$1020,MATCH($E97,Clients!$A$2:$A$1020,0)),"") | U97: =IFERROR(INDEX(Clients!$I$2:$I$1020,MATCH($E97,Clients!$A$2:$A$1020,0)),"") | V97: =1 | W97: =IF($N97="Accepté",1,0) | X97: =$M97*$W97 | Y97: =IF($N97="En cours",0,$M97) | Z97: =IF($P97="",0,1) | AA97: =IF($P97="",0,$P97) | AB97: =IF(AND($P97<>"",$P97<=Paramètres!$C$14),1,0) | AC97: =IF($P97="","Jamais relancé",IF($P97<=3,"0-3 j",IF($P97<=7,"4-7 j",IF($P97<=15,"8-15 j","Plus de 15 j")))) | AD97: =IF($M97<=1000,"Moins de 1 k€",IF($M97<=5000,"1 à 5 k€",IF($M97<=15000,"5 à 15 k€","Plus de 15 k€")))
A98: DEV-00097 | B98: 44819 | C98: 2022-09 | D98: 2022-2023 | E98: CLI-0214 | F98: Particulier | G98: Toulouse | H98: Julien Fabre | I98: Salle de bain | J98: SB-001 | K98: Rénovation salle de bain complète | L98: 1 | M98: 9611.5 | N98: Accepté | O98: 44832 | P98: 5 | Q98: 1 | R98: =$I98 | S98: =$K98 | T98: =IFERROR(INDEX(Clients!$G$2:$G$1020,MATCH($E98,Clients!$A$2:$A$1020,0)),"") | U98: =IFERROR(INDEX(Clients!$I$2:$I$1020,MATCH($E98,Clients!$A$2:$A$1020,0)),"") | V98: =1 | W98: =IF($N98="Accepté",1,0) | X98: =$M98*$W98 | Y98: =IF($N98="En cours",0,$M98) | Z98: =IF($P98="",0,1) | AA98: =IF($P98="",0,$P98) | AB98: =IF(AND($P98<>"",$P98<=Paramètres!$C$14),1,0) | AC98: =IF($P98="","Jamais relancé",IF($P98<=3,"0-3 j",IF($P98<=7,"4-7 j",IF($P98<=15,"8-15 j","Plus de 15 j")))) | AD98: =IF($M98<=1000,"Moins de 1 k€",IF($M98<=5000,"1 à 5 k€",IF($M98<=15000,"5 à 15 k€","Plus de 15 k€")))
A99: DEV-00098 | B99: 44819 | C99: 2022-09 | D99: 2022-2023 | E99: CLI-0108 | F99: Professionnel | G99: Toulouse | H99: Julien Fabre | I99: Salle de bain | J99: SB-003 | K99: Pose meuble vasque + robinetterie | L99: 1 | M99: 1921.53 | N99: Sans réponse | O99: 44823 | P99: 4 | Q99: 1 | R99: =$I99 | S99: =$K99 | T99: =IFERROR(INDEX(Clients!$G$2:$G$1020,MATCH($E99,Clients!$A$2:$A$1020,0)),"") | U99: =IFERROR(INDEX(Clients!$I$2:$I$1020,MATCH($E99,Clients!$A$2:$A$1020,0)),"") | V99: =1 | W99: =IF($N99="Accepté",1,0) | X99: =$M99*$W99 | Y99: =IF($N99="En cours",0,$M99) | Z99: =IF($P99="",0,1) | AA99: =IF($P99="",0,$P99) | AB99: =IF(AND($P99<>"",$P99<=Paramètres!$C$14),1,0) | AC99: =IF($P99="","Jamais relancé",IF($P99<=3,"0-3 j",IF($P99<=7,"4-7 j",IF($P99<=15,"8-15 j","Plus de 15 j")))) | AD99: =IF($M99<=1000,"Moins de 1 k€",IF($M99<=5000,"1 à 5 k€",IF($M99<=15000,"5 à 15 k€","Plus de 15 k€")))
A100: DEV-00099 | B100: 44819 | C100: 2022-09 | D100: 2022-2023 | E100: CLI-0156 | F100: Particulier | G100: Bordeaux | H100: Karim Belkacem | I100: Salle de bain | J100: SB-001 | K100: Rénovation salle de bain complète | L100: 1 | M100: 10092.69 | N100: Sans réponse | O100: 44840 | P100: 8 | Q100: 1 | R100: =$I100 | S100: =$K100 | T100: =IFERROR(INDEX(Clients!$G$2:$G$1020,MATCH($E100,Clients!$A$2:$A$1020,0)),"") | U100: =IFERROR(INDEX(Clients!$I$2:$I$1020,MATCH($E100,Clients!$A$2:$A$1020,0)),"") | V100: =1 | W100: =IF($N100="Accepté",1,0) | X100: =$M100*$W100 | Y100: =IF($N100="En cours",0,$M100) | Z100: =IF($P100="",0,1) | AA100: =IF($P100="",0,$P100) | AB100: =IF(AND($P100<>"",$P100<=Paramètres!$C$14),1,0) | AC100: =IF($P100="","Jamais relancé",IF($P100<=3,"0-3 j",IF($P100<=7,"4-7 j",IF($P100<=15,"8-15 j","Plus de 15 j")))) | AD100: =IF($M100<=1000,"Moins de 1 k€",IF($M100<=5000,"1 à 5 k€",IF($M100<=15000,"5 à 15 k€","Plus de 15 k€")))
...

Sheet Relances
A1: Relance id | B1: Devis id | C1: Date relance | D1: Mois | E1: Exercice | F1: Rang | G1: Canal | H1: Agence | I1: Commercial | J1: Issue | K1: Duree min
A2: REL-00001 | B2: DEV-00001 | C2: 44747 | D2: 2022-07 | E2: 2022-2023 | F2: 1 | G2: Email | H2: Toulouse | I2: Julien Fabre | J2: Rappel demandé | K2: 4.3
A3: REL-00002 | B3: DEV-00001 | C3: 44756 | D3: 2022-07 | E3: 2022-2023 | F3: 2 | G3: Téléphone | H3: Toulouse | I3: Julien Fabre | J3: Injoignable | K3: 10.9
A4: REL-00003 | B4: DEV-00002 | C4: 44744 | D4: 2022-07 | E4: 2022-2023 | F4: 1 | G4: Email | H4: Bordeaux | I4: Sophie Marchand | J4: Refus signifié | K4: 1.4
A5: REL-00004 | B5: DEV-00004 | C5: 44756 | D5: 2022-07 | E5: 2022-2023 | F5: 1 | G5: Email | H5: Toulouse | I5: Julien Fabre | J5: Sans réponse | K5: 1.5
A6: REL-00005 | B6: DEV-00004 | C6: 44767 | D6: 2022-07 | E6: 2022-2023 | F6: 2 | G6: SMS | H6: Toulouse | I6: Julien Fabre | J6: Refus signifié | K6: 1.7
A7: REL-00006 | B7: DEV-00006 | C7: 44748 | D7: 2022-07 | E7: 2022-2023 | F7: 1 | G7: SMS | H7: Bordeaux | I7: Sophie Marchand | J7: Sans réponse | K7: 4
A8: REL-00007 | B8: DEV-00006 | C8: 44757 | D8: 2022-07 | E8: 2022-2023 | F8: 2 | G8: Email | H8: Bordeaux | I8: Sophie Marchand | J8: Accord obtenu | K8: 2.2
A9: REL-00008 | B9: DEV-00007 | C9: 44749 | D9: 2022-07 | E9: 2022-2023 | F9: 1 | G9: Téléphone | H9: Bordeaux | I9: Karim Belkacem | J9: Refus signifié | K9: 7.8
A10: REL-00009 | B10: DEV-00008 | C10: 44751 | D10: 2022-07 | E10: 2022-2023 | F10: 1 | G10: Email | H10: Bordeaux | I10: Karim Belkacem | J10: Accord obtenu | K10: 4.4
A11: REL-00010 | B11: DEV-00009 | C11: 44756 | D11: 2022-07 | E11: 2022-2023 | F11: 1 | G11: Téléphone | H11: Toulouse | I11: Julien Fabre | J11: Sans réponse | K11: 8.6
A12: REL-00011 | B12: DEV-00009 | C12: 44761 | D12: 2022-07 | E12: 2022-2023 | F12: 2 | G12: Téléphone | H12: Toulouse | I12: Julien Fabre | J12: Refus signifié | K12: 4.2
A13: REL-00012 | B13: DEV-00010 | C13: 44751 | D13: 2022-07 | E13: 2022-2023 | F13: 1 | G13: Email | H13: Bordeaux | I13: Karim Belkacem | J13: Sans réponse | K13: 4.4
... A3168: REL-03167 | B3168: DEV-03038 | C3168: 46202 | D3168: 2026-06 | E3168: 2025-2026 | F3168: 1 | G3168: Téléphone | H3168: Bordeaux | I3168: Karim Belkacem | J3168: Sans réponse | K3168: 12.8

Sheet Factures
A1: Facture id | B1: Devis id | C1: Client id | D1: Type client | E1: Agence | F1: Date facture | G1: Mois | H1: Exercice | I1: Date echeance | J1: Delai contractuel j | K1: Montant ht | L1: Taux tva | M1: Montant ttc | N1: Profil paiement | O1: Date paiement | P1: Statut facture | Q1: Métier | R1: Prestation | S1: Canal d'acquisition | T1: Ligne | U1: Coût de revient | V1: Marge brute | W1: Réglée | X1: Encours TTC | Y1: Retard (j) | Z1: Retard pondéré | AA1: Délai réel (j) | AB1: En retard | AC1: Exception | AD1: Mois d'encaissement | AE1: Ancienneté de créance | AF1: Tranche de montant
A2: FAC-00001 | B2: DEV-00006 | C2: CLI-0114 | D2: Particulier | E2: Bordeaux | F2: 44785 | G2: 2022-08 | H2: 2022-2023 | I2: 44800 | J2: 15 | K2: 408.99 | L2: 0.1 | M2: 449.89 | N2: Bon payeur | O2: 44797 | P2: Payée | Q2: =IFERROR(INDEX(Devis!$I$2:$I$3053,MATCH($B2,Devis!$A$2:$A$3053,0)),"") | R2: =IFERROR(INDEX(Devis!$K$2:$K$3053,MATCH($B2,Devis!$A$2:$A$3053,0)),"") | S2: =IFERROR(INDEX(Clients!$G$2:$G$1020,MATCH($C2,Clients!$A$2:$A$1020,0)),"") | T2: =1 | U2: =IFERROR(INDEX(Interventions!$S$2:$S$1106,MATCH($B2,Interventions!$B$2:$B$1106,0)),0) | V2: =$K2-$U2 | W2: =IF($O2="",0,1) | X2: =IF($O2="",$M2,0) | Y2: =IF($O2="",MAX(0,Paramètres!$C$8-$I2),MAX(0,$O2-$I2)) | Z2: =$Y2*$X2 | AA2: =IF($O2="",0,$O2-$F2) | AB2: =IF(AND($O2="",$I2<Paramètres!$C$8),1,0) | AC2: =IF(AND($O2="",$Y2>Paramètres!$C$13),1,0) | AD2: =IF($O2="","",YEAR($O2)&"-"&TEXT(MONTH($O2),"00")) | AE2: =IF($W2=1,"Réglée",IF($Y2<=0,"Non échu",IF($Y2<=30,"1-30 j",IF($Y2<=60,"31-60 j",IF($Y2<=90,"61-90 j","Plus de 90 j"))))) | AF2: =IF($K2<=1000,"Moins de 1 k€",IF($K2<=5000,"1 à 5 k€",IF($K2<=15000,"5 à 15 k€","Plus de 15 k€")))
A3: FAC-00002 | B3: DEV-00008 | C3: CLI-0160 | D3: Particulier | E3: Bordeaux | F3: 44795 | G3: 2022-08 | H3: 2022-2023 | I3: 44810 | J3: 15 | K3: 5812.36 | L3: 0.1 | M3: 6393.6 | N3: Standard | O3: 44808 | P3: Payée | Q3: =IFERROR(INDEX(Devis!$I$2:$I$3053,MATCH($B3,Devis!$A$2:$A$3053,0)),"") | R3: =IFERROR(INDEX(Devis!$K$2:$K$3053,MATCH($B3,Devis!$A$2:$A$3053,0)),"") | S3: =IFERROR(INDEX(Clients!$G$2:$G$1020,MATCH($C3,Clients!$A$2:$A$1020,0)),"") | T3: =1 | U3: =IFERROR(INDEX(Interventions!$S$2:$S$1106,MATCH($B3,Interventions!$B$2:$B$1106,0)),0) | V3: =$K3-$U3 | W3: =IF($O3="",0,1) | X3: =IF($O3="",$M3,0) | Y3: =IF($O3="",MAX(0,Paramètres!$C$8-$I3),MAX(0,$O3-$I3)) | Z3: =$Y3*$X3 | AA3: =IF($O3="",0,$O3-$F3) | AB3: =IF(AND($O3="",$I3<Paramètres!$C$8),1,0) | AC3: =IF(AND($O3="",$Y3>Paramètres!$C$13),1,0) | AD3: =IF($O3="","",YEAR($O3)&"-"&TEXT(MONTH($O3),"00")) | AE3: =IF($W3=1,"Réglée",IF($Y3<=0,"Non échu",IF($Y3<=30,"1-30 j",IF($Y3<=60,"31-60 j",IF($Y3<=90,"61-90 j","Plus de 90 j"))))) | AF3: =IF($K3<=1000,"Moins de 1 k€",IF($K3<=5000,"1 à 5 k€",IF($K3<=15000,"5 à 15 k€","Plus de 15 k€")))
A4: FAC-00003 | B4: DEV-00010 | C4: CLI-0089 | D4: Particulier | E4: Bordeaux | F4: 44795 | G4: 2022-08 | H4: 2022-2023 | I4: 44810 | J4: 15 | K4: 1332.2 | L4: 0.1 | M4: 1465.42 | N4: Bon payeur | O4: 44813 | P4: Payée | Q4: =IFERROR(INDEX(Devis!$I$2:$I$3053,MATCH($B4,Devis!$A$2:$A$3053,0)),"") | R4: =IFERROR(INDEX(Devis!$K$2:$K$3053,MATCH($B4,Devis!$A$2:$A$3053,0)),"") | S4: =IFERROR(INDEX(Clients!$G$2:$G$1020,MATCH($C4,Clients!$A$2:$A$1020,0)),"") | T4: =1 | U4: =IFERROR(INDEX(Interventions!$S$2:$S$1106,MATCH($B4,Interventions!$B$2:$B$1106,0)),0) | V4: =$K4-$U4 | W4: =IF($O4="",0,1) | X4: =IF($O4="",$M4,0) | Y4: =IF($O4="",MAX(0,Paramètres!$C$8-$I4),MAX(0,$O4-$I4)) | Z4: =$Y4*$X4 | AA4: =IF($O4="",0,$O4-$F4) | AB4: =IF(AND($O4="",$I4<Paramètres!$C$8),1,0) | AC4: =IF(AND($O4="",$Y4>Paramètres!$C$13),1,0) | AD4: =IF($O4="","",YEAR($O4)&"-"&TEXT(MONTH($O4),"00")) | AE4: =IF($W4=1,"Réglée",IF($Y4<=0,"Non échu",IF($Y4<=30,"1-30 j",IF($Y4<=60,"31-60 j",IF($Y4<=90,"61-90 j","Plus de 90 j"))))) | AF4: =IF($K4<=1000,"Moins de 1 k€",IF($K4<=5000,"1 à 5 k€",IF($K4<=15000,"5 à 15 k€","Plus de 15 k€")))
A5: FAC-00004 | B5: DEV-00014 | C5: CLI-0098 | D5: Particulier | E5: Bordeaux | F5: 44784 | G5: 2022-08 | H5: 2022-2023 | I5: 44799 | J5: 15 | K5: 223.45 | L5: 0.2 | M5: 268.14 | N5: Bon payeur | O5: 44795 | P5: Payée | Q5: =IFERROR(INDEX(Devis!$I$2:$I$3053,MATCH($B5,Devis!$A$2:$A$3053,0)),"") | R5: =IFERROR(INDEX(Devis!$K$2:$K$3053,MATCH($B5,Devis!$A$2:$A$3053,0)),"") | S5: =IFERROR(INDEX(Clients!$G$2:$G$1020,MATCH($C5,Clients!$A$2:$A$1020,0)),"") | T5: =1 | U5: =IFERROR(INDEX(Interventions!$S$2:$S$1106,MATCH($B5,Interventions!$B$2:$B$1106,0)),0) | V5: =$K5-$U5 | W5: =IF($O5="",0,1) | X5: =IF($O5="",$M5,0) | Y5: =IF($O5="",MAX(0,Paramètres!$C$8-$I5),MAX(0,$O5-$I5)) | Z5: =$Y5*$X5 | AA5: =IF($O5="",0,$O5-$F5) | AB5: =IF(AND($O5="",$I5<Paramètres!$C$8),1,0) | AC5: =IF(AND($O5="",$Y5>Paramètres!$C$13),1,0) | AD5: =IF($O5="","",YEAR($O5)&"-"&TEXT(MONTH($O5),"00")) | AE5: =IF($W5=1,"Réglée",IF($Y5<=0,"Non échu",IF($Y5<=30,"1-30 j",IF($Y5<=60,"31-60 j",IF($Y5<=90,"61-90 j","Plus de 90 j"))))) | AF5: =IF($K5<=1000,"Moins de 1 k€",IF($K5<=5000,"1 à 5 k€",IF($K5<=15000,"5 à 15 k€","Plus de 15 k€")))
A6: FAC-00005 | B6: DEV-00015 | C6: CLI-0042 | D6: Particulier | E6: Bordeaux | F6: 44797 | G6: 2022-08 | H6: 2022-2023 | I6: 44812 | J6: 15 | K6: 331.48 | L6: 0.2 | M6: 397.78 | N6: Standard | O6: 44842 | P6: Payée | Q6: =IFERROR(INDEX(Devis!$I$2:$I$3053,MATCH($B6,Devis!$A$2:$A$3053,0)),"") | R6: =IFERROR(INDEX(Devis!$K$2:$K$3053,MATCH($B6,Devis!$A$2:$A$3053,0)),"") | S6: =IFERROR(INDEX(Clients!$G$2:$G$1020,MATCH($C6,Clients!$A$2:$A$1020,0)),"") | T6: =1 | U6: =IFERROR(INDEX(Interventions!$S$2:$S$1106,MATCH($B6,Interventions!$B$2:$B$1106,0)),0) | V6: =$K6-$U6 | W6: =IF($O6="",0,1) | X6: =IF($O6="",$M6,0) | Y6: =IF($O6="",MAX(0,Paramètres!$C$8-$I6),MAX(0,$O6-$I6)) | Z6: =$Y6*$X6 | AA6: =IF($O6="",0,$O6-$F6) | AB6: =IF(AND($O6="",$I6<Paramètres!$C$8),1,0) | AC6: =IF(AND($O6="",$Y6>Paramètres!$C$13),1,0) | AD6: =IF($O6="","",YEAR($O6)&"-"&TEXT(MONTH($O6),"00")) | AE6: =IF($W6=1,"Réglée",IF($Y6<=0,"Non échu",IF($Y6<=30,"1-30 j",IF($Y6<=60,"31-60 j",IF($Y6<=90,"61-90 j","Plus de 90 j"))))) | AF6: =IF($K6<=1000,"Moins de 1 k€",IF($K6<=5000,"1 à 5 k€",IF($K6<=15000,"5 à 15 k€","Plus de 15 k€")))
A7: FAC-00006 | B7: DEV-00026 | C7: CLI-0156 | D7: Particulier | E7: Bordeaux | F7: 44795 | G7: 2022-08 | H7: 2022-2023 | I7: 44810 | J7: 15 | K7: 3476.87 | L7: 0.1 | M7: 3824.56 | N7: Bon payeur | O7: 44820 | P7: Payée | Q7: =IFERROR(INDEX(Devis!$I$2:$I$3053,MATCH($B7,Devis!$A$2:$A$3053,0)),"") | R7: =IFERROR(INDEX(Devis!$K$2:$K$3053,MATCH($B7,Devis!$A$2:$A$3053,0)),"") | S7: =IFERROR(INDEX(Clients!$G$2:$G$1020,MATCH($C7,Clients!$A$2:$A$1020,0)),"") | T7: =1 | U7: =IFERROR(INDEX(Interventions!$S$2:$S$1106,MATCH($B7,Interventions!$B$2:$B$1106,0)),0) | V7: =$K7-$U7 | W7: =IF($O7="",0,1) | X7: =IF($O7="",$M7,0) | Y7: =IF($O7="",MAX(0,Paramètres!$C$8-$I7),MAX(0,$O7-$I7)) | Z7: =$Y7*$X7 | AA7: =IF($O7="",0,$O7-$F7) | AB7: =IF(AND($O7="",$I7<Paramètres!$C$8),1,0) | AC7: =IF(AND($O7="",$Y7>Paramètres!$C$13),1,0) | AD7: =IF($O7="","",YEAR($O7)&"-"&TEXT(MONTH($O7),"00")) | AE7: =IF($W7=1,"Réglée",IF($Y7<=0,"Non échu",IF($Y7<=30,"1-30 j",IF($Y7<=60,"31-60 j",IF($Y7<=90,"61-90 j","Plus de 90 j"))))) | AF7: =IF($K7<=1000,"Moins de 1 k€",IF($K7<=5000,"1 à 5 k€",IF($K7<=15000,"5 à 15 k€","Plus de 15 k€")))
A8: FAC-00007 | B8: DEV-00028 | C8: CLI-0005 | D8: Particulier | E8: Bordeaux | F8: 44795 | G8: 2022-08 | H8: 2022-2023 | I8: 44810 | J8: 15 | K8: 262.87 | L8: 0.2 | M8: 315.44 | N8: Standard | O8: 44832 | P8: Payée | Q8: =IFERROR(INDEX(Devis!$I$2:$I$3053,MATCH($B8,Devis!$A$2:$A$3053,0)),"") | R8: =IFERROR(INDEX(Devis!$K$2:$K$3053,MATCH($B8,Devis!$A$2:$A$3053,0)),"") | S8: =IFERROR(INDEX(Clients!$G$2:$G$1020,MATCH($C8,Clients!$A$2:$A$1020,0)),"") | T8: =1 | U8: =IFERROR(INDEX(Interventions!$S$2:$S$1106,MATCH($B8,Interventions!$B$2:$B$1106,0)),0) | V8: =$K8-$U8 | W8: =IF($O8="",0,1) | X8: =IF($O8="",$M8,0) | Y8: =IF($O8="",MAX(0,Paramètres!$C$8-$I8),MAX(0,$O8-$I8)) | Z8: =$Y8*$X8 | AA8: =IF($O8="",0,$O8-$F8) | AB8: =IF(AND($O8="",$I8<Paramètres!$C$8),1,0) | AC8: =IF(AND($O8="",$Y8>Paramètres!$C$13),1,0) | AD8: =IF($O8="","",YEAR($O8)&"-"&TEXT(MONTH($O8),"00")) | AE8: =IF($W8=1,"Réglée",IF($Y8<=0,"Non échu",IF($Y8<=30,"1-30 j",IF($Y8<=60,"31-60 j",IF($Y8<=90,"61-90 j","Plus de 90 j"))))) | AF8: =IF($K8<=1000,"Moins de 1 k€",IF($K8<=5000,"1 à 5 k€",IF($K8<=15000,"5 à 15 k€","Plus de 15 k€")))
A9: FAC-00008 | B9: DEV-00031 | C9: CLI-0196 | D9: Particulier | E9: Bordeaux | F9: 44812 | G9: 2022-09 | H9: 2022-2023 | I9: 44827 | J9: 15 | K9: 10167.81 | L9: 0.1 | M9: 11184.59 | N9: Standard | O9: 44835 | P9: Payée | Q9: =IFERROR(INDEX(Devis!$I$2:$I$3053,MATCH($B9,Devis!$A$2:$A$3053,0)),"") | R9: =IFERROR(INDEX(Devis!$K$2:$K$3053,MATCH($B9,Devis!$A$2:$A$3053,0)),"") | S9: =IFERROR(INDEX(Clients!$G$2:$G$1020,MATCH($C9,Clients!$A$2:$A$1020,0)),"") | T9: =1 | U9: =IFERROR(INDEX(Interventions!$S$2:$S$1106,MATCH($B9,Interventions!$B$2:$B$1106,0)),0) | V9: =$K9-$U9 | W9: =IF($O9="",0,1) | X9: =IF($O9="",$M9,0) | Y9: =IF($O9="",MAX(0,Paramètres!$C$8-$I9),MAX(0,$O9-$I9)) | Z9: =$Y9*$X9 | AA9: =IF($O9="",0,$O9-$F9) | AB9: =IF(AND($O9="",$I9<Paramètres!$C$8),1,0) | AC9: =IF(AND($O9="",$Y9>Paramètres!$C$13),1,0) | AD9: =IF($O9="","",YEAR($O9)&"-"&TEXT(MONTH($O9),"00")) | AE9: =IF($W9=1,"Réglée",IF($Y9<=0,"Non échu",IF($Y9<=30,"1-30 j",IF($Y9<=60,"31-60 j",IF($Y9<=90,"61-90 j","Plus de 90 j"))))) | AF9: =IF($K9<=1000,"Moins de 1 k€",IF($K9<=5000,"1 à 5 k€",IF($K9<=15000,"5 à 15 k€","Plus de 15 k€")))
A10: FAC-00009 | B10: DEV-00034 | C10: CLI-0025 | D10: Syndic | E10: Bordeaux | F10: 44791 | G10: 2022-08 | H10: 2022-2023 | I10: 44851 | J10: 60 | K10: 8733 | L10: 0.2 | M10: 10479.6 | N10: Standard | O10: 44847 | P10: Payée | Q10: =IFERROR(INDEX(Devis!$I$2:$I$3053,MATCH($B10,Devis!$A$2:$A$3053,0)),"") | R10: =IFERROR(INDEX(Devis!$K$2:$K$3053,MATCH($B10,Devis!$A$2:$A$3053,0)),"") | S10: =IFERROR(INDEX(Clients!$G$2:$G$1020,MATCH($C10,Clients!$A$2:$A$1020,0)),"") | T10: =1 | U10: =IFERROR(INDEX(Interventions!$S$2:$S$1106,MATCH($B10,Interventions!$B$2:$B$1106,0)),0) | V10: =$K10-$U10 | W10: =IF($O10="",0,1) | X10: =IF($O10="",$M10,0) | Y10: =IF($O10="",MAX(0,Paramètres!$C$8-$I10),MAX(0,$O10-$I10)) | Z10: =$Y10*$X10 | AA10: =IF($O10="",0,$O10-$F10) | AB10: =IF(AND($O10="",$I10<Paramètres!$C$8),1,0) | AC10: =IF(AND($O10="",$Y10>Paramètres!$C$13),1,0) | AD10: =IF($O10="","",YEAR($O10)&"-"&TEXT(MONTH($O10),"00")) | AE10: =IF($W10=1,"Réglée",IF($Y10<=0,"Non échu",IF($Y10<=30,"1-30 j",IF($Y10<=60,"31-60 j",IF($Y10<=90,"61-90 j","Plus de 90 j"))))) | AF10: =IF($K10<=1000,"Moins de 1 k€",IF($K10<=5000,"1 à 5 k€",IF($K10<=15000,"5 à 15 k€","Plus de 15 k€")))
A11: FAC-00010 | B11: DEV-00036 | C11: CLI-0052 | D11: Particulier | E11: Toulouse | F11: 44837 | G11: 2022-10 | H11: 2022-2023 | I11: 44852 | J11: 15 | K11: 3641.62 | L11: 0.1 | M11: 4005.78 | N11: Standard | O11: 44848 | P11: Payée | Q11: =IFERROR(INDEX(Devis!$I$2:$I$3053,MATCH($B11,Devis!$A$2:$A$3053,0)),"") | R11: =IFERROR(INDEX(Devis!$K$2:$K$3053,MATCH($B11,Devis!$A$2:$A$3053,0)),"") | S11: =IFERROR(INDEX(Clients!$G$2:$G$1020,MATCH($C11,Clients!$A$2:$A$1020,0)),"") | T11: =1 | U11: =IFERROR(INDEX(Interventions!$S$2:$S$1106,MATCH($B11,Interventions!$B$2:$B$1106,0)),0) | V11: =$K11-$U11 | W11: =IF($O11="",0,1) | X11: =IF($O11="",$M11,0) | Y11: =IF($O11="",MAX(0,Paramètres!$C$8-$I11),MAX(0,$O11-$I11)) | Z11: =$Y11*$X11 | AA11: =IF($O11="",0,$O11-$F11) | AB11: =IF(AND($O11="",$I11<Paramètres!$C$8),1,0) | AC11: =IF(AND($O11="",$Y11>Paramètres!$C$13),1,0) | AD11: =IF($O11="","",YEAR($O11)&"-"&TEXT(MONTH($O11),"00")) | AE11: =IF($W11=1,"Réglée",IF($Y11<=0,"Non échu",IF($Y11<=30,"1-30 j",IF($Y11<=60,"31-60 j",IF($Y11<=90,"61-90 j","Plus de 90 j"))))) | AF11: =IF($K11<=1000,"Moins de 1 k€",IF($K11<=5000,"1 à 5 k€",IF($K11<=15000,"5 à 15 k€","Plus de 15 k€")))
A12: FAC-00011 | B12: DEV-00037 | C12: CLI-0036 | D12: Particulier | E12: Toulouse | F12: 44823 | G12: 2022-09 | H12: 2022-2023 | I12: 44838 | J12: 15 | K12: 422.16 | L12: 0.1 | M12: 464.38 | N12: Standard | O12: 44824 | P12: Payée | Q12: =IFERROR(INDEX(Devis!$I$2:$I$3053,MATCH($B12,Devis!$A$2:$A$3053,0)),"") | R12: =IFERROR(INDEX(Devis!$K$2:$K$3053,MATCH($B12,Devis!$A$2:$A$3053,0)),"") | S12: =IFERROR(INDEX(Clients!$G$2:$G$1020,MATCH($C12,Clients!$A$2:$A$1020,0)),"") | T12: =1 | U12: =IFERROR(INDEX(Interventions!$S$2:$S$1106,MATCH($B12,Interventions!$B$2:$B$1106,0)),0) | V12: =$K12-$U12 | W12: =IF($O12="",0,1) | X12: =IF($O12="",$M12,0) | Y12: =IF($O12="",MAX(0,Paramètres!$C$8-$I12),MAX(0,$O12-$I12)) | Z12: =$Y12*$X12 | AA12: =IF($O12="",0,$O12-$F12) | AB12: =IF(AND($O12="",$I12<Paramètres!$C$8),1,0) | AC12: =IF(AND($O12="",$Y12>Paramètres!$C$13),1,0) | AD12: =IF($O12="","",YEAR($O12)&"-"&TEXT(MONTH($O12),"00")) | AE12: =IF($W12=1,"Réglée",IF($Y12<=0,"Non échu",IF($Y12<=30,"1-30 j",IF($Y12<=60,"31-60 j",IF($Y12<=90,"61-90 j","Plus de 90 j"))))) | AF12: =IF($K12<=1000,"Moins de 1 k€",IF($K12<=5000,"1 à 5 k€",IF($K12<=15000,"5 à 15 k€","Plus de 15 k€")))
A13: FAC-00012 | B13: DEV-00038 | C13: CLI-0158 | D13: Particulier | E13: Bordeaux | F13: 44809 | G13: 2022-09 | H13: 2022-2023 | I13: 44824 | J13: 15 | K13: 1418.22 | L13: 0.2 | M13: 1701.86 | N13: Bon payeur | O13: 44827 | P13: Payée | Q13: =IFERROR(INDEX(Devis!$I$2:$I$3053,MATCH($B13,Devis!$A$2:$A$3053,0)),"") | R13: =IFERROR(INDEX(Devis!$K$2:$K$3053,MATCH($B13,Devis!$A$2:$A$3053,0)),"") | S13: =IFERROR(INDEX(Clients!$G$2:$G$1020,MATCH($C13,Clients!$A$2:$A$1020,0)),"") | T13: =1 | U13: =IFERROR(INDEX(Interventions!$S$2:$S$1106,MATCH($B13,Interventions!$B$2:$B$1106,0)),0) | V13: =$K13-$U13 | W13: =IF($O13="",0,1) | X13: =IF($O13="",$M13,0) | Y13: =IF($O13="",MAX(0,Paramètres!$C$8-$I13),MAX(0,$O13-$I13)) | Z13: =$Y13*$X13 | AA13: =IF($O13="",0,$O13-$F13) | AB13: =IF(AND($O13="",$I13<Paramètres!$C$8),1,0) | AC13: =IF(AND($O13="",$Y13>Paramètres!$C$13),1,0) | AD13: =IF($O13="","",YEAR($O13)&"-"&TEXT(MONTH($O13),"00")) | AE13: =IF($W13=1,"Réglée",IF($Y13<=0,"Non échu",IF($Y13<=30,"1-30 j",IF($Y13<=60,"31-60 j",IF($Y13<=90,"61-90 j","Plus de 90 j"))))) | AF13: =IF($K13<=1000,"Moins de 1 k€",IF($K13<=5000,"1 à 5 k€",IF($K13<=15000,"5 à 15 k€","Plus de 15 k€")))
... A155: FAC-00154 | B155: DEV-00364 | C155: CLI-0221 | D155: Particulier | E155: Bordeaux | F155: 45054 | G155: 2023-05 | H155: 2022-2023 | I155: 45069 | J155: 15 | K155: 4019.02 | L155: 0.1 | M155: 4420.92 | N155: Lent | O155: 45120 | P155: Payée | Q155: =IFERROR(INDEX(Devis!$I$2:$I$3053,MATCH($B155,Devis!$A$2:$A$3053,0)),"") | R155: =IFERROR(INDEX(Devis!$K$2:$K$3053,MATCH($B155,Devis!$A$2:$A$3053,0)),"") | S155: =IFERROR(INDEX(Clients!$G$2:$G$1020,MATCH($C155,Clients!$A$2:$A$1020,0)),"") | T155: =1 | U155: =IFERROR(INDEX(Interventions!$S$2:$S$1106,MATCH($B155,Interventions!$B$2:$B$1106,0)),0) | V155: =$K155-$U155 | W155: =IF($O155="",0,1) | X155: =IF($O155="",$M155,0) | Y155: =IF($O155="",MAX(0,Paramètres!$C$8-$I155),MAX(0,$O155-$I155)) | Z155: =$Y155*$X155 | AA155: =IF($O155="",0,$O155-$F155) | AB155: =IF(AND($O155="",$I155<Paramètres!$C$8),1,0) | AC155: =IF(AND($O155="",$Y155>Paramètres!$C$13),1,0) | AD155: =IF($O155="","",YEAR($O155)&"-"&TEXT(MONTH($O155),"00")) | AE155: =IF($W155=1,"Réglée",IF($Y155<=0,"Non échu",IF($Y155<=30,"1-30 j",IF($Y155<=60,"31-60 j",IF($Y155<=90,"61-90 j","Plus de 90 j"))))) | AF155: =IF($K155<=1000,"Moins de 1 k€",IF($K155<=5000,"1 à 5 k€",IF($K155<=15000,"5 à 15 k€","Plus de 15 k€")))
A156: FAC-00155 | B156: DEV-00366 | C156: CLI-0075 | D156: Syndic | E156: Toulouse | F156: 45058 | G156: 2023-05 | H156: 2022-2023 | I156: 45118 | J156: 60 | K156: 517.06 | L156: 0.2 | M156: 620.47 | N156: Litigieux | P156: En retard | Q156: =IFERROR(INDEX(Devis!$I$2:$I$3053,MATCH($B156,Devis!$A$2:$A$3053,0)),"") | R156: =IFERROR(INDEX(Devis!$K$2:$K$3053,MATCH($B156,Devis!$A$2:$A$3053,0)),"") | S156: =IFERROR(INDEX(Clients!$G$2:$G$1020,MATCH($C156,Clients!$A$2:$A$1020,0)),"") | T156: =1 | U156: =IFERROR(INDEX(Interventions!$S$2:$S$1106,MATCH($B156,Interventions!$B$2:$B$1106,0)),0) | V156: =$K156-$U156 | W156: =IF($O156="",0,1) | X156: =IF($O156="",$M156,0) | Y156: =IF($O156="",MAX(0,Paramètres!$C$8-$I156),MAX(0,$O156-$I156)) | Z156: =$Y156*$X156 | AA156: =IF($O156="",0,$O156-$F156) | AB156: =IF(AND($O156="",$I156<Paramètres!$C$8),1,0) | AC156: =IF(AND($O156="",$Y156>Paramètres!$C$13),1,0) | AD156: =IF($O156="","",YEAR($O156)&"-"&TEXT(MONTH($O156),"00")) | AE156: =IF($W156=1,"Réglée",IF($Y156<=0,"Non échu",IF($Y156<=30,"1-30 j",IF($Y156<=60,"31-60 j",IF($Y156<=90,"61-90 j","Plus de 90 j"))))) | AF156: =IF($K156<=1000,"Moins de 1 k€",IF($K156<=5000,"1 à 5 k€",IF($K156<=15000,"5 à 15 k€","Plus de 15 k€")))
A157: FAC-00156 | B157: DEV-00368 | C157: CLI-0258 | D157: Professionnel | E157: Bordeaux | F157: 45048 | G157: 2023-05 | H157: 2022-2023 | I157: 45078 | J157: 30 | K157: 5174.9 | L157: 0.2 | M157: 6209.88 | N157: Standard | O157: 45078 | P157: Payée | Q157: =IFERROR(INDEX(Devis!$I$2:$I$3053,MATCH($B157,Devis!$A$2:$A$3053,0)),"") | R157: =IFERROR(INDEX(Devis!$K$2:$K$3053,MATCH($B157,Devis!$A$2:$A$3053,0)),"") | S157: =IFERROR(INDEX(Clients!$G$2:$G$1020,MATCH($C157,Clients!$A$2:$A$1020,0)),"") | T157: =1 | U157: =IFERROR(INDEX(Interventions!$S$2:$S$1106,MATCH($B157,Interventions!$B$2:$B$1106,0)),0) | V157: =$K157-$U157 | W157: =IF($O157="",0,1) | X157: =IF($O157="",$M157,0) | Y157: =IF($O157="",MAX(0,Paramètres!$C$8-$I157),MAX(0,$O157-$I157)) | Z157: =$Y157*$X157 | AA157: =IF($O157="",0,$O157-$F157) | AB157: =IF(AND($O157="",$I157<Paramètres!$C$8),1,0) | AC157: =IF(AND($O157="",$Y157>Paramètres!$C$13),1,0) | AD157: =IF($O157="","",YEAR($O157)&"-"&TEXT(MONTH($O157),"00")) | AE157: =IF($W157=1,"Réglée",IF($Y157<=0,"Non échu",IF($Y157<=30,"1-30 j",IF($Y157<=60,"31-60 j",IF($Y157<=90,"61-90 j","Plus de 90 j"))))) | AF157: =IF($K157<=1000,"Moins de 1 k€",IF($K157<=5000,"1 à 5 k€",IF($K157<=15000,"5 à 15 k€","Plus de 15 k€")))
A158: FAC-00157 | B158: DEV-00369 | C158: CLI-0027 | D158: Particulier | E158: Toulouse | F158: 45069 | G158: 2023-05 | H158: 2022-2023 | I158: 45084 | J158: 15 | K158: 8898.65 | L158: 0.2 | M158: 10678.38 | N158: Bon payeur | O158: 45070 | P158: Payée | Q158: =IFERROR(INDEX(Devis!$I$2:$I$3053,MATCH($B158,Devis!$A$2:$A$3053,0)),"") | R158: =IFERROR(INDEX(Devis!$K$2:$K$3053,MATCH($B158,Devis!$A$2:$A$3053,0)),"") | S158: =IFERROR(INDEX(Clients!$G$2:$G$1020,MATCH($C158,Clients!$A$2:$A$1020,0)),"") | T158: =1 | U158: =IFERROR(INDEX(Interventions!$S$2:$S$1106,MATCH($B158,Interventions!$B$2:$B$1106,0)),0) | V158: =$K158-$U158 | W158: =IF($O158="",0,1) | X158: =IF($O158="",$M158,0) | Y158: =IF($O158="",MAX(0,Paramètres!$C$8-$I158),MAX(0,$O158-$I158)) | Z158: =$Y158*$X158 | AA158: =IF($O158="",0,$O158-$F158) | AB158: =IF(AND($O158="",$I158<Paramètres!$C$8),1,0) | AC158: =IF(AND($O158="",$Y158>Paramètres!$C$13),1,0) | AD158: =IF($O158="","",YEAR($O158)&"-"&TEXT(MONTH($O158),"00")) | AE158: =IF($W158=1,"Réglée",IF($Y158<=0,"Non échu",IF($Y158<=30,"1-30 j",IF($Y158<=60,"31-60 j",IF($Y158<=90,"61-90 j","Plus de 90 j"))))) | AF158: =IF($K158<=1000,"Moins de 1 k€",IF($K158<=5000,"1 à 5 k€",IF($K158<=15000,"5 à 15 k€","Plus de 15 k€")))
A159: FAC-00158 | B159: DEV-00370 | C159: CLI-0258 | D159: Professionnel | E159: Bordeaux | F159: 45103 | G159: 2023-06 | H159: 2022-2023 | I159: 45133 | J159: 30 | K159: 5655.53 | L159: 0.2 | M159: 6786.64 | N159: Standard | O159: 45141 | P159: Payée | Q159: =IFERROR(INDEX(Devis!$I$2:$I$3053,MATCH($B159,Devis!$A$2:$A$3053,0)),"") | R159: =IFERROR(INDEX(Devis!$K$2:$K$3053,MATCH($B159,Devis!$A$2:$A$3053,0)),"") | S159: =IFERROR(INDEX(Clients!$G$2:$G$1020,MATCH($C159,Clients!$A$2:$A$1020,0)),"") | T159: =1 | U159: =IFERROR(INDEX(Interventions!$S$2:$S$1106,MATCH($B159,Interventions!$B$2:$B$1106,0)),0) | V159: =$K159-$U159 | W159: =IF($O159="",0,1) | X159: =IF($O159="",$M159,0) | Y159: =IF($O159="",MAX(0,Paramètres!$C$8-$I159),MAX(0,$O159-$I159)) | Z159: =$Y159*$X159 | AA159: =IF($O159="",0,$O159-$F159) | AB159: =IF(AND($O159="",$I159<Paramètres!$C$8),1,0) | AC159: =IF(AND($O159="",$Y159>Paramètres!$C$13),1,0) | AD159: =IF($O159="","",YEAR($O159)&"-"&TEXT(MONTH($O159),"00")) | AE159: =IF($W159=1,"Réglée",IF($Y159<=0,"Non échu",IF($Y159<=30,"1-30 j",IF($Y159<=60,"31-60 j",IF($Y159<=90,"61-90 j","Plus de 90 j"))))) | AF159: =IF($K159<=1000,"Moins de 1 k€",IF($K159<=5000,"1 à 5 k€",IF($K159<=15000,"5 à 15 k€","Plus de 15 k€")))
A160: FAC-00159 | B160: DEV-00373 | C160: CLI-0197 | D160: Particulier | E160: Bordeaux | F160: 45082 | G160: 2023-06 | H160: 2022-2023 | I160: 45097 | J160: 15 | K160: 3476.87 | L160: 0.1 | M160: 3824.56 | N160: Bon payeur | O160: 45103 | P160: Payée | Q160: =IFERROR(INDEX(Devis!$I$2:$I$3053,MATCH($B160,Devis!$A$2:$A$3053,0)),"") | R160: =IFERROR(INDEX(Devis!$K$2:$K$3053,MATCH($B160,Devis!$A$2:$A$3053,0)),"") | S160: =IFERROR(INDEX(Clients!$G$2:$G$1020,MATCH($C160,Clients!$A$2:$A$1020,0)),"") | T160: =1 | U160: =IFERROR(INDEX(Interventions!$S$2:$S$1106,MATCH($B160,Interventions!$B$2:$B$1106,0)),0) | V160: =$K160-$U160 | W160: =IF($O160="",0,1) | X160: =IF($O160="",$M160,0) | Y160: =IF($O160="",MAX(0,Paramètres!$C$8-$I160),MAX(0,$O160-$I160)) | Z160: =$Y160*$X160 | AA160: =IF($O160="",0,$O160-$F160) | AB160: =IF(AND($O160="",$I160<Paramètres!$C$8),1,0) | AC160: =IF(AND($O160="",$Y160>Paramètres!$C$13),1,0) | AD160: =IF($O160="","",YEAR($O160)&"-"&TEXT(MONTH($O160),"00")) | AE160: =IF($W160=1,"Réglée",IF($Y160<=0,"Non échu",IF($Y160<=30,"1-30 j",IF($Y160<=60,"31-60 j",IF($Y160<=90,"61-90 j","Plus de 90 j"))))) | AF160: =IF($K160<=1000,"Moins de 1 k€",IF($K160<=5000,"1 à 5 k€",IF($K160<=15000,"5 à 15 k€","Plus de 15 k€")))
A161: FAC-00160 | B161: DEV-00376 | C161: CLI-0238 | D161: Particulier | E161: Bordeaux | F161: 45062 | G161: 2023-05 | H161: 2022-2023 | I161: 45077 | J161: 15 | K161: 347.89 | L161: 0.2 | M161: 417.47 | N161: Lent | O161: 45122 | P161: Payée | Q161: =IFERROR(INDEX(Devis!$I$2:$I$3053,MATCH($B161,Devis!$A$2:$A$3053,0)),"") | R161: =IFERROR(INDEX(Devis!$K$2:$K$3053,MATCH($B161,Devis!$A$2:$A$3053,0)),"") | S161: =IFERROR(INDEX(Clients!$G$2:$G$1020,MATCH($C161,Clients!$A$2:$A$1020,0)),"") | T161: =1 | U161: =IFERROR(INDEX(Interventions!$S$2:$S$1106,MATCH($B161,Interventions!$B$2:$B$1106,0)),0) | V161: =$K161-$U161 | W161: =IF($O161="",0,1) | X161: =IF($O161="",$M161,0) | Y161: =IF($O161="",MAX(0,Paramètres!$C$8-$I161),MAX(0,$O161-$I161)) | Z161: =$Y161*$X161 | AA161: =IF($O161="",0,$O161-$F161) | AB161: =IF(AND($O161="",$I161<Paramètres!$C$8),1,0) | AC161: =IF(AND($O161="",$Y161>Paramètres!$C$13),1,0) | AD161: =IF($O161="","",YEAR($O161)&"-"&TEXT(MONTH($O161),"00")) | AE161: =IF($W161=1,"Réglée",IF($Y161<=0,"Non échu",IF($Y161<=30,"1-30 j",IF($Y161<=60,"31-60 j",IF($Y161<=90,"61-90 j","Plus de 90 j"))))) | AF161: =IF($K161<=1000,"Moins de 1 k€",IF($K161<=5000,"1 à 5 k€",IF($K161<=15000,"5 à 15 k€","Plus de 15 k€")))
A162: FAC-00161 | B162: DEV-00379 | C162: CLI-0202 | D162: Particulier | E162: Bordeaux | F162: 45079 | G162: 2023-06 | H162: 2022-2023 | I162: 45094 | J162: 15 | K162: 9421.98 | L162: 0.1 | M162: 10364.18 | N162: Bon payeur | O162: 45095 | P162: Payée | Q162: =IFERROR(INDEX(Devis!$I$2:$I$3053,MATCH($B162,Devis!$A$2:$A$3053,0)),"") | R162: =IFERROR(INDEX(Devis!$K$2:$K$3053,MATCH($B162,Devis!$A$2:$A$3053,0)),"") | S162: =IFERROR(INDEX(Clients!$G$2:$G$1020,MATCH($C162,Clients!$A$2:$A$1020,0)),"") | T162: =1 | U162: =IFERROR(INDEX(Interventions!$S$2:$S$1106,MATCH($B162,Interventions!$B$2:$B$1106,0)),0) | V162: =$K162-$U162 | W162: =IF($O162="",0,1) | X162: =IF($O162="",$M162,0) | Y162: =IF($O162="",MAX(0,Paramètres!$C$8-$I162),MAX(0,$O162-$I162)) | Z162: =$Y162*$X162 | AA162: =IF($O162="",0,$O162-$F162) | AB162: =IF(AND($O162="",$I162<Paramètres!$C$8),1,0) | AC162: =IF(AND($O162="",$Y162>Paramètres!$C$13),1,0) | AD162: =IF($O162="","",YEAR($O162)&"-"&TEXT(MONTH($O162),"00")) | AE162: =IF($W162=1,"Réglée",IF($Y162<=0,"Non échu",IF($Y162<=30,"1-30 j",IF($Y162<=60,"31-60 j",IF($Y162<=90,"61-90 j","Plus de 90 j"))))) | AF162: =IF($K162<=1000,"Moins de 1 k€",IF($K162<=5000,"1 à 5 k€",IF($K162<=15000,"5 à 15 k€","Plus de 15 k€")))
A163: FAC-00162 | B163: DEV-00382 | C163: CLI-0163 | D163: Particulier | E163: Toulouse | F163: 45089 | G163: 2023-06 | H163: 2022-2023 | I163: 45104 | J163: 15 | K163: 1803.21 | L163: 0.2 | M163: 2163.85 | N163: Standard | O163: 45131 | P163: Payée | Q163: =IFERROR(INDEX(Devis!$I$2:$I$3053,MATCH($B163,Devis!$A$2:$A$3053,0)),"") | R163: =IFERROR(INDEX(Devis!$K$2:$K$3053,MATCH($B163,Devis!$A$2:$A$3053,0)),"") | S163: =IFERROR(INDEX(Clients!$G$2:$G$1020,MATCH($C163,Clients!$A$2:$A$1020,0)),"") | T163: =1 | U163: =IFERROR(INDEX(Interventions!$S$2:$S$1106,MATCH($B163,Interventions!$B$2:$B$1106,0)),0) | V163: =$K163-$U163 | W163: =IF($O163="",0,1) | X163: =IF($O163="",$M163,0) | Y163: =IF($O163="",MAX(0,Paramètres!$C$8-$I163),MAX(0,$O163-$I163)) | Z163: =$Y163*$X163 | AA163: =IF($O163="",0,$O163-$F163) | AB163: =IF(AND($O163="",$I163<Paramètres!$C$8),1,0) | AC163: =IF(AND($O163="",$Y163>Paramètres!$C$13),1,0) | AD163: =IF($O163="","",YEAR($O163)&"-"&TEXT(MONTH($O163),"00")) | AE163: =IF($W163=1,"Réglée",IF($Y163<=0,"Non échu",IF($Y163<=30,"1-30 j",IF($Y163<=60,"31-60 j",IF($Y163<=90,"61-90 j","Plus de 90 j"))))) | AF163: =IF($K163<=1000,"Moins de 1 k€",IF($K163<=5000,"1 à 5 k€",IF($K163<=15000,"5 à 15 k€","Plus de 15 k€")))
A164: FAC-00163 | B164: DEV-00384 | C164: CLI-0153 | D164: Particulier | E164: Bordeaux | F164: 45062 | G164: 2023-05 | H164: 2022-2023 | I164: 45077 | J164: 15 | K164: 1288.68 | L164: 0.1 | M164: 1417.55 | N164: Standard | O164: 45063 | P164: Payée | Q164: =IFERROR(INDEX(Devis!$I$2:$I$3053,MATCH($B164,Devis!$A$2:$A$3053,0)),"") | R164: =IFERROR(INDEX(Devis!$K$2:$K$3053,MATCH($B164,Devis!$A$2:$A$3053,0)),"") | S164: =IFERROR(INDEX(Clients!$G$2:$G$1020,MATCH($C164,Clients!$A$2:$A$1020,0)),"") | T164: =1 | U164: =IFERROR(INDEX(Interventions!$S$2:$S$1106,MATCH($B164,Interventions!$B$2:$B$1106,0)),0) | V164: =$K164-$U164 | W164: =IF($O164="",0,1) | X164: =IF($O164="",$M164,0) | Y164: =IF($O164="",MAX(0,Paramètres!$C$8-$I164),MAX(0,$O164-$I164)) | Z164: =$Y164*$X164 | AA164: =IF($O164="",0,$O164-$F164) | AB164: =IF(AND($O164="",$I164<Paramètres!$C$8),1,0) | AC164: =IF(AND($O164="",$Y164>Paramètres!$C$13),1,0) | AD164: =IF($O164="","",YEAR($O164)&"-"&TEXT(MONTH($O164),"00")) | AE164: =IF($W164=1,"Réglée",IF($Y164<=0,"Non échu",IF($Y164<=30,"1-30 j",IF($Y164<=60,"31-60 j",IF($Y164<=90,"61-90 j","Plus de 90 j"))))) | AF164: =IF($K164<=1000,"Moins de 1 k€",IF($K164<=5000,"1 à 5 k€",IF($K164<=15000,"5 à 15 k€","Plus de 15 k€")))
A165: FAC-00164 | B165: DEV-00386 | C165: CLI-0162 | D165: Particulier | E165: Bordeaux | F165: 45062 | G165: 2023-05 | H165: 2022-2023 | I165: 45077 | J165: 15 | K165: 9318.99 | L165: 0.2 | M165: 11182.79 | N165: Standard | O165: 45084 | P165: Payée | Q165: =IFERROR(INDEX(Devis!$I$2:$I$3053,MATCH($B165,Devis!$A$2:$A$3053,0)),"") | R165: =IFERROR(INDEX(Devis!$K$2:$K$3053,MATCH($B165,Devis!$A$2:$A$3053,0)),"") | S165: =IFERROR(INDEX(Clients!$G$2:$G$1020,MATCH($C165,Clients!$A$2:$A$1020,0)),"") | T165: =1 | U165: =IFERROR(INDEX(Interventions!$S$2:$S$1106,MATCH($B165,Interventions!$B$2:$B$1106,0)),0) | V165: =$K165-$U165 | W165: =IF($O165="",0,1) | X165: =IF($O165="",$M165,0) | Y165: =IF($O165="",MAX(0,Paramètres!$C$8-$I165),MAX(0,$O165-$I165)) | Z165: =$Y165*$X165 | AA165: =IF($O165="",0,$O165-$F165) | AB165: =IF(AND($O165="",$I165<Paramètres!$C$8),1,0) | AC165: =IF(AND($O165="",$Y165>Paramètres!$C$13),1,0) | AD165: =IF($O165="","",YEAR($O165)&"-"&TEXT(MONTH($O165),"00")) | AE165: =IF($W165=1,"Réglée",IF($Y165<=0,"Non échu",IF($Y165<=30,"1-30 j",IF($Y165<=60,"31-60 j",IF($Y165<=90,"61-90 j","Plus de 90 j"))))) | AF165: =IF($K165<=1000,"Moins de 1 k€",IF($K165<=5000,"1 à 5 k€",IF($K165<=15000,"5 à 15 k€","Plus de 15 k€")))
A166: FAC-00165 | B166: DEV-00387 | C166: CLI-0154 | D166: Particulier | E166: Bordeaux | F166: 45065 | G166: 2023-05 | H166: 2022-2023 | I166: 45080 | J166: 15 | K166: 639.78 | L166: 0.2 | M166: 767.74 | N166: Bon payeur | O166: 45066 | P166: Payée | Q166: =IFERROR(INDEX(Devis!$I$2:$I$3053,MATCH($B166,Devis!$A$2:$A$3053,0)),"") | R166: =IFERROR(INDEX(Devis!$K$2:$K$3053,MATCH($B166,Devis!$A$2:$A$3053,0)),"") | S166: =IFERROR(INDEX(Clients!$G$2:$G$1020,MATCH($C166,Clients!$A$2:$A$1020,0)),"") | T166: =1 | U166: =IFERROR(INDEX(Interventions!$S$2:$S$1106,MATCH($B166,Interventions!$B$2:$B$1106,0)),0) | V166: =$K166-$U166 | W166: =IF($O166="",0,1) | X166: =IF($O166="",$M166,0) | Y166: =IF($O166="",MAX(0,Paramètres!$C$8-$I166),MAX(0,$O166-$I166)) | Z166: =$Y166*$X166 | AA166: =IF($O166="",0,$O166-$F166) | AB166: =IF(AND($O166="",$I166<Paramètres!$C$8),1,0) | AC166: =IF(AND($O166="",$Y166>Paramètres!$C$13),1,0) | AD166: =IF($O166="","",YEAR($O166)&"-"&TEXT(MONTH($O166),"00")) | AE166: =IF($W166=1,"Réglée",IF($Y166<=0,"Non échu",IF($Y166<=30,"1-30 j",IF($Y166<=60,"31-60 j",IF($Y166<=90,"61-90 j","Plus de 90 j"))))) | AF166: =IF($K166<=1000,"Moins de 1 k€",IF($K166<=5000,"1 à 5 k€",IF($K166<=15000,"5 à 15 k€","Plus de 15 k€")))
A167: FAC-00166 | B167: DEV-00388 | C167: CLI-0276 | D167: Professionnel | E167: Bordeaux | F167: 45083 | G167: 2023-06 | H167: 2022-2023 | I167: 45113 | J167: 30 | K167: 445.12 | L167: 0.2 | M167: 534.14 | N167: Litigieux | O167: 45199 | P167: Payée | Q167: =IFERROR(INDEX(Devis!$I$2:$I$3053,MATCH($B167,Devis!$A$2:$A$3053,0)),"") | R167: =IFERROR(INDEX(Devis!$K$2:$K$3053,MATCH($B167,Devis!$A$2:$A$3053,0)),"") | S167: =IFERROR(INDEX(Clients!$G$2:$G$1020,MATCH($C167,Clients!$A$2:$A$1020,0)),"") | T167: =1 | U167: =IFERROR(INDEX(Interventions!$S$2:$S$1106,MATCH($B167,Interventions!$B$2:$B$1106,0)),0) | V167: =$K167-$U167 | W167: =IF($O167="",0,1) | X167: =IF($O167="",$M167,0) | Y167: =IF($O167="",MAX(0,Paramètres!$C$8-$I167),MAX(0,$O167-$I167)) | Z167: =$Y167*$X167 | AA167: =IF($O167="",0,$O167-$F167) | AB167: =IF(AND($O167="",$I167<Paramètres!$C$8),1,0) | AC167: =IF(AND($O167="",$Y167>Paramètres!$C$13),1,0) | AD167: =IF($O167="","",YEAR($O167)&"-"&TEXT(MONTH($O167),"00")) | AE167: =IF($W167=1,"Réglée",IF($Y167<=0,"Non échu",IF($Y167<=30,"1-30 j",IF($Y167<=60,"31-60 j",IF($Y167<=90,"61-90 j","Plus de 90 j"))))) | AF167: =IF($K167<=1000,"Moins de 1 k€",IF($K167<=5000,"1 à 5 k€",IF($K167<=15000,"5 à 15 k€","Plus de 15 k€")))
A168: FAC-00167 | B168: DEV-00389 | C168: CLI-0023 | D168: Particulier | E168: Toulouse | F168: 45100 | G168: 2023-06 | H168: 2022-2023 | I168: 45115 | J168: 15 | K168: 6934.73 | L168: 0.1 | M168: 7628.2 | N168: Bon payeur | O168: 45114 | P168: Payée | Q168: =IFERROR(INDEX(Devis!$I$2:$I$3053,MATCH($B168,Devis!$A$2:$A$3053,0)),"") | R168: =IFERROR(INDEX(Devis!$K$2:$K$3053,MATCH($B168,Devis!$A$2:$A$3053,0)),"") | S168: =IFERROR(INDEX(Clients!$G$2:$G$1020,MATCH($C168,Clients!$A$2:$A$1020,0)),"") | T168: =1 | U168: =IFERROR(INDEX(Interventions!$S$2:$S$1106,MATCH($B168,Interventions!$B$2:$B$1106,0)),0) | V168: =$K168-$U168 | W168: =IF($O168="",0,1) | X168: =IF($O168="",$M168,0) | Y168: =IF($O168="",MAX(0,Paramètres!$C$8-$I168),MAX(0,$O168-$I168)) | Z168: =$Y168*$X168 | AA168: =IF($O168="",0,$O168-$F168) | AB168: =IF(AND($O168="",$I168<Paramètres!$C$8),1,0) | AC168: =IF(AND($O168="",$Y168>Paramètres!$C$13),1,0) | AD168: =IF($O168="","",YEAR($O168)&"-"&TEXT(MONTH($O168),"00")) | AE168: =IF($W168=1,"Réglée",IF($Y168<=0,"Non échu",IF($Y168<=30,"1-30 j",IF($Y168<=60,"31-60 j",IF($Y168<=90,"61-90 j","Plus de 90 j"))))) | AF168: =IF($K168<=1000,"Moins de 1 k€",IF($K168<=5000,"1 à 5 k€",IF($K168<=15000,"5 à 15 k€","Plus de 15 k€")))
... A238: FAC-00237 | B238: DEV-00555 | C238: CLI-0091 | D238: Particulier | E238: Bordeaux | F238: 45196 | G238: 2023-09 | H238: 2023-2024 | I238: 45211 | J238: 15 | K238: 9225.37 | L238: 0.2 | M238: 11070.44 | N238: Bon payeur | O238: 45197 | P238: Payée | Q238: =IFERROR(INDEX(Devis!$I$2:$I$3053,MATCH($B238,Devis!$A$2:$A$3053,0)),"") | R238: =IFERROR(INDEX(Devis!$K$2:$K$3053,MATCH($B238,Devis!$A$2:$A$3053,0)),"") | S238: =IFERROR(INDEX(Clients!$G$2:$G$1020,MATCH($C238,Clients!$A$2:$A$1020,0)),"") | T238: =1 | U238: =IFERROR(INDEX(Interventions!$S$2:$S$1106,MATCH($B238,Interventions!$B$2:$B$1106,0)),0) | V238: =$K238-$U238 | W238: =IF($O238="",0,1) | X238: =IF($O238="",$M238,0) | Y238: =IF($O238="",MAX(0,Paramètres!$C$8-$I238),MAX(0,$O238-$I238)) | Z238: =$Y238*$X238 | AA238: =IF($O238="",0,$O238-$F238) | AB238: =IF(AND($O238="",$I238<Paramètres!$C$8),1,0) | AC238: =IF(AND($O238="",$Y238>Paramètres!$C$13),1,0) | AD238: =IF($O238="","",YEAR($O238)&"-"&TEXT(MONTH($O238),"00")) | AE238: =IF($W238=1,"Réglée",IF($Y238<=0,"Non échu",IF($Y238<=30,"1-30 j",IF($Y238<=60,"31-60 j",IF($Y238<=90,"61-90 j","Plus de 90 j"))))) | AF238: =IF($K238<=1000,"Moins de 1 k€",IF($K238<=5000,"1 à 5 k€",IF($K238<=15000,"5 à 15 k€","Plus de 15 k€")))
A239: FAC-00238 | B239: DEV-00559 | C239: CLI-0207 | D239: Particulier | E239: Toulouse | F239: 45170 | G239: 2023-09 | H239: 2023-2024 | I239: 45185 | J239: 15 | K239: 249.44 | L239: 0.2 | M239: 299.33 | N239: Litigieux | P239: En retard | Q239: =IFERROR(INDEX(Devis!$I$2:$I$3053,MATCH($B239,Devis!$A$2:$A$3053,0)),"") | R239: =IFERROR(INDEX(Devis!$K$2:$K$3053,MATCH($B239,Devis!$A$2:$A$3053,0)),"") | S239: =IFERROR(INDEX(Clients!$G$2:$G$1020,MATCH($C239,Clients!$A$2:$A$1020,0)),"") | T239: =1 | U239: =IFERROR(INDEX(Interventions!$S$2:$S$1106,MATCH($B239,Interventions!$B$2:$B$1106,0)),0) | V239: =$K239-$U239 | W239: =IF($O239="",0,1) | X239: =IF($O239="",$M239,0) | Y239: =IF($O239="",MAX(0,Paramètres!$C$8-$I239),MAX(0,$O239-$I239)) | Z239: =$Y239*$X239 | AA239: =IF($O239="",0,$O239-$F239) | AB239: =IF(AND($O239="",$I239<Paramètres!$C$8),1,0) | AC239: =IF(AND($O239="",$Y239>Paramètres!$C$13),1,0) | AD239: =IF($O239="","",YEAR($O239)&"-"&TEXT(MONTH($O239),"00")) | AE239: =IF($W239=1,"Réglée",IF($Y239<=0,"Non échu",IF($Y239<=30,"1-30 j",IF($Y239<=60,"31-60 j",IF($Y239<=90,"61-90 j","Plus de 90 j"))))) | AF239: =IF($K239<=1000,"Moins de 1 k€",IF($K239<=5000,"1 à 5 k€",IF($K239<=15000,"5 à 15 k€","Plus de 15 k€")))
A240: FAC-00239 | B240: DEV-00561 | C240: CLI-0304 | D240: Professionnel | E240: Toulouse | F240: 45201 | G240: 2023-10 | H240: 2023-2024 | I240: 45231 | J240: 30 | K240: 744.42 | L240: 0.2 | M240: 893.3 | N240: Lent | O240: 45312 | P240: Payée | Q240: =IFERROR(INDEX(Devis!$I$2:$I$3053,MATCH($B240,Devis!$A$2:$A$3053,0)),"") | R240: =IFERROR(INDEX(Devis!$K$2:$K$3053,MATCH($B240,Devis!$A$2:$A$3053,0)),"") | S240: =IFERROR(INDEX(Clients!$G$2:$G$1020,MATCH($C240,Clients!$A$2:$A$1020,0)),"") | T240: =1 | U240: =IFERROR(INDEX(Interventions!$S$2:$S$1106,MATCH($B240,Interventions!$B$2:$B$1106,0)),0) | V240: =$K240-$U240 | W240: =IF($O240="",0,1) | X240: =IF($O240="",$M240,0) | Y240: =IF($O240="",MAX(0,Paramètres!$C$8-$I240),MAX(0,$O240-$I240)) | Z240: =$Y240*$X240 | AA240: =IF($O240="",0,$O240-$F240) | AB240: =IF(AND($O240="",$I240<Paramètres!$C$8),1,0) | AC240: =IF(AND($O240="",$Y240>Paramètres!$C$13),1,0) | AD240: =IF($O240="","",YEAR($O240)&"-"&TEXT(MONTH($O240),"00")) | AE240: =IF($W240=1,"Réglée",IF($Y240<=0,"Non échu",IF($Y240<=30,"1-30 j",IF($Y240<=60,"31-60 j",IF($Y240<=90,"61-90 j","Plus de 90 j"))))) | AF240: =IF($K240<=1000,"Moins de 1 k€",IF($K240<=5000,"1 à 5 k€",IF($K240<=15000,"5 à 15 k€","Plus de 15 k€")))
A241: FAC-00240 | B241: DEV-00568 | C241: CLI-0159 | D241: Syndic | E241: Bordeaux | F241: 45187 | G241: 2023-09 | H241: 2023-2024 | I241: 45247 | J241: 60 | K241: 17516.6 | L241: 0.2 | M241: 21019.92 | N241: Lent | O241: 45281 | P241: Payée | Q241: =IFERROR(INDEX(Devis!$I$2:$I$3053,MATCH($B241,Devis!$A$2:$A$3053,0)),"") | R241: =IFERROR(INDEX(Devis!$K$2:$K$3053,MATCH($B241,Devis!$A$2:$A$3053,0)),"") | S241: =IFERROR(INDEX(Clients!$G$2:$G$1020,MATCH($C241,Clients!$A$2:$A$1020,0)),"") | T241: =1 | U241: =IFERROR(INDEX(Interventions!$S$2:$S$1106,MATCH($B241,Interventions!$B$2:$B$1106,0)),0) | V241: =$K241-$U241 | W241: =IF($O241="",0,1) | X241: =IF($O241="",$M241,0) | Y241: =IF($O241="",MAX(0,Paramètres!$C$8-$I241),MAX(0,$O241-$I241)) | Z241: =$Y241*$X241 | AA241: =IF($O241="",0,$O241-$F241) | AB241: =IF(AND($O241="",$I241<Paramètres!$C$8),1,0) | AC241: =IF(AND($O241="",$Y241>Paramètres!$C$13),1,0) | AD241: =IF($O241="","",YEAR($O241)&"-"&TEXT(MONTH($O241),"00")) | AE241: =IF($W241=1,"Réglée",IF($Y241<=0,"Non échu",IF($Y241<=30,"1-30 j",IF($Y241<=60,"31-60 j",IF($Y241<=90,"61-90 j","Plus de 90 j"))))) | AF241: =IF($K241<=1000,"Moins de 1 k€",IF($K241<=5000,"1 à 5 k€",IF($K241<=15000,"5 à 15 k€","Plus de 15 k€")))
A242: FAC-00241 | B242: DEV-00569 | C242: CLI-0064 | D242: Professionnel | E242: Toulouse | F242: 45170 | G242: 2023-09 | H242: 2023-2024 | I242: 45200 | J242: 30 | K242: 807.4 | L242: 0.2 | M242: 968.88 | N242: Standard | O242: 45199 | P242: Payée | Q242: =IFERROR(INDEX(Devis!$I$2:$I$3053,MATCH($B242,Devis!$A$2:$A$3053,0)),"") | R242: =IFERROR(INDEX(Devis!$K$2:$K$3053,MATCH($B242,Devis!$A$2:$A$3053,0)),"") | S242: =IFERROR(INDEX(Clients!$G$2:$G$1020,MATCH($C242,Clients!$A$2:$A$1020,0)),"") | T242: =1 | U242: =IFERROR(INDEX(Interventions!$S$2:$S$1106,MATCH($B242,Interventions!$B$2:$B$1106,0)),0) | V242: =$K242-$U242 | W242: =IF($O242="",0,1) | X242: =IF($O242="",$M242,0) | Y242: =IF($O242="",MAX(0,Paramètres!$C$8-$I242),MAX(0,$O242-$I242)) | Z242: =$Y242*$X242 | AA242: =IF($O242="",0,$O242-$F242) | AB242: =IF(AND($O242="",$I242<Paramètres!$C$8),1,0) | AC242: =IF(AND($O242="",$Y242>Paramètres!$C$13),1,0) | AD242: =IF($O242="","",YEAR($O242)&"-"&TEXT(MONTH($O242),"00")) | AE242: =IF($W242=1,"Réglée",IF($Y242<=0,"Non échu",IF($Y242<=30,"1-30 j",IF($Y242<=60,"31-60 j",IF($Y242<=90,"61-90 j","Plus de 90 j"))))) | AF242: =IF($K242<=1000,"Moins de 1 k€",IF($K242<=5000,"1 à 5 k€",IF($K242<=15000,"5 à 15 k€","Plus de 15 k€")))
A243: FAC-00242 | B243: DEV-00572 | C243: CLI-0129 | D243: Professionnel | E243: Toulouse | F243: 45189 | G243: 2023-09 | H243: 2023-2024 | I243: 45219 | J243: 30 | K243: 18191.16 | L243: 0.2 | M243: 21829.39 | N243: Bon payeur | O243: 45229 | P243: Payée | Q243: =IFERROR(INDEX(Devis!$I$2:$I$3053,MATCH($B243,Devis!$A$2:$A$3053,0)),"") | R243: =IFERROR(INDEX(Devis!$K$2:$K$3053,MATCH($B243,Devis!$A$2:$A$3053,0)),"") | S243: =IFERROR(INDEX(Clients!$G$2:$G$1020,MATCH($C243,Clients!$A$2:$A$1020,0)),"") | T243: =1 | U243: =IFERROR(INDEX(Interventions!$S$2:$S$1106,MATCH($B243,Interventions!$B$2:$B$1106,0)),0) | V243: =$K243-$U243 | W243: =IF($O243="",0,1) | X243: =IF($O243="",$M243,0) | Y243: =IF($O243="",MAX(0,Paramètres!$C$8-$I243),MAX(0,$O243-$I243)) | Z243: =$Y243*$X243 | AA243: =IF($O243="",0,$O243-$F243) | AB243: =IF(AND($O243="",$I243<Paramètres!$C$8),1,0) | AC243: =IF(AND($O243="",$Y243>Paramètres!$C$13),1,0) | AD243: =IF($O243="","",YEAR($O243)&"-"&TEXT(MONTH($O243),"00")) | AE243: =IF($W243=1,"Réglée",IF($Y243<=0,"Non échu",IF($Y243<=30,"1-30 j",IF($Y243<=60,"31-60 j",IF($Y243<=90,"61-90 j","Plus de 90 j"))))) | AF243: =IF($K243<=1000,"Moins de 1 k€",IF($K243<=5000,"1 à 5 k€",IF($K243<=15000,"5 à 15 k€","Plus de 15 k€")))
A244: FAC-00243 | B244: DEV-00573 | C244: CLI-0248 | D244: Particulier | E244: Bordeaux | F244: 45194 | G244: 2023-09 | H244: 2023-2024 | I244: 45209 | J244: 15 | K244: 351.01 | L244: 0.2 | M244: 421.21 | N244: Bon payeur | O244: 45209 | P244: Payée | Q244: =IFERROR(INDEX(Devis!$I$2:$I$3053,MATCH($B244,Devis!$A$2:$A$3053,0)),"") | R244: =IFERROR(INDEX(Devis!$K$2:$K$3053,MATCH($B244,Devis!$A$2:$A$3053,0)),"") | S244: =IFERROR(INDEX(Clients!$G$2:$G$1020,MATCH($C244,Clients!$A$2:$A$1020,0)),"") | T244: =1 | U244: =IFERROR(INDEX(Interventions!$S$2:$S$1106,MATCH($B244,Interventions!$B$2:$B$1106,0)),0) | V244: =$K244-$U244 | W244: =IF($O244="",0,1) | X244: =IF($O244="",$M244,0) | Y244: =IF($O244="",MAX(0,Paramètres!$C$8-$I244),MAX(0,$O244-$I244)) | Z244: =$Y244*$X244 | AA244: =IF($O244="",0,$O244-$F244) | AB244: =IF(AND($O244="",$I244<Paramètres!$C$8),1,0) | AC244: =IF(AND($O244="",$Y244>Paramètres!$C$13),1,0) | AD244: =IF($O244="","",YEAR($O244)&"-"&TEXT(MONTH($O244),"00")) | AE244: =IF($W244=1,"Réglée",IF($Y244<=0,"Non échu",IF($Y244<=30,"1-30 j",IF($Y244<=60,"31-60 j",IF($Y244<=90,"61-90 j","Plus de 90 j"))))) | AF244: =IF($K244<=1000,"Moins de 1 k€",IF($K244<=5000,"1 à 5 k€",IF($K244<=15000,"5 à 15 k€","Plus de 15 k€")))
A245: FAC-00244 | B245: DEV-00574 | C245: CLI-0183 | D245: Particulier | E245: Bordeaux | F245: 45211 | G245: 2023-10 | H245: 2023-2024 | I245: 45226 | J245: 15 | K245: 13394.09 | L245: 0.1 | M245: 14733.5 | N245: Bon payeur | O245: 45243 | P245: Payée | Q245: =IFERROR(INDEX(Devis!$I$2:$I$3053,MATCH($B245,Devis!$A$2:$A$3053,0)),"") | R245: =IFERROR(INDEX(Devis!$K$2:$K$3053,MATCH($B245,Devis!$A$2:$A$3053,0)),"") | S245: =IFERROR(INDEX(Clients!$G$2:$G$1020,MATCH($C245,Clients!$A$2:$A$1020,0)),"") | T245: =1 | U245: =IFERROR(INDEX(Interventions!$S$2:$S$1106,MATCH($B245,Interventions!$B$2:$B$1106,0)),0) | V245: =$K245-$U245 | W245: =IF($O245="",0,1) | X245: =IF($O245="",$M245,0) | Y245: =IF($O245="",MAX(0,Paramètres!$C$8-$I245),MAX(0,$O245-$I245)) | Z245: =$Y245*$X245 | AA245: =IF($O245="",0,$O245-$F245) | AB245: =IF(AND($O245="",$I245<Paramètres!$C$8),1,0) | AC245: =IF(AND($O245="",$Y245>Paramètres!$C$13),1,0) | AD245: =IF($O245="","",YEAR($O245)&"-"&TEXT(MONTH($O245),"00")) | AE245: =IF($W245=1,"Réglée",IF($Y245<=0,"Non échu",IF($Y245<=30,"1-30 j",IF($Y245<=60,"31-60 j",IF($Y245<=90,"61-90 j","Plus de 90 j"))))) | AF245: =IF($K245<=1000,"Moins de 1 k€",IF($K245<=5000,"1 à 5 k€",IF($K245<=15000,"5 à 15 k€","Plus de 15 k€")))
A246: FAC-00245 | B246: DEV-00578 | C246: CLI-0055 | D246: Professionnel | E246: Bordeaux | F246: 45209 | G246: 2023-10 | H246: 2023-2024 | I246: 45239 | J246: 30 | K246: 683.83 | L246: 0.2 | M246: 820.6 | N246: Standard | O246: 45233 | P246: Payée | Q246: =IFERROR(INDEX(Devis!$I$2:$I$3053,MATCH($B246,Devis!$A$2:$A$3053,0)),"") | R246: =IFERROR(INDEX(Devis!$K$2:$K$3053,MATCH($B246,Devis!$A$2:$A$3053,0)),"") | S246: =IFERROR(INDEX(Clients!$G$2:$G$1020,MATCH($C246,Clients!$A$2:$A$1020,0)),"") | T246: =1 | U246: =IFERROR(INDEX(Interventions!$S$2:$S$1106,MATCH($B246,Interventions!$B$2:$B$1106,0)),0) | V246: =$K246-$U246 | W246: =IF($O246="",0,1) | X246: =IF($O246="",$M246,0) | Y246: =IF($O246="",MAX(0,Paramètres!$C$8-$I246),MAX(0,$O246-$I246)) | Z246: =$Y246*$X246 | AA246: =IF($O246="",0,$O246-$F246) | AB246: =IF(AND($O246="",$I246<Paramètres!$C$8),1,0) | AC246: =IF(AND($O246="",$Y246>Paramètres!$C$13),1,0) | AD246: =IF($O246="","",YEAR($O246)&"-"&TEXT(MONTH($O246),"00")) | AE246: =IF($W246=1,"Réglée",IF($Y246<=0,"Non échu",IF($Y246<=30,"1-30 j",IF($Y246<=60,"31-60 j",IF($Y246<=90,"61-90 j","Plus de 90 j"))))) | AF246: =IF($K246<=1000,"Moins de 1 k€",IF($K246<=5000,"1 à 5 k€",IF($K246<=15000,"5 à 15 k€","Plus de 15 k€")))
A247: FAC-00246 | B247: DEV-00581 | C247: CLI-0174 | D247: Professionnel | E247: Bordeaux | F247: 45191 | G247: 2023-09 | H247: 2023-2024 | I247: 45221 | J247: 30 | K247: 796.69 | L247: 0.2 | M247: 956.03 | N247: Bon payeur | O247: 45199 | P247: Payée | Q247: =IFERROR(INDEX(Devis!$I$2:$I$3053,MATCH($B247,Devis!$A$2:$A$3053,0)),"") | R247: =IFERROR(INDEX(Devis!$K$2:$K$3053,MATCH($B247,Devis!$A$2:$A$3053,0)),"") | S247: =IFERROR(INDEX(Clients!$G$2:$G$1020,MATCH($C247,Clients!$A$2:$A$1020,0)),"") | T247: =1 | U247: =IFERROR(INDEX(Interventions!$S$2:$S$1106,MATCH($B247,Interventions!$B$2:$B$1106,0)),0) | V247: =$K247-$U247 | W247: =IF($O247="",0,1) | X247: =IF($O247="",$M247,0) | Y247: =IF($O247="",MAX(0,Paramètres!$C$8-$I247),MAX(0,$O247-$I247)) | Z247: =$Y247*$X247 | AA247: =IF($O247="",0,$O247-$F247) | AB247: =IF(AND($O247="",$I247<Paramètres!$C$8),1,0) | AC247: =IF(AND($O247="",$Y247>Paramètres!$C$13),1,0) | AD247: =IF($O247="","",YEAR($O247)&"-"&TEXT(MONTH($O247),"00")) | AE247: =IF($W247=1,"Réglée",IF($Y247<=0,"Non échu",IF($Y247<=30,"1-30 j",IF($Y247<=60,"31-60 j",IF($Y247<=90,"61-90 j","Plus de 90 j"))))) | AF247: =IF($K247<=1000,"Moins de 1 k€",IF($K247<=5000,"1 à 5 k€",IF($K247<=15000,"5 à 15 k€","Plus de 15 k€")))
A248: FAC-00247 | B248: DEV-00583 | C248: CLI-0135 | D248: Professionnel | E248: Bordeaux | F248: 45197 | G248: 2023-09 | H248: 2023-2024 | I248: 45227 | J248: 30 | K248: 2618.7 | L248: 0.2 | M248: 3142.44 | N248: Litigieux | O248: 45380 | P248: Payée | Q248: =IFERROR(INDEX(Devis!$I$2:$I$3053,MATCH($B248,Devis!$A$2:$A$3053,0)),"") | R248: =IFERROR(INDEX(Devis!$K$2:$K$3053,MATCH($B248,Devis!$A$2:$A$3053,0)),"") | S248: =IFERROR(INDEX(Clients!$G$2:$G$1020,MATCH($C248,Clients!$A$2:$A$1020,0)),"") | T248: =1 | U248: =IFERROR(INDEX(Interventions!$S$2:$S$1106,MATCH($B248,Interventions!$B$2:$B$1106,0)),0) | V248: =$K248-$U248 | W248: =IF($O248="",0,1) | X248: =IF($O248="",$M248,0) | Y248: =IF($O248="",MAX(0,Paramètres!$C$8-$I248),MAX(0,$O248-$I248)) | Z248: =$Y248*$X248 | AA248: =IF($O248="",0,$O248-$F248) | AB248: =IF(AND($O248="",$I248<Paramètres!$C$8),1,0) | AC248: =IF(AND($O248="",$Y248>Paramètres!$C$13),1,0) | AD248: =IF($O248="","",YEAR($O248)&"-"&TEXT(MONTH($O248),"00")) | AE248: =IF($W248=1,"Réglée",IF($Y248<=0,"Non échu",IF($Y248<=30,"1-30 j",IF($Y248<=60,"31-60 j",IF($Y248<=90,"61-90 j","Plus de 90 j"))))) | AF248: =IF($K248<=1000,"Moins de 1 k€",IF($K248<=5000,"1 à 5 k€",IF($K248<=15000,"5 à 15 k€","Plus de 15 k€")))
A249: FAC-00248 | B249: DEV-00587 | C249: CLI-0031 | D249: Professionnel | E249: Bordeaux | F249: 45182 | G249: 2023-09 | H249: 2023-2024 | I249: 45212 | J249: 30 | K249: 2468.07 | L249: 0.2 | M249: 2961.68 | N249: Standard | O249: 45210 | P249: Payée | Q249: =IFERROR(INDEX(Devis!$I$2:$I$3053,MATCH($B249,Devis!$A$2:$A$3053,0)),"") | R249: =IFERROR(INDEX(Devis!$K$2:$K$3053,MATCH($B249,Devis!$A$2:$A$3053,0)),"") | S249: =IFERROR(INDEX(Clients!$G$2:$G$1020,MATCH($C249,Clients!$A$2:$A$1020,0)),"") | T249: =1 | U249: =IFERROR(INDEX(Interventions!$S$2:$S$1106,MATCH($B249,Interventions!$B$2:$B$1106,0)),0) | V249: =$K249-$U249 | W249: =IF($O249="",0,1) | X249: =IF($O249="",$M249,0) | Y249: =IF($O249="",MAX(0,Paramètres!$C$8-$I249),MAX(0,$O249-$I249)) | Z249: =$Y249*$X249 | AA249: =IF($O249="",0,$O249-$F249) | AB249: =IF(AND($O249="",$I249<Paramètres!$C$8),1,0) | AC249: =IF(AND($O249="",$Y249>Paramètres!$C$13),1,0) | AD249: =IF($O249="","",YEAR($O249)&"-"&TEXT(MONTH($O249),"00")) | AE249: =IF($W249=1,"Réglée",IF($Y249<=0,"Non échu",IF($Y249<=30,"1-30 j",IF($Y249<=60,"31-60 j",IF($Y249<=90,"61-90 j","Plus de 90 j"))))) | AF249: =IF($K249<=1000,"Moins de 1 k€",IF($K249<=5000,"1 à 5 k€",IF($K249<=15000,"5 à 15 k€","Plus de 15 k€")))
A250: FAC-00249 | B250: DEV-00588 | C250: CLI-0078 | D250: Collectivité | E250: Toulouse | F250: 45216 | G250: 2023-10 | H250: 2023-2024 | I250: 45261 | J250: 45 | K250: 3028.79 | L250: 0.2 | M250: 3634.55 | N250: Lent | O250: 45289 | P250: Payée | Q250: =IFERROR(INDEX(Devis!$I$2:$I$3053,MATCH($B250,Devis!$A$2:$A$3053,0)),"") | R250: =IFERROR(INDEX(Devis!$K$2:$K$3053,MATCH($B250,Devis!$A$2:$A$3053,0)),"") | S250: =IFERROR(INDEX(Clients!$G$2:$G$1020,MATCH($C250,Clients!$A$2:$A$1020,0)),"") | T250: =1 | U250: =IFERROR(INDEX(Interventions!$S$2:$S$1106,MATCH($B250,Interventions!$B$2:$B$1106,0)),0) | V250: =$K250-$U250 | W250: =IF($O250="",0,1) | X250: =IF($O250="",$M250,0) | Y250: =IF($O250="",MAX(0,Paramètres!$C$8-$I250),MAX(0,$O250-$I250)) | Z250: =$Y250*$X250 | AA250: =IF($O250="",0,$O250-$F250) | AB250: =IF(AND($O250="",$I250<Paramètres!$C$8),1,0) | AC250: =IF(AND($O250="",$Y250>Paramètres!$C$13),1,0) | AD250: =IF($O250="","",YEAR($O250)&"-"&TEXT(MONTH($O250),"00")) | AE250: =IF($W250=1,"Réglée",IF($Y250<=0,"Non échu",IF($Y250<=30,"1-30 j",IF($Y250<=60,"31-60 j",IF($Y250<=90,"61-90 j","Plus de 90 j"))))) | AF250: =IF($K250<=1000,"Moins de 1 k€",IF($K250<=5000,"1 à 5 k€",IF($K250<=15000,"5 à 15 k€","Plus de 15 k€")))
A251: FAC-00250 | B251: DEV-00589 | C251: CLI-0137 | D251: Particulier | E251: Bordeaux | F251: 45194 | G251: 2023-09 | H251: 2023-2024 | I251: 45209 | J251: 15 | K251: 7776.25 | L251: 0.1 | M251: 8553.88 | N251: Standard | O251: 45213 | P251: Payée | Q251: =IFERROR(INDEX(Devis!$I$2:$I$3053,MATCH($B251,Devis!$A$2:$A$3053,0)),"") | R251: =IFERROR(INDEX(Devis!$K$2:$K$3053,MATCH($B251,Devis!$A$2:$A$3053,0)),"") | S251: =IFERROR(INDEX(Clients!$G$2:$G$1020,MATCH($C251,Clients!$A$2:$A$1020,0)),"") | T251: =1 | U251: =IFERROR(INDEX(Interventions!$S$2:$S$1106,MATCH($B251,Interventions!$B$2:$B$1106,0)),0) | V251: =$K251-$U251 | W251: =IF($O251="",0,1) | X251: =IF($O251="",$M251,0) | Y251: =IF($O251="",MAX(0,Paramètres!$C$8-$I251),MAX(0,$O251-$I251)) | Z251: =$Y251*$X251 | AA251: =IF($O251="",0,$O251-$F251) | AB251: =IF(AND($O251="",$I251<Paramètres!$C$8),1,0) | AC251: =IF(AND($O251="",$Y251>Paramètres!$C$13),1,0) | AD251: =IF($O251="","",YEAR($O251)&"-"&TEXT(MONTH($O251),"00")) | AE251: =IF($W251=1,"Réglée",IF($Y251<=0,"Non échu",IF($Y251<=30,"1-30 j",IF($Y251<=60,"31-60 j",IF($Y251<=90,"61-90 j","Plus de 90 j"))))) | AF251: =IF($K251<=1000,"Moins de 1 k€",IF($K251<=5000,"1 à 5 k€",IF($K251<=15000,"5 à 15 k€","Plus de 15 k€")))
... A279: FAC-00278 | B279: DEV-00656 | C279: CLI-0329 | D279: Particulier | E279: Bordeaux | F279: 45275 | G279: 2023-12 | H279: 2023-2024 | I279: 45290 | J279: 15 | K279: 2481.46 | L279: 0.1 | M279: 2729.61 | N279: Standard | O279: 45332 | P279: Payée | Q279: =IFERROR(INDEX(Devis!$I$2:$I$3053,MATCH($B279,Devis!$A$2:$A$3053,0)),"") | R279: =IFERROR(INDEX(Devis!$K$2:$K$3053,MATCH($B279,Devis!$A$2:$A$3053,0)),"") | S279: =IFERROR(INDEX(Clients!$G$2:$G$1020,MATCH($C279,Clients!$A$2:$A$1020,0)),"") | T279: =1 | U279: =IFERROR(INDEX(Interventions!$S$2:$S$1106,MATCH($B279,Interventions!$B$2:$B$1106,0)),0) | V279: =$K279-$U279 | W279: =IF($O279="",0,1) | X279: =IF($O279="",$M279,0) | Y279: =IF($O279="",MAX(0,Paramètres!$C$8-$I279),MAX(0,$O279-$I279)) | Z279: =$Y279*$X279 | AA279: =IF($O279="",0,$O279-$F279) | AB279: =IF(AND($O279="",$I279<Paramètres!$C$8),1,0) | AC279: =IF(AND($O279="",$Y279>Paramètres!$C$13),1,0) | AD279: =IF($O279="","",YEAR($O279)&"-"&TEXT(MONTH($O279),"00")) | AE279: =IF($W279=1,"Réglée",IF($Y279<=0,"Non échu",IF($Y279<=30,"1-30 j",IF($Y279<=60,"31-60 j",IF($Y279<=90,"61-90 j","Plus de 90 j"))))) | AF279: =IF($K279<=1000,"Moins de 1 k€",IF($K279<=5000,"1 à 5 k€",IF($K279<=15000,"5 à 15 k€","Plus de 15 k€")))
A280: FAC-00279 | B280: DEV-00664 | C280: CLI-0065 | D280: Particulier | E280: Bordeaux | F280: 45264 | G280: 2023-12 | H280: 2023-2024 | I280: 45279 | J280: 15 | K280: 335.45 | L280: 0.2 | M280: 402.54 | N280: Litigieux | P280: En retard | Q280: =IFERROR(INDEX(Devis!$I$2:$I$3053,MATCH($B280,Devis!$A$2:$A$3053,0)),"") | R280: =IFERROR(INDEX(Devis!$K$2:$K$3053,MATCH($B280,Devis!$A$2:$A$3053,0)),"") | S280: =IFERROR(INDEX(Clients!$G$2:$G$1020,MATCH($C280,Clients!$A$2:$A$1020,0)),"") | T280: =1 | U280: =IFERROR(INDEX(Interventions!$S$2:$S$1106,MATCH($B280,Interventions!$B$2:$B$1106,0)),0) | V280: =$K280-$U280 | W280: =IF($O280="",0,1) | X280: =IF($O280="",$M280,0) | Y280: =IF($O280="",MAX(0,Paramètres!$C$8-$I280),MAX(0,$O280-$I280)) | Z280: =$Y280*$X280 | AA280: =IF($O280="",0,$O280-$F280) | AB280: =IF(AND($O280="",$I280<Paramètres!$C$8),1,0) | AC280: =IF(AND($O280="",$Y280>Paramètres!$C$13),1,0) | AD280: =IF($O280="","",YEAR($O280)&"-"&TEXT(MONTH($O280),"00")) | AE280: =IF($W280=1,"Réglée",IF($Y280<=0,"Non échu",IF($Y280<=30,"1-30 j",IF($Y280<=60,"31-60 j",IF($Y280<=90,"61-90 j","Plus de 90 j"))))) | AF280: =IF($K280<=1000,"Moins de 1 k€",IF($K280<=5000,"1 à 5 k€",IF($K280<=15000,"5 à 15 k€","Plus de 15 k€")))
A281: FAC-00280 | B281: DEV-00665 | C281: CLI-0098 | D281: Particulier | E281: Bordeaux | F281: 45251 | G281: 2023-11 | H281: 2023-2024 | I281: 45266 | J281: 15 | K281: 377.9 | L281: 0.2 | M281: 453.48 | N281: Bon payeur | O281: 45252 | P281: Payée | Q281: =IFERROR(INDEX(Devis!$I$2:$I$3053,MATCH($B281,Devis!$A$2:$A$3053,0)),"") | R281: =IFERROR(INDEX(Devis!$K$2:$K$3053,MATCH($B281,Devis!$A$2:$A$3053,0)),"") | S281: =IFERROR(INDEX(Clients!$G$2:$G$1020,MATCH($C281,Clients!$A$2:$A$1020,0)),"") | T281: =1 | U281: =IFERROR(INDEX(Interventions!$S$2:$S$1106,MATCH($B281,Interventions!$B$2:$B$1106,0)),0) | V281: =$K281-$U281 | W281: =IF($O281="",0,1) | X281: =IF($O281="",$M281,0) | Y281: =IF($O281="",MAX(0,Paramètres!$C$8-$I281),MAX(0,$O281-$I281)) | Z281: =$Y281*$X281 | AA281: =IF($O281="",0,$O281-$F281) | AB281: =IF(AND($O281="",$I281<Paramètres!$C$8),1,0) | AC281: =IF(AND($O281="",$Y281>Paramètres!$C$13),1,0) | AD281: =IF($O281="","",YEAR($O281)&"-"&TEXT(MONTH($O281),"00")) | AE281: =IF($W281=1,"Réglée",IF($Y281<=0,"Non échu",IF($Y281<=30,"1-30 j",IF($Y281<=60,"31-60 j",IF($Y281<=90,"61-90 j","Plus de 90 j"))))) | AF281: =IF($K281<=1000,"Moins de 1 k€",IF($K281<=5000,"1 à 5 k€",IF($K281<=15000,"5 à 15 k€","Plus de 15 k€")))
A282: FAC-00281 | B282: DEV-00666 | C282: CLI-0230 | D282: Professionnel | E282: Bordeaux | F282: 45266 | G282: 2023-12 | H282: 2023-2024 | I282: 45296 | J282: 30 | K282: 2862 | L282: 0.2 | M282: 3434.4 | N282: Bon payeur | O282: 45289 | P282: Payée | Q282: =IFERROR(INDEX(Devis!$I$2:$I$3053,MATCH($B282,Devis!$A$2:$A$3053,0)),"") | R282: =IFERROR(INDEX(Devis!$K$2:$K$3053,MATCH($B282,Devis!$A$2:$A$3053,0)),"") | S282: =IFERROR(INDEX(Clients!$G$2:$G$1020,MATCH($C282,Clients!$A$2:$A$1020,0)),"") | T282: =1 | U282: =IFERROR(INDEX(Interventions!$S$2:$S$1106,MATCH($B282,Interventions!$B$2:$B$1106,0)),0) | V282: =$K282-$U282 | W282: =IF($O282="",0,1) | X282: =IF($O282="",$M282,0) | Y282: =IF($O282="",MAX(0,Paramètres!$C$8-$I282),MAX(0,$O282-$I282)) | Z282: =$Y282*$X282 | AA282: =IF($O282="",0,$O282-$F282) | AB282: =IF(AND($O282="",$I282<Paramètres!$C$8),1,0) | AC282: =IF(AND($O282="",$Y282>Paramètres!$C$13),1,0) | AD282: =IF($O282="","",YEAR($O282)&"-"&TEXT(MONTH($O282),"00")) | AE282: =IF($W282=1,"Réglée",IF($Y282<=0,"Non échu",IF($Y282<=30,"1-30 j",IF($Y282<=60,"31-60 j",IF($Y282<=90,"61-90 j","Plus de 90 j"))))) | AF282: =IF($K282<=1000,"Moins de 1 k€",IF($K282<=5000,"1 à 5 k€",IF($K282<=15000,"5 à 15 k€","Plus de 15 k€")))
A283: FAC-00282 | B283: DEV-00667 | C283: CLI-0207 | D283: Particulier | E283: Toulouse | F283: 45247 | G283: 2023-11 | H283: 2023-2024 | I283: 45262 | J283: 15 | K283: 1584.18 | L283: 0.2 | M283: 1901.02 | N283: Litigieux | O283: 45248 | P283: Payée | Q283: =IFERROR(INDEX(Devis!$I$2:$I$3053,MATCH($B283,Devis!$A$2:$A$3053,0)),"") | R283: =IFERROR(INDEX(Devis!$K$2:$K$3053,MATCH($B283,Devis!$A$2:$A$3053,0)),"") | S283: =IFERROR(INDEX(Clients!$G$2:$G$1020,MATCH($C283,Clients!$A$2:$A$1020,0)),"") | T283: =1 | U283: =IFERROR(INDEX(Interventions!$S$2:$S$1106,MATCH($B283,Interventions!$B$2:$B$1106,0)),0) | V283: =$K283-$U283 | W283: =IF($O283="",0,1) | X283: =IF($O283="",$M283,0) | Y283: =IF($O283="",MAX(0,Paramètres!$C$8-$I283),MAX(0,$O283-$I283)) | Z283: =$Y283*$X283 | AA283: =IF($O283="",0,$O283-$F283) | AB283: =IF(AND($O283="",$I283<Paramètres!$C$8),1,0) | AC283: =IF(AND($O283="",$Y283>Paramètres!$C$13),1,0) | AD283: =IF($O283="","",YEAR($O283)&"-"&TEXT(MONTH($O283),"00")) | AE283: =IF($W283=1,"Réglée",IF($Y283<=0,"Non échu",IF($Y283<=30,"1-30 j",IF($Y283<=60,"31-60 j",IF($Y283<=90,"61-90 j","Plus de 90 j"))))) | AF283: =IF($K283<=1000,"Moins de 1 k€",IF($K283<=5000,"1 à 5 k€",IF($K283<=15000,"5 à 15 k€","Plus de 15 k€")))
A284: FAC-00283 | B284: DEV-00668 | C284: CLI-0102 | D284: Particulier | E284: Toulouse | F284: 45250 | G284: 2023-11 | H284: 2023-2024 | I284: 45265 | J284: 15 | K284: 335.82 | L284: 0.1 | M284: 369.4 | N284: Bon payeur | O284: 45259 | P284: Payée | Q284: =IFERROR(INDEX(Devis!$I$2:$I$3053,MATCH($B284,Devis!$A$2:$A$3053,0)),"") | R284: =IFERROR(INDEX(Devis!$K$2:$K$3053,MATCH($B284,Devis!$A$2:$A$3053,0)),"") | S284: =IFERROR(INDEX(Clients!$G$2:$G$1020,MATCH($C284,Clients!$A$2:$A$1020,0)),"") | T284: =1 | U284: =IFERROR(INDEX(Interventions!$S$2:$S$1106,MATCH($B284,Interventions!$B$2:$B$1106,0)),0) | V284: =$K284-$U284 | W284: =IF($O284="",0,1) | X284: =IF($O284="",$M284,0) | Y284: =IF($O284="",MAX(0,Paramètres!$C$8-$I284),MAX(0,$O284-$I284)) | Z284: =$Y284*$X284 | AA284: =IF($O284="",0,$O284-$F284) | AB284: =IF(AND($O284="",$I284<Paramètres!$C$8),1,0) | AC284: =IF(AND($O284="",$Y284>Paramètres!$C$13),1,0) | AD284: =IF($O284="","",YEAR($O284)&"-"&TEXT(MONTH($O284),"00")) | AE284: =IF($W284=1,"Réglée",IF($Y284<=0,"Non échu",IF($Y284<=30,"1-30 j",IF($Y284<=60,"31-60 j",IF($Y284<=90,"61-90 j","Plus de 90 j"))))) | AF284: =IF($K284<=1000,"Moins de 1 k€",IF($K284<=5000,"1 à 5 k€",IF($K284<=15000,"5 à 15 k€","Plus de 15 k€")))
A285: FAC-00284 | B285: DEV-00669 | C285: CLI-0243 | D285: Professionnel | E285: Bordeaux | F285: 45264 | G285: 2023-12 | H285: 2023-2024 | I285: 45294 | J285: 30 | K285: 5212.27 | L285: 0.2 | M285: 6254.72 | N285: Bon payeur | O285: 45275 | P285: Payée | Q285: =IFERROR(INDEX(Devis!$I$2:$I$3053,MATCH($B285,Devis!$A$2:$A$3053,0)),"") | R285: =IFERROR(INDEX(Devis!$K$2:$K$3053,MATCH($B285,Devis!$A$2:$A$3053,0)),"") | S285: =IFERROR(INDEX(Clients!$G$2:$G$1020,MATCH($C285,Clients!$A$2:$A$1020,0)),"") | T285: =1 | U285: =IFERROR(INDEX(Interventions!$S$2:$S$1106,MATCH($B285,Interventions!$B$2:$B$1106,0)),0) | V285: =$K285-$U285 | W285: =IF($O285="",0,1) | X285: =IF($O285="",$M285,0) | Y285: =IF($O285="",MAX(0,Paramètres!$C$8-$I285),MAX(0,$O285-$I285)) | Z285: =$Y285*$X285 | AA285: =IF($O285="",0,$O285-$F285) | AB285: =IF(AND($O285="",$I285<Paramètres!$C$8),1,0) | AC285: =IF(AND($O285="",$Y285>Paramètres!$C$13),1,0) | AD285: =IF($O285="","",YEAR($O285)&"-"&TEXT(MONTH($O285),"00")) | AE285: =IF($W285=1,"Réglée",IF($Y285<=0,"Non échu",IF($Y285<=30,"1-30 j",IF($Y285<=60,"31-60 j",IF($Y285<=90,"61-90 j","Plus de 90 j"))))) | AF285: =IF($K285<=1000,"Moins de 1 k€",IF($K285<=5000,"1 à 5 k€",IF($K285<=15000,"5 à 15 k€","Plus de 15 k€")))
A286: FAC-00285 | B286: DEV-00670 | C286: CLI-0181 | D286: Professionnel | E286: Toulouse | F286: 45250 | G286: 2023-11 | H286: 2023-2024 | I286: 45280 | J286: 30 | K286: 5557.99 | L286: 0.2 | M286: 6669.59 | N286: Bon payeur | O286: 45298 | P286: Payée | Q286: =IFERROR(INDEX(Devis!$I$2:$I$3053,MATCH($B286,Devis!$A$2:$A$3053,0)),"") | R286: =IFERROR(INDEX(Devis!$K$2:$K$3053,MATCH($B286,Devis!$A$2:$A$3053,0)),"") | S286: =IFERROR(INDEX(Clients!$G$2:$G$1020,MATCH($C286,Clients!$A$2:$A$1020,0)),"") | T286: =1 | U286: =IFERROR(INDEX(Interventions!$S$2:$S$1106,MATCH($B286,Interventions!$B$2:$B$1106,0)),0) | V286: =$K286-$U286 | W286: =IF($O286="",0,1) | X286: =IF($O286="",$M286,0) | Y286: =IF($O286="",MAX(0,Paramètres!$C$8-$I286),MAX(0,$O286-$I286)) | Z286: =$Y286*$X286 | AA286: =IF($O286="",0,$O286-$F286) | AB286: =IF(AND($O286="",$I286<Paramètres!$C$8),1,0) | AC286: =IF(AND($O286="",$Y286>Paramètres!$C$13),1,0) | AD286: =IF($O286="","",YEAR($O286)&"-"&TEXT(MONTH($O286),"00")) | AE286: =IF($W286=1,"Réglée",IF($Y286<=0,"Non échu",IF($Y286<=30,"1-30 j",IF($Y286<=60,"31-60 j",IF($Y286<=90,"61-90 j","Plus de 90 j"))))) | AF286: =IF($K286<=1000,"Moins de 1 k€",IF($K286<=5000,"1 à 5 k€",IF($K286<=15000,"5 à 15 k€","Plus de 15 k€")))
A287: FAC-00286 | B287: DEV-00676 | C287: CLI-0272 | D287: Professionnel | E287: Toulouse | F287: 45267 | G287: 2023-12 | H287: 2023-2024 | I287: 45297 | J287: 30 | K287: 371.95 | L287: 0.2 | M287: 446.34 | N287: Standard | O287: 45284 | P287: Payée | Q287: =IFERROR(INDEX(Devis!$I$2:$I$3053,MATCH($B287,Devis!$A$2:$A$3053,0)),"") | R287: =IFERROR(INDEX(Devis!$K$2:$K$3053,MATCH($B287,Devis!$A$2:$A$3053,0)),"") | S287: =IFERROR(INDEX(Clients!$G$2:$G$1020,MATCH($C287,Clients!$A$2:$A$1020,0)),"") | T287: =1 | U287: =IFERROR(INDEX(Interventions!$S$2:$S$1106,MATCH($B287,Interventions!$B$2:$B$1106,0)),0) | V287: =$K287-$U287 | W287: =IF($O287="",0,1) | X287: =IF($O287="",$M287,0) | Y287: =IF($O287="",MAX(0,Paramètres!$C$8-$I287),MAX(0,$O287-$I287)) | Z287: =$Y287*$X287 | AA287: =IF($O287="",0,$O287-$F287) | AB287: =IF(AND($O287="",$I287<Paramètres!$C$8),1,0) | AC287: =IF(AND($O287="",$Y287>Paramètres!$C$13),1,0) | AD287: =IF($O287="","",YEAR($O287)&"-"&TEXT(MONTH($O287),"00")) | AE287: =IF($W287=1,"Réglée",IF($Y287<=0,"Non échu",IF($Y287<=30,"1-30 j",IF($Y287<=60,"31-60 j",IF($Y287<=90,"61-90 j","Plus de 90 j"))))) | AF287: =IF($K287<=1000,"Moins de 1 k€",IF($K287<=5000,"1 à 5 k€",IF($K287<=15000,"5 à 15 k€","Plus de 15 k€")))
A288: FAC-00287 | B288: DEV-00677 | C288: CLI-0342 | D288: Particulier | E288: Toulouse | F288: 45285 | G288: 2023-12 | H288: 2023-2024 | I288: 45300 | J288: 15 | K288: 413.78 | L288: 0.2 | M288: 496.54 | N288: Bon payeur | O288: 45302 | P288: Payée | Q288: =IFERROR(INDEX(Devis!$I$2:$I$3053,MATCH($B288,Devis!$A$2:$A$3053,0)),"") | R288: =IFERROR(INDEX(Devis!$K$2:$K$3053,MATCH($B288,Devis!$A$2:$A$3053,0)),"") | S288: =IFERROR(INDEX(Clients!$G$2:$G$1020,MATCH($C288,Clients!$A$2:$A$1020,0)),"") | T288: =1 | U288: =IFERROR(INDEX(Interventions!$S$2:$S$1106,MATCH($B288,Interventions!$B$2:$B$1106,0)),0) | V288: =$K288-$U288 | W288: =IF($O288="",0,1) | X288: =IF($O288="",$M288,0) | Y288: =IF($O288="",MAX(0,Paramètres!$C$8-$I288),MAX(0,$O288-$I288)) | Z288: =$Y288*$X288 | AA288: =IF($O288="",0,$O288-$F288) | AB288: =IF(AND($O288="",$I288<Paramètres!$C$8),1,0) | AC288: =IF(AND($O288="",$Y288>Paramètres!$C$13),1,0) | AD288: =IF($O288="","",YEAR($O288)&"-"&TEXT(MONTH($O288),"00")) | AE288: =IF($W288=1,"Réglée",IF($Y288<=0,"Non échu",IF($Y288<=30,"1-30 j",IF($Y288<=60,"31-60 j",IF($Y288<=90,"61-90 j","Plus de 90 j"))))) | AF288: =IF($K288<=1000,"Moins de 1 k€",IF($K288<=5000,"1 à 5 k€",IF($K288<=15000,"5 à 15 k€","Plus de 15 k€")))
A289: FAC-00288 | B289: DEV-00679 | C289: CLI-0079 | D289: Particulier | E289: Bordeaux | F289: 45285 | G289: 2023-12 | H289: 2023-2024 | I289: 45300 | J289: 15 | K289: 1288.4 | L289: 0.1 | M289: 1417.24 | N289: Standard | O289: 45322 | P289: Payée | Q289: =IFERROR(INDEX(Devis!$I$2:$I$3053,MATCH($B289,Devis!$A$2:$A$3053,0)),"") | R289: =IFERROR(INDEX(Devis!$K$2:$K$3053,MATCH($B289,Devis!$A$2:$A$3053,0)),"") | S289: =IFERROR(INDEX(Clients!$G$2:$G$1020,MATCH($C289,Clients!$A$2:$A$1020,0)),"") | T289: =1 | U289: =IFERROR(INDEX(Interventions!$S$2:$S$1106,MATCH($B289,Interventions!$B$2:$B$1106,0)),0) | V289: =$K289-$U289 | W289: =IF($O289="",0,1) | X289: =IF($O289="",$M289,0) | Y289: =IF($O289="",MAX(0,Paramètres!$C$8-$I289),MAX(0,$O289-$I289)) | Z289: =$Y289*$X289 | AA289: =IF($O289="",0,$O289-$F289) | AB289: =IF(AND($O289="",$I289<Paramètres!$C$8),1,0) | AC289: =IF(AND($O289="",$Y289>Paramètres!$C$13),1,0) | AD289: =IF($O289="","",YEAR($O289)&"-"&TEXT(MONTH($O289),"00")) | AE289: =IF($W289=1,"Réglée",IF($Y289<=0,"Non échu",IF($Y289<=30,"1-30 j",IF($Y289<=60,"31-60 j",IF($Y289<=90,"61-90 j","Plus de 90 j"))))) | AF289: =IF($K289<=1000,"Moins de 1 k€",IF($K289<=5000,"1 à 5 k€",IF($K289<=15000,"5 à 15 k€","Plus de 15 k€")))
A290: FAC-00289 | B290: DEV-00681 | C290: CLI-0274 | D290: Particulier | E290: Bordeaux | F290: 45244 | G290: 2023-11 | H290: 2023-2024 | I290: 45259 | J290: 15 | K290: 5563.15 | L290: 0.1 | M290: 6119.47 | N290: Bon payeur | O290: 45246 | P290: Payée | Q290: =IFERROR(INDEX(Devis!$I$2:$I$3053,MATCH($B290,Devis!$A$2:$A$3053,0)),"") | R290: =IFERROR(INDEX(Devis!$K$2:$K$3053,MATCH($B290,Devis!$A$2:$A$3053,0)),"") | S290: =IFERROR(INDEX(Clients!$G$2:$G$1020,MATCH($C290,Clients!$A$2:$A$1020,0)),"") | T290: =1 | U290: =IFERROR(INDEX(Interventions!$S$2:$S$1106,MATCH($B290,Interventions!$B$2:$B$1106,0)),0) | V290: =$K290-$U290 | W290: =IF($O290="",0,1) | X290: =IF($O290="",$M290,0) | Y290: =IF($O290="",MAX(0,Paramètres!$C$8-$I290),MAX(0,$O290-$I290)) | Z290: =$Y290*$X290 | AA290: =IF($O290="",0,$O290-$F290) | AB290: =IF(AND($O290="",$I290<Paramètres!$C$8),1,0) | AC290: =IF(AND($O290="",$Y290>Paramètres!$C$13),1,0) | AD290: =IF($O290="","",YEAR($O290)&"-"&TEXT(MONTH($O290),"00")) | AE290: =IF($W290=1,"Réglée",IF($Y290<=0,"Non échu",IF($Y290<=30,"1-30 j",IF($Y290<=60,"31-60 j",IF($Y290<=90,"61-90 j","Plus de 90 j"))))) | AF290: =IF($K290<=1000,"Moins de 1 k€",IF($K290<=5000,"1 à 5 k€",IF($K290<=15000,"5 à 15 k€","Plus de 15 k€")))
A291: FAC-00290 | B291: DEV-00682 | C291: CLI-0261 | D291: Particulier | E291: Toulouse | F291: 45236 | G291: 2023-11 | H291: 2023-2024 | I291: 45251 | J291: 15 | K291: 4082.21 | L291: 0.1 | M291: 4490.43 | N291: Standard | O291: 45258 | P291: Payée | Q291: =IFERROR(INDEX(Devis!$I$2:$I$3053,MATCH($B291,Devis!$A$2:$A$3053,0)),"") | R291: =IFERROR(INDEX(Devis!$K$2:$K$3053,MATCH($B291,Devis!$A$2:$A$3053,0)),"") | S291: =IFERROR(INDEX(Clients!$G$2:$G$1020,MATCH($C291,Clients!$A$2:$A$1020,0)),"") | T291: =1 | U291: =IFERROR(INDEX(Interventions!$S$2:$S$1106,MATCH($B291,Interventions!$B$2:$B$1106,0)),0) | V291: =$K291-$U291 | W291: =IF($O291="",0,1) | X291: =IF($O291="",$M291,0) | Y291: =IF($O291="",MAX(0,Paramètres!$C$8-$I291),MAX(0,$O291-$I291)) | Z291: =$Y291*$X291 | AA291: =IF($O291="",0,$O291-$F291) | AB291: =IF(AND($O291="",$I291<Paramètres!$C$8),1,0) | AC291: =IF(AND($O291="",$Y291>Paramètres!$C$13),1,0) | AD291: =IF($O291="","",YEAR($O291)&"-"&TEXT(MONTH($O291),"00")) | AE291: =IF($W291=1,"Réglée",IF($Y291<=0,"Non échu",IF($Y291<=30,"1-30 j",IF($Y291<=60,"31-60 j",IF($Y291<=90,"61-90 j","Plus de 90 j"))))) | AF291: =IF($K291<=1000,"Moins de 1 k€",IF($K291<=5000,"1 à 5 k€",IF($K291<=15000,"5 à 15 k€","Plus de 15 k€")))
A292: FAC-00291 | B292: DEV-00683 | C292: CLI-0364 | D292: Particulier | E292: Bordeaux | F292: 45268 | G292: 2023-12 | H292: 2023-2024 | I292: 45283 | J292: 15 | K292: 1344.69 | L292: 0.1 | M292: 1479.16 | N292: Standard | O292: 45292 | P292: Payée | Q292: =IFERROR(INDEX(Devis!$I$2:$I$3053,MATCH($B292,Devis!$A$2:$A$3053,0)),"") | R292: =IFERROR(INDEX(Devis!$K$2:$K$3053,MATCH($B292,Devis!$A$2:$A$3053,0)),"") | S292: =IFERROR(INDEX(Clients!$G$2:$G$1020,MATCH($C292,Clients!$A$2:$A$1020,0)),"") | T292: =1 | U292: =IFERROR(INDEX(Interventions!$S$2:$S$1106,MATCH($B292,Interventions!$B$2:$B$1106,0)),0) | V292: =$K292-$U292 | W292: =IF($O292="",0,1) | X292: =IF($O292="",$M292,0) | Y292: =IF($O292="",MAX(0,Paramètres!$C$8-$I292),MAX(0,$O292-$I292)) | Z292: =$Y292*$X292 | AA292: =IF($O292="",0,$O292-$F292) | AB292: =IF(AND($O292="",$I292<Paramètres!$C$8),1,0) | AC292: =IF(AND($O292="",$Y292>Paramètres!$C$13),1,0) | AD292: =IF($O292="","",YEAR($O292)&"-"&TEXT(MONTH($O292),"00")) | AE292: =IF($W292=1,"Réglée",IF($Y292<=0,"Non échu",IF($Y292<=30,"1-30 j",IF($Y292<=60,"31-60 j",IF($Y292<=90,"61-90 j","Plus de 90 j"))))) | AF292: =IF($K292<=1000,"Moins de 1 k€",IF($K292<=5000,"1 à 5 k€",IF($K292<=15000,"5 à 15 k€","Plus de 15 k€")))
... A353: FAC-00352 | B353: DEV-00817 | C353: CLI-0152 | D353: Particulier | E353: Bordeaux | F353: 45356 | G353: 2024-03 | H353: 2023-2024 | I353: 45371 | J353: 15 | K353: 10851.81 | L353: 0.1 | M353: 11936.99 | N353: Standard | O353: 45410 | P353: Payée | Q353: =IFERROR(INDEX(Devis!$I$2:$I$3053,MATCH($B353,Devis!$A$2:$A$3053,0)),"") | R353: =IFERROR(INDEX(Devis!$K$2:$K$3053,MATCH($B353,Devis!$A$2:$A$3053,0)),"") | S353: =IFERROR(INDEX(Clients!$G$2:$G$1020,MATCH($C353,Clients!$A$2:$A$1020,0)),"") | T353: =1 | U353: =IFERROR(INDEX(Interventions!$S$2:$S$1106,MATCH($B353,Interventions!$B$2:$B$1106,0)),0) | V353: =$K353-$U353 | W353: =IF($O353="",0,1) | X353: =IF($O353="",$M353,0) | Y353: =IF($O353="",MAX(0,Paramètres!$C$8-$I353),MAX(0,$O353-$I353)) | Z353: =$Y353*$X353 | AA353: =IF($O353="",0,$O353-$F353) | AB353: =IF(AND($O353="",$I353<Paramètres!$C$8),1,0) | AC353: =IF(AND($O353="",$Y353>Paramètres!$C$13),1,0) | AD353: =IF($O353="","",YEAR($O353)&"-"&TEXT(MONTH($O353),"00")) | AE353: =IF($W353=1,"Réglée",IF($Y353<=0,"Non échu",IF($Y353<=30,"1-30 j",IF($Y353<=60,"31-60 j",IF($Y353<=90,"61-90 j","Plus de 90 j"))))) | AF353: =IF($K353<=1000,"Moins de 1 k€",IF($K353<=5000,"1 à 5 k€",IF($K353<=15000,"5 à 15 k€","Plus de 15 k€")))
A354: FAC-00353 | B354: DEV-00818 | C354: CLI-0147 | D354: Particulier | E354: Bordeaux | F354: 45358 | G354: 2024-03 | H354: 2023-2024 | I354: 45373 | J354: 15 | K354: 263.68 | L354: 0.2 | M354: 316.42 | N354: Litigieux | P354: En retard | Q354: =IFERROR(INDEX(Devis!$I$2:$I$3053,MATCH($B354,Devis!$A$2:$A$3053,0)),"") | R354: =IFERROR(INDEX(Devis!$K$2:$K$3053,MATCH($B354,Devis!$A$2:$A$3053,0)),"") | S354: =IFERROR(INDEX(Clients!$G$2:$G$1020,MATCH($C354,Clients!$A$2:$A$1020,0)),"") | T354: =1 | U354: =IFERROR(INDEX(Interventions!$S$2:$S$1106,MATCH($B354,Interventions!$B$2:$B$1106,0)),0) | V354: =$K354-$U354 | W354: =IF($O354="",0,1) | X354: =IF($O354="",$M354,0) | Y354: =IF($O354="",MAX(0,Paramètres!$C$8-$I354),MAX(0,$O354-$I354)) | Z354: =$Y354*$X354 | AA354: =IF($O354="",0,$O354-$F354) | AB354: =IF(AND($O354="",$I354<Paramètres!$C$8),1,0) | AC354: =IF(AND($O354="",$Y354>Paramètres!$C$13),1,0) | AD354: =IF($O354="","",YEAR($O354)&"-"&TEXT(MONTH($O354),"00")) | AE354: =IF($W354=1,"Réglée",IF($Y354<=0,"Non échu",IF($Y354<=30,"1-30 j",IF($Y354<=60,"31-60 j",IF($Y354<=90,"61-90 j","Plus de 90 j"))))) | AF354: =IF($K354<=1000,"Moins de 1 k€",IF($K354<=5000,"1 à 5 k€",IF($K354<=15000,"5 à 15 k€","Plus de 15 k€")))
A355: FAC-00354 | B355: DEV-00819 | C355: CLI-0355 | D355: Particulier | E355: Bordeaux | F355: 45334 | G355: 2024-02 | H355: 2023-2024 | I355: 45349 | J355: 15 | K355: 2983.75 | L355: 0.1 | M355: 3282.13 | N355: Bon payeur | O355: 45335 | P355: Payée | Q355: =IFERROR(INDEX(Devis!$I$2:$I$3053,MATCH($B355,Devis!$A$2:$A$3053,0)),"") | R355: =IFERROR(INDEX(Devis!$K$2:$K$3053,MATCH($B355,Devis!$A$2:$A$3053,0)),"") | S355: =IFERROR(INDEX(Clients!$G$2:$G$1020,MATCH($C355,Clients!$A$2:$A$1020,0)),"") | T355: =1 | U355: =IFERROR(INDEX(Interventions!$S$2:$S$1106,MATCH($B355,Interventions!$B$2:$B$1106,0)),0) | V355: =$K355-$U355 | W355: =IF($O355="",0,1) | X355: =IF($O355="",$M355,0) | Y355: =IF($O355="",MAX(0,Paramètres!$C$8-$I355),MAX(0,$O355-$I355)) | Z355: =$Y355*$X355 | AA355: =IF($O355="",0,$O355-$F355) | AB355: =IF(AND($O355="",$I355<Paramètres!$C$8),1,0) | AC355: =IF(AND($O355="",$Y355>Paramètres!$C$13),1,0) | AD355: =IF($O355="","",YEAR($O355)&"-"&TEXT(MONTH($O355),"00")) | AE355: =IF($W355=1,"Réglée",IF($Y355<=0,"Non échu",IF($Y355<=30,"1-30 j",IF($Y355<=60,"31-60 j",IF($Y355<=90,"61-90 j","Plus de 90 j"))))) | AF355: =IF($K355<=1000,"Moins de 1 k€",IF($K355<=5000,"1 à 5 k€",IF($K355<=15000,"5 à 15 k€","Plus de 15 k€")))
A356: FAC-00355 | B356: DEV-00820 | C356: CLI-0331 | D356: Particulier | E356: Bordeaux | F356: 45356 | G356: 2024-03 | H356: 2023-2024 | I356: 45371 | J356: 15 | K356: 13193.36 | L356: 0.1 | M356: 14512.7 | N356: Standard | O356: 45371 | P356: Payée | Q356: =IFERROR(INDEX(Devis!$I$2:$I$3053,MATCH($B356,Devis!$A$2:$A$3053,0)),"") | R356: =IFERROR(INDEX(Devis!$K$2:$K$3053,MATCH($B356,Devis!$A$2:$A$3053,0)),"") | S356: =IFERROR(INDEX(Clients!$G$2:$G$1020,MATCH($C356,Clients!$A$2:$A$1020,0)),"") | T356: =1 | U356: =IFERROR(INDEX(Interventions!$S$2:$S$1106,MATCH($B356,Interventions!$B$2:$B$1106,0)),0) | V356: =$K356-$U356 | W356: =IF($O356="",0,1) | X356: =IF($O356="",$M356,0) | Y356: =IF($O356="",MAX(0,Paramètres!$C$8-$I356),MAX(0,$O356-$I356)) | Z356: =$Y356*$X356 | AA356: =IF($O356="",0,$O356-$F356) | AB356: =IF(AND($O356="",$I356<Paramètres!$C$8),1,0) | AC356: =IF(AND($O356="",$Y356>Paramètres!$C$13),1,0) | AD356: =IF($O356="","",YEAR($O356)&"-"&TEXT(MONTH($O356),"00")) | AE356: =IF($W356=1,"Réglée",IF($Y356<=0,"Non échu",IF($Y356<=30,"1-30 j",IF($Y356<=60,"31-60 j",IF($Y356<=90,"61-90 j","Plus de 90 j"))))) | AF356: =IF($K356<=1000,"Moins de 1 k€",IF($K356<=5000,"1 à 5 k€",IF($K356<=15000,"5 à 15 k€","Plus de 15 k€")))
A357: FAC-00356 | B357: DEV-00821 | C357: CLI-0029 | D357: Particulier | E357: Bordeaux | F357: 45362 | G357: 2024-03 | H357: 2023-2024 | I357: 45377 | J357: 15 | K357: 706.88 | L357: 0.1 | M357: 777.57 | N357: Standard | O357: 45363 | P357: Payée | Q357: =IFERROR(INDEX(Devis!$I$2:$I$3053,MATCH($B357,Devis!$A$2:$A$3053,0)),"") | R357: =IFERROR(INDEX(Devis!$K$2:$K$3053,MATCH($B357,Devis!$A$2:$A$3053,0)),"") | S357: =IFERROR(INDEX(Clients!$G$2:$G$1020,MATCH($C357,Clients!$A$2:$A$1020,0)),"") | T357: =1 | U357: =IFERROR(INDEX(Interventions!$S$2:$S$1106,MATCH($B357,Interventions!$B$2:$B$1106,0)),0) | V357: =$K357-$U357 | W357: =IF($O357="",0,1) | X357: =IF($O357="",$M357,0) | Y357: =IF($O357="",MAX(0,Paramètres!$C$8-$I357),MAX(0,$O357-$I357)) | Z357: =$Y357*$X357 | AA357: =IF($O357="",0,$O357-$F357) | AB357: =IF(AND($O357="",$I357<Paramètres!$C$8),1,0) | AC357: =IF(AND($O357="",$Y357>Paramètres!$C$13),1,0) | AD357: =IF($O357="","",YEAR($O357)&"-"&TEXT(MONTH($O357),"00")) | AE357: =IF($W357=1,"Réglée",IF($Y357<=0,"Non échu",IF($Y357<=30,"1-30 j",IF($Y357<=60,"31-60 j",IF($Y357<=90,"61-90 j","Plus de 90 j"))))) | AF357: =IF($K357<=1000,"Moins de 1 k€",IF($K357<=5000,"1 à 5 k€",IF($K357<=15000,"5 à 15 k€","Plus de 15 k€")))
A358: FAC-00357 | B358: DEV-00823 | C358: CLI-0034 | D358: Particulier | E358: Toulouse | F358: 45365 | G358: 2024-03 | H358: 2023-2024 | I358: 45380 | J358: 15 | K358: 474.56 | L358: 0.1 | M358: 522.02 | N358: Bon payeur | O358: 45366 | P358: Payée | Q358: =IFERROR(INDEX(Devis!$I$2:$I$3053,MATCH($B358,Devis!$A$2:$A$3053,0)),"") | R358: =IFERROR(INDEX(Devis!$K$2:$K$3053,MATCH($B358,Devis!$A$2:$A$3053,0)),"") | S358: =IFERROR(INDEX(Clients!$G$2:$G$1020,MATCH($C358,Clients!$A$2:$A$1020,0)),"") | T358: =1 | U358: =IFERROR(INDEX(Interventions!$S$2:$S$1106,MATCH($B358,Interventions!$B$2:$B$1106,0)),0) | V358: =$K358-$U358 | W358: =IF($O358="",0,1) | X358: =IF($O358="",$M358,0) | Y358: =IF($O358="",MAX(0,Paramètres!$C$8-$I358),MAX(0,$O358-$I358)) | Z358: =$Y358*$X358 | AA358: =IF($O358="",0,$O358-$F358) | AB358: =IF(AND($O358="",$I358<Paramètres!$C$8),1,0) | AC358: =IF(AND($O358="",$Y358>Paramètres!$C$13),1,0) | AD358: =IF($O358="","",YEAR($O358)&"-"&TEXT(MONTH($O358),"00")) | AE358: =IF($W358=1,"Réglée",IF($Y358<=0,"Non échu",IF($Y358<=30,"1-30 j",IF($Y358<=60,"31-60 j",IF($Y358<=90,"61-90 j","Plus de 90 j"))))) | AF358: =IF($K358<=1000,"Moins de 1 k€",IF($K358<=5000,"1 à 5 k€",IF($K358<=15000,"5 à 15 k€","Plus de 15 k€")))
A359: FAC-00358 | B359: DEV-00824 | C359: CLI-0384 | D359: Particulier | E359: Toulouse | F359: 45348 | G359: 2024-02 | H359: 2023-2024 | I359: 45363 | J359: 15 | K359: 1244.28 | L359: 0.1 | M359: 1368.71 | N359: Standard | O359: 45384 | P359: Payée | Q359: =IFERROR(INDEX(Devis!$I$2:$I$3053,MATCH($B359,Devis!$A$2:$A$3053,0)),"") | R359: =IFERROR(INDEX(Devis!$K$2:$K$3053,MATCH($B359,Devis!$A$2:$A$3053,0)),"") | S359: =IFERROR(INDEX(Clients!$G$2:$G$1020,MATCH($C359,Clients!$A$2:$A$1020,0)),"") | T359: =1 | U359: =IFERROR(INDEX(Interventions!$S$2:$S$1106,MATCH($B359,Interventions!$B$2:$B$1106,0)),0) | V359: =$K359-$U359 | W359: =IF($O359="",0,1) | X359: =IF($O359="",$M359,0) | Y359: =IF($O359="",MAX(0,Paramètres!$C$8-$I359),MAX(0,$O359-$I359)) | Z359: =$Y359*$X359 | AA359: =IF($O359="",0,$O359-$F359) | AB359: =IF(AND($O359="",$I359<Paramètres!$C$8),1,0) | AC359: =IF(AND($O359="",$Y359>Paramètres!$C$13),1,0) | AD359: =IF($O359="","",YEAR($O359)&"-"&TEXT(MONTH($O359),"00")) | AE359: =IF($W359=1,"Réglée",IF($Y359<=0,"Non échu",IF($Y359<=30,"1-30 j",IF($Y359<=60,"31-60 j",IF($Y359<=90,"61-90 j","Plus de 90 j"))))) | AF359: =IF($K359<=1000,"Moins de 1 k€",IF($K359<=5000,"1 à 5 k€",IF($K359<=15000,"5 à 15 k€","Plus de 15 k€")))
